Workbook
Name _: #REF!
Name _______kjnjknv: #REF!
Name _______kjnjknv: #REF!
Name _______kjnjknv: #REF!
Name _______kjnjknv: #REF!
Name _______kjnjknv: #REF!
Name _______kjnjknv: #REF!
Name _______kjnjknv: #REF!
Name _______kjnjknv: #REF!
Name _______kjnjknv: #REF!
Name _______kjnjknv: #REF!
Name _______kjnjknv: #REF!
Name _______kjnjknv: #REF!
Name _______kjnjknv: #REF!
Name _______kjnjknv: #REF!
Name _______kjnjknv: #REF!
Name _______kjnjknv: #REF!
Name ___ms4: '[1]Legend 2'!$B$16:$B$35
Name ___ms4: '[1]Legend 2'!$B$16:$B$35
Name ___ms4: #REF!
Name __ms4: '[1]Legend 2'!$B$16:$B$35
Name __ms4: '[1]Legend 2'!$B$16:$B$35
Name __ms4: #REF!
Name _jkk: #REF!
Name _ms4: '[1]Legend 2'!$B$16:$B$35
Name _ms4: '[1]Legend 2'!$B$16:$B$35
Name _ms4: #REF!
Name _ReplyAwaited: #REF!
Name _ReplyAwaited: #REF!
Name _ReplyAwaited: #REF!
Name _ReplyAwaited: #REF!
Name _ReplyAwaited: #REF!
Name _ReplyAwaited: #REF!
Name _ReplyAwaited: #REF!
Name _ReplyAwaited: #REF!
Name _ReplyAwaited: #REF!
Name _ReplyAwaited: #REF!
Name _ReplyAwaited: #REF!
Name _ReplyAwaited: #REF!
Name _ReplyAwaited: #REF!
Name aa: #REF!
Name aa: #REF!
Name aa: #REF!
Name aa: #REF!
Name aa: #REF!
Name aa: #REF!
Name aa: #REF!
Name aa: #REF!
Name aa: #REF!
Name aa: #REF!
Name aa: #REF!
Name aa: #REF!
Name aa: #REF!
Name aa: #REF!
Name aa: #REF!
Name aa: #REF!
Name aa: #REF!
Name aa: #REF!
Name aa: #REF!
Name aa: #REF!

Sheet Title Page

Sheet Content
C10: Table of Contents – RTD Ice Tea – France, Netherlands and Portugal
A33: Copyright © 2025 WNS (Holdings) Ltd. All rights reserved.

Sheet Objective, Scope and Approach
B5: Objective and Scope
B7: To develop a process should cost model for RTD Ice Tea in France, Netherlands and Portugal
B9: Approach
B12: – Carried out secondary research to form an initial understanding of the RTD Ice Tea production and packaging process and obtained information about the key steps involved – Studied documents such as research papers, news articles, company websites, and company information and presentations and viewed videos on YouTube to further understand the process – Undertook extensive secondary research to identify relevant stakeholders such as machinery suppliers, equipment suppliers and industry experts | D12: – Carried out secondary and primary research to understand the associated cost heads – Conducted interviews with industry experts, along with expert to understand key operational procedures followed in a plant, along with product dimensions, packaging quantity, and other specifications – Conducted extensive primary research to source information on the prices of machineries by contacting machinery suppliers – Studied annual report of manufacturers to validate information on the fixed and variable costs associated with RTD Ice Tea and packaging | F12: – Synthesized the findings obtained from secondary and primary research sources to develop the cost model – Extracted relevant insights regarding various cost heads – Highlighted the assumptions and benchmarks that were considered to build the cost model
A14: Copyright © 2025 WNS (Holdings) Ltd. All rights reserved.
B18: Plant Building, Installation, and Other Infrastructure Cost

Sheet Production Process
B5: Production Process – RTD Ice Tea
B126: Note: The production process is based on information available through secondary research sources and has been validated through interviews with industry participants
A128: Copyright © 2025 WNS (Holdings) Ltd. All rights reserved.

Sheet Input Sheet
B5: General information about the CM
B6: Key Parameters | C6: Sub-parameters | D6: Input Cells | E6: Units
B7: Number of Production Lines | D7: 1
B8: Production Info | C8: Number of Shifts/day (France) | D8: 3 | E8: Shifts/day
C9: Number of Shifts/day (Netherlands) | D9: 3 | E9: Shifts/day
C10: Number of Shifts/day (Portugal) | D10: 3 | E10: Shifts/day
C11: Number of Shifts/day (Country B) | D11: 3 | E11: Shifts/day
C12: Working Hours per Shift (France) | D12: 8 | E12: Hours/shift
C13: Working Hours per Shift (Netherlands) | D13: 8 | E13: Hours/shift
C14: Working Hours per Shift (Portugal) | D14: 8 | E14: Hours/shift
C15: Working Hours per Shift (Country B) | D15: 8 | E15: Hours/shift
C16: Total Working Days/year (France) | D16: 330 | E16: Days/year
C17: Total Working Days/year (Netherlands) | D17: 320 | E17: Days/year
C18: Total Working Days/year (Portugal) | D18: 310 | E18: Days/year
C19: Total Working Days/year (Country B) | D19: 330 | E19: Days/year
B20: Plant Details and Capex | C20: Construction Rate – France | D20: 1330 | E20: €/sqm
C21: Construction Rate – Netherlands | D21: 1220 | E21: €/sqm
C22: Construction Rate – Portugal | D22: 1429 | E22: €/sqm
C23: Construction Rate – Country B | D23: 1119 | E23: €/sqm
C24: Industrial Land Rate – France | D24: 80 | E24: €/sqm
C25: Industrial Land Rate – Netherlands | D25: 90 | E25: €/sqm
C26: Industrial Land Rate – Portugal | D26: 65 | E26: €/sqm
C27: Industrial Land Rate – Country B | D27: 18 | E27: €/sqm
C28: Total Plant Area3 | D28: 15000 | E28: sq. m
B29: Utility Costs | C29: Electricity – France | D29: 0.15825473 | E29: €/kWh
C30: Electricity – Netherlands | D30: 0.1578283 | E30: €/kWh
C31: Electricity – Portugal | D31: 0.13 | E31: €/kWh
C32: Electricity – Country B | D32: 0.15 | E32: €/kWh
C33: Natural Gas – France | D33: 0.076756443 | E33: €/kWh
C34: Natural Gas – Netherlands | D34: 0.076756443 | E34: €/kWh
C35: Natural Gas – Portugal | D35: 0.1 | E35: €/kWh
C36: Natural Gas – Country B | D36: 0.07 | E36: €/kWh
C37: Industrial Steam – France | D37: 68.5 | E37: €/MT
C38: Industrial Steam – Netherlands | D38: 68 | E38: €/MT
C39: Industrial Steam – Portugal | D39: 39.5 | E39: €/MT
C40: Industrial Steam – Country B | D40: 68.64 | E40: €/MT
C41: Boiler Feed Water – France | D41: 30 | E41: €/MT
... C52: Other Utilities – Country B | D52: 0.15 | E52: of Total Electricity Cost
B53: Other Costs | C53: Selling, General and Administrative Costs | D53: 0.6 | E53: of total process cost
C54: Other Depreciation Costs | D54: 0.033333333 | E54: of non-machinery cost
C55: Finance Cost | D55: 0.0342 | E55: of total equipment and infrastructure cost
C56: Others (tax, insurance, and other expenses) | D56: 0.05 | E56: of total process cost
B57: Scale of Production | C57: Small-scale | D57: 150 | E57: MT per day
C58: Medium-scale | D58: 200 | E58: MT per day
C59: Large Scale | D59: 250 | E59: MT per day
B60: Site Complexity | C60: Low | D60: 4 | E60: Number of Product Changeovers/line/week
C61: Medium | D61: 8 | E61: Number of Product Changeovers/line/week
C62: Large | D62: 12 | E62: Number of Product Changeovers/line/week
C63: Working Hours/Day | D63: 8 | E63: Hours/Day
C64: Working Days/Week | D64: 6 | E64: Days/Week
C65: Working Weeks/Year | D65: 50 | E65: Weeks.Year
B66: Labour Data | C66: Production Manager – France | D66: 138540 | E66: Annual Salary (€)
C67: Shift Supervisor – France | D67: 68895.8 | E67: Annual Salary (€)
C68: Production Workers – France | D68: 42905 | E68: Annual Salary (€)
C69: Equipment Operator – France | D69: 40899 | E69: Annual Salary (€)
C70: Wage Increment – France | D70: 0.03 | E70: 2024-2025
C71: Average US Manufacturing Wages | D71: 31738 | E71: Annual Salary (€)
C72: Average France Manufacturing Wages | D72: 28564 | E72: Annual Salary (€)
C73: Employee Other Benefits – France | D73: 0.077 | E73: of Direct Labour Cost
C74: Management Overheads – France | D74: 0.05 | E74: of Direct Labour Cost and Employee Benefits
C75: Working Hours/Day | D75: 8 | E75: Hours/Day
C76: Working Days/Week | D76: 6 | E76: Days/Week
C77: Working Weeks/Year | D77: 50 | E77: Weeks.Year
C78: Production Manager – Netherlands | D78: 138540 | E78: Annual Salary (€)
... C110: Management Overheads – Country B | D110: 0.08 | E110: of Direct Labour Cost and Employee Benefits
B112: Equipment Data | D112: Semi-Automatic Equipment | E112: Fully-Automatic Equipment
C113: Reverse Osmosis Water Treatement Machine | D113: 94000 | E113: 112000
C114: Jacket Mixing Tank with High Shear Mixer | D114: 12000 | E114: 136000
C115: Pressure Blending Tanks | D115: 80000 | E115: 94000
C116: Pasteuriser | D116: 163000 | E116: 175000
C117: Carbonation Maker | D117: 26000 | E117: 28600
C118: Preform Steriliser | D118: 29000 | E118: 35000
C119: Air Jet and Vacuum Cleaning Machines | D119: 19500 | E119: 24000
C120: PET Bottle Blowing Machine | D120: 52000 | E120: 55000
C121: PET Bottle Washing and Rinsing Machine | D121: 15000 | E121: 19000
C122: Can Filling and Sealing Machine | D122: 78000 | E122: 90000
C123: Aseptic Liquid Filling and Capping Machine | D123: 56000 | E123: 65000
C124: Nitrogen Injection System | D124: 26000 | E124: 29000
... C129: Palletiser Machine | D129: 22000 | E129: 27000
C130: Product Changeover Time (hours per batch) | D130: 1.5 | E130: Hours/Batch
C131: Cleaning and Maintenance Time (hour per batch) | D131: 0.5 | E131: Hours/Batch
B134: Detailed information at a Process level
B135: Phase | C135: Process | D135: Variables | E135: Data - Semi Automatic Machine | F135: Data - Fully Automatic Machine | G135: Unit
B136: Production | C136: Water Treatment | D136: Number of Equipment Installed | E136: 1 | F136: 1 | G136: Unit
D137: Installed Capacity of Equipment | E137: 1000 | F137: 1100 | G137: Kgs/Cycle
D138: Time Taken by Machine per Cycle | E138: 0.35 | F138: 0.25 | G138: Hours
D139: Loading/Unloading Time per Cycle | E139: 0.06 | F139: 0.05 | G139: Hours
D140: Equipment Depreciation Rate | E140: 0.1 | F140: 0.1 | G140: %
D141: Wastage Rate | E141: 0.01 | F141: 0.01 | G141: %
D142: No. of Production Manager | E142: 1 | F142: 1 | G142: Unit
D143: No. of Shift Supervisor | E143: 1 | F143: 1 | G143: Unit
D144: No. of Machine Operator | E144: 1 | F144: 1 | G144: Unit
D145: No. of Production Worker | E145: 1 | F145: 1 | G145: Unit
D146: Contribution Factor of Production Manager | E146: 0.03 | F146: 0.03 | G146: %
D147: Contribution Factor of Shift Supervisor | E147: 0.05 | F147: 0.05 | G147: %
D148: Contribution Factor of Machine Operator | E148: 0.05 | F148: 0.05 | G148: %
D149: Contribution Factor of Production Worker | E149: 0.1 | F149: 0.1 | G149: %
C150: Syrup Preparation | D150: Number of Equipment Installed | E150: 1 | F150: 1 | G150: Unit
D151: Installed Capacity of Equipment | E151: 850 | F151: 900 | G151: Kgs/Cycle
D152: Time Taken by Machine per Cycle | E152: 0.35 | F152: 0.25 | G152: Hours
...

Sheet Part 1 - Summary

Sheet 1.1 Summary
E2: Bottles | F2: Multipack | G2: Tray | H2: Country | I2: Container Format | J2: Decontamination Process | K2: Product type
E3: 0.25 | F3: 4 | G3: 12 | H3: France | I3: PET Bottle | J3: Dry Aseptic | K3: Carbonated
E4: 0.33 | F4: 6 | G4: 24 | H4: Netherlands | I4: Can | J4: Wet Aseptic | K4: Non-Carbonated
B5: Summary – RTD Ice Tea | E5: 0.5 | F5: 8 | H5: Portugal
E6: 1 | F6: 12 | H6: Country B
B7: Indicates drop-down menu | C7: Indicates input cell | E7: 1.5 | R7: Vietnam
B8: Product Name | C8: RTD Ice Tea | E8: 2
B9: Production Country | C9: Netherlands
B10: Time Period | C10: December
B11: Currency | C11: EUR (€)
B12: RTD Ice Tea Machinery | C12: Fully-Automated | D12: << for machinery type | E12: Please click for definition | G12: Multipack | H12: Can
B13: Facility Type | C13: New | D13: << for facility type | E13: Please click for definition | G13: Tray
B14: Product Type | C14: Non-Carbonated | D14: << for product type
B15: SKU Packing Type | C15: PET Bottle | D15: << for packing type | I15: 4 | J15: 4*6
B16: SKU Size | C16: 2 | D16: << for Unit SKU Size
B17: Number of Units in Multipacks | C17: 6 | D17: << for Secondary Packaging | H17: Dry Aseptic | I17: 8 | J17: 8*3
B18: Tray Combination | C18: =IF(C17=4,"4*6",IF(C17=6,"6*4",IF(C17=8,"8*3",IF(C17=12,"12*2","24*1")))) -> 6*4 | D18: << for multipacks in a tray | H18: Wet Aseptic | I18: 12 | J18: 12*2
B19: PET Bottle Decontamination Process (For Can Packing, Select " – ") | C19: Dry Aseptic | D19: << for PET decontamination type | H19: –
B20: Scale of Production | C20: High-scale
B21: Site Complexity | C21: Low | D21: << for site complexity | E21: Please click for definition
B25: Cost Structure Summary – RTD Ice Tea
G26: =B25 -> Cost Structure Summary – RTD Ice Tea
B27: Parameters | C27: Cost Breakdown* | D27: Cost Breakdown (€/MT) | E27: Cost per Consumer/Unit Column
B28: Total Equipment Cost | C28: =D28/$D$32 -> 0.023571088 | D28: ='1.1 Summary'!D45+'1.1 Summary'!D77 -> 2.5086824 | E28: =D28/(1000/$C$16) -> 0.0050173647
B29: Total Utility Cost | C29: =D29/$D$32 -> 0.20057098 | D29: ='1.1 Summary'!D46+'1.1 Summary'!D78 -> 21.346868 | E29: =D29/(1000/$C$16) -> 0.042693736
B30: Total Labour Cost | C30: =D30/$D$32 -> 0.10901249 | D30: ='1.1 Summary'!D79+'1.1 Summary'!D47 -> 11.602253 | E30: =D30/(1000/$C$16) -> 0.023204505
B31: Total Overhead and Indirect Cost | C31: =D31/$D$32 -> 0.66684544 | D31: =D49+D81 -> 70.972686 | E31: =D31/(1000/$C$16) -> 0.14194537
B32: Total Production Cost | C32: =SUM(C28:C31) -> 1 | D32: =SUM(D28:D31) -> 106.43049 | E32: =D32/(1000/C16) -> 0.21286098
B35: Average Margins Earned by Supplier | C35: High | D35: =IF(C35="High",20%,IF(C35="Medium",15%,10%)) -> 0.2 | E35: Please click for definition
B36: Production Cost including Margin Earned by Supplier | D36: =(D35*D32)+D32 -> 127.71659
B38: Purchase Price (€/MT)
B40: Gap (€/MT) | D40: =IF(D38="","Please enter purchase price in cell D35",D38-D36) -> Please enter purchase price in cell D35
B42: Cost Breakdown – Processes – By Cost Type | G42: Cost Breakdown – Processes – By Processing Step
B44: Parameters | C44: Cost Breakdown* | D44: Cost Breakdown (€/MT) | G44: Parameters | H44: Cost Breakdown* | I44: Cost Breakdown (€/MT)
B45: Equipment Cost | C45: =D45/$D$48 -> 0.074455554 | D45: =IF('1.1 Summary'!C12="Semi-Automated",SUM('2.1 Cost Model Processes'!E12+'2.1 Cost Model Processes'!E30+'2.1 Cost Model Processes'!E48+'2.1 Cost Model Processes'!E67+'2.1 Cost Model Processes'!E86),SUM('2.1 Cost Model Processes'!I12+'2.1 Cost Model Processes'!I30+'2.1 Cost Model Processes'!I48+'2.1 Cost Model Processes'!I67+'2.1 Cost Model Processes'!I86)) -> 2.3012232 | G45: Water Treatment | H45: =I45/$I$50 -> 0.17075297 | I45: =IF(C12="Semi-Automated",'2.1 Cost Model Processes'!E25,'2.1 Cost Model Processes'!I25) -> 5.2775202
B46: Utility Cost | C46: =D46/$D$48 -> 0.6179917 | D46: =IF('1.1 Summary'!C12="Semi-Automated",SUM('2.1 Cost Model Processes'!E17+'2.1 Cost Model Processes'!E35+'2.1 Cost Model Processes'!E53+'2.1 Cost Model Processes'!E72+'2.1 Cost Model Processes'!E91),SUM('2.1 Cost Model Processes'!I17+'2.1 Cost Model Processes'!I35+'2.1 Cost Model Processes'!I53+'2.1 Cost Model Processes'!I72+'2.1 Cost Model Processes'!I91)) -> 19.10048 | G46: Syrup Preparation | H46: =I46/$I$50 -> 0.25464721 | I46: =IF(C12="Semi-Automated",'2.1 Cost Model Processes'!E43,'2.1 Cost Model Processes'!I43) -> 7.870468
B47: Labour Cost | C47: =D47/$D$48 -> 0.30755274 | D47: =IF('1.1 Summary'!C12="Semi-Automated",SUM('2.1 Cost Model Processes'!E24+'2.1 Cost Model Processes'!E42+'2.1 Cost Model Processes'!E60+'2.1 Cost Model Processes'!E79+'2.1 Cost Model Processes'!E98),SUM('2.1 Cost Model Processes'!I24+'2.1 Cost Model Processes'!I42+'2.1 Cost Model Processes'!I60+'2.1 Cost Model Processes'!I79+'2.1 Cost Model Processes'!I98)) -> 9.5056374 | G47: Carbonising | H47: =I47/$I$50 -> 0 | I47: =IF(C12="Semi-Automated",'2.1 Cost Model Processes'!E100,'2.1 Cost Model Processes'!I100) -> 0
B48: Total Production Cost | C48: =SUM(C45:C47) -> 1 | D48: =SUM(D45:D47) -> 30.907341 | G48: Mixing | H48: =I48/$I$50 -> 0.023815631 | I48: =IF(C12="Semi-Automated",'2.1 Cost Model Processes'!E62,'2.1 Cost Model Processes'!I62) -> 0.7360778
B49: Overheads and Indirect Cost for the Process | D49: =IF(C12="Semi-Automated",'2.1 Cost Model Processes'!E115,'2.1 Cost Model Processes'!I115) -> 58.85206 | G49: Pasteurising | H49: =I49/$I$50 -> 0.55078419 | I49: =IF($C$12="Semi-Automated",'2.1 Cost Model Processes'!E81,'2.1 Cost Model Processes'!I81) -> 17.023275
B50: Total Production Cost (including overheads and indirect cost) | D50: =D48+D49 -> 89.7594 | G50: Total Production Cost | H50: =SUM(H45:H49) -> 1 | I50: =SUM(I45:I49) -> 30.907341
B51: *Figures in the table and the corresponding graph may not add to 100.0% as the figures have been rounded off | G51: Overheads and Indirect Cost for the Process | I51: =IF(C12="Semi-Automated",'2.1 Cost Model Processes'!E115,'2.1 Cost Model Processes'!I115) -> 58.85206
G52: Total Production Cost (including overheads and indirect cost) | I52: =I50+I51 -> 89.7594
G54: *Figures in the table and the corresponding graph may not add to 100.0% as the figures have been rounded off | I54: `
B55: =B42 -> Cost Breakdown – Processes – By Cost Type
G56: Cost Breakdown – Processes – By Processing Step
B74: Cost Breakdown – Packing – By Cost Type
G75: Cost Breakdown – Packing – By Packing Step
B76: Parameters | C76: Cost Breakdown* | D76: Cost Breakdown (€/MT)
B77: Equipment Cost | C77: =D77/$D$80 -> 0.045590798 | D77: =IF($C$12="Semi-Automated",SUM('2.2 Cost Model Packing'!E12,'2.2 Cost Model Packing'!E32,'2.2 Cost Model Packing'!E51,'2.2 Cost Model Packing'!E70,'2.2 Cost Model Packing'!E89,'2.2 Cost Model Packing'!E108,'2.2 Cost Model Packing'!E127,'2.2 Cost Model Packing'!E146,'2.2 Cost Model Packing'!E165,'2.2 Cost Model Packing'!E184,'2.2 Cost Model Packing'!E203),SUM('2.2 Cost Model Packing'!I12,'2.2 Cost Model Packing'!I32,'2.2 Cost Model Packing'!I51,'2.2 Cost Model Packing'!I70,'2.2 Cost Model Packing'!I89,'2.2 Cost Model Packing'!I108,'2.2 Cost Model Packing'!I127,'2.2 Cost Model Packing'!I146,'2.2 Cost Model Packing'!I165,'2.2 Cost Model Packing'!I184,'2.2 Cost Model Packing'!I203)) -> 0.2074592 | G77: Parameters | H77: Cost Breakdown* | I77: Cost Breakdown (€/MT)
B78: Utility Cost | C78: =D78/$D$80 -> 0.49366146 | D78: =IF(C12="Semi-Automated",('2.2 Cost Model Packing'!E17+'2.2 Cost Model Packing'!E37+'2.2 Cost Model Packing'!E56+'2.2 Cost Model Packing'!E75+'2.2 Cost Model Packing'!E94+'2.2 Cost Model Packing'!E113+'2.2 Cost Model Packing'!E132+'2.2 Cost Model Packing'!E151+'2.2 Cost Model Packing'!E170+'2.2 Cost Model Packing'!E189+'2.2 Cost Model Packing'!E208),('2.2 Cost Model Packing'!I17+'2.2 Cost Model Packing'!I37+'2.2 Cost Model Packing'!I56+'2.2 Cost Model Packing'!I75+'2.2 Cost Model Packing'!I94+'2.2 Cost Model Packing'!I113+'2.2 Cost Model Packing'!I132+'2.2 Cost Model Packing'!I151+'2.2 Cost Model Packing'!I170+'2.2 Cost Model Packing'!I189+'2.2 Cost Model Packing'!I208)) -> 2.2463878 | G78: Dry Aseptic Cleaning | H78: =I78/$I$89 -> 0.13414721 | I78: =IF($C$12="Semi-Automated",'2.2 Cost Model Packing'!$E$26,'2.2 Cost Model Packing'!$I$26) -> 0.61043181
B79: Labour Cost | C79: =D79/$D$80 -> 0.46074774 | D79: =IF(C12="Semi-Automated",'2.2 Cost Model Packing'!E25+'2.2 Cost Model Packing'!E45+'2.2 Cost Model Packing'!E64+'2.2 Cost Model Packing'!E83+'2.2 Cost Model Packing'!E102+'2.2 Cost Model Packing'!E121+'2.2 Cost Model Packing'!E140+'2.2 Cost Model Packing'!E159+'2.2 Cost Model Packing'!E178+'2.2 Cost Model Packing'!E197+'2.2 Cost Model Packing'!E216,'2.2 Cost Model Packing'!I25+'2.2 Cost Model Packing'!I45+'2.2 Cost Model Packing'!I64+'2.2 Cost Model Packing'!I83+'2.2 Cost Model Packing'!I102+'2.2 Cost Model Packing'!I121+'2.2 Cost Model Packing'!I140+'2.2 Cost Model Packing'!I159+'2.2 Cost Model Packing'!I178+'2.2 Cost Model Packing'!I197+'2.2 Cost Model Packing'!I216) -> 2.0966151 | G79: PET Bottle Blowing | H79: =I79/$I$89 -> 0.29514834 | I79: =IF($C$12="Semi-Automated",'2.2 Cost Model Packing'!$E$46,'2.2 Cost Model Packing'!$I$46) -> 1.3430614
B80: Total Production Cost | C80: =SUM(C77:C79) -> 1 | D80: =SUM(D77:D79) -> 4.5504621 | G80: Wet Aseptic Cleaning | H80: =I80/$I$89 -> 0 | I80: =IF($C$12="Semi-Automated",'2.2 Cost Model Packing'!$E$65,'2.2 Cost Model Packing'!$I$65) -> 0
B81: Overheads and Indirect Cost for the Packing | D81: =IF(C12="Semi-Automated",'2.2 Cost Model Packing'!E232,'2.2 Cost Model Packing'!I232) -> 12.120626 | G81: Can Filling & Closing | H81: =I81/$I$89 -> 0 | I81: =IF($C$12="Semi-Automated",'2.2 Cost Model Packing'!$E$84,'2.2 Cost Model Packing'!$I$84) -> 0
B82: Total Production Cost (including overheads and indirect cost) | D82: =D81+D80 -> 16.671088 | G82: Aseptic Filling & Closing | H82: =I82/$I$89 -> 0.093347112 | I82: =IF($C$12="Semi-Automated",'2.2 Cost Model Packing'!$E$103,'2.2 Cost Model Packing'!$I$103) -> 0.4247725
B83: *Figures in the table and the corresponding graph may not add to 100.0% as the figures have been rounded off | G83: Nitrogenation | H83: =I83/$I$89 -> 0.088122111 | I83: =IF($C$12="Semi-Automated",'2.2 Cost Model Packing'!$E$122,'2.2 Cost Model Packing'!$I$122) -> 0.40099633
G84: Can Pasteurisation | H84: =I84/$I$89 -> 0 | I84: =IF($C$12="Semi-Automated",'2.2 Cost Model Packing'!$E$141,'2.2 Cost Model Packing'!$I$141) -> 0
G85: Shrink Sleeve Labelling | H85: =I85/$I$89 -> 0.081383738 | I85: =IF($C$12="Semi-Automated",'2.2 Cost Model Packing'!$E$160,'2.2 Cost Model Packing'!$I$160) -> 0.37033361
G86: Shrinking into Multipack | H86: =I86/$I$89 -> 0.17840413 | I86: =IF($C$12="Semi-Automated",'2.2 Cost Model Packing'!$E$179,'2.2 Cost Model Packing'!$I$179) -> 0.81182125
B87: =B74 -> Cost Breakdown – Packing – By Cost Type | G87: Packing in Tray & Shrink | H87: =I87/$I$89 -> 0.090231727 | I87: =IF($C$12="Semi-Automated",'2.2 Cost Model Packing'!$E$198,'2.2 Cost Model Packing'!$I$198) -> 0.41059606
G88: Palletising | H88: =I88/$I$89 -> 0.039215623 | I88: =IF($C$12="Semi-Automated",'2.2 Cost Model Packing'!$E$217,'2.2 Cost Model Packing'!$I$217) -> 0.17844921
G89: Total Production Cost | H89: =SUM(H79:H88) -> 0.86585279 | I89: =SUM(I78:I88) -> 4.5504621
G90: Overheads and Indirect Cost for the Process | I90: =IF($C$12="Semi-Automated",'2.2 Cost Model Packing'!$E$232,'2.2 Cost Model Packing'!$I$232) -> 12.120626
G91: Total Production Cost (including overheads and indirect cost) | I91: =I89+I90 -> 16.671088
G94: =G75 -> Cost Breakdown – Packing – By Packing Step
A237: Copyright © 2025 WNS (Holdings) Ltd. All rights reserved.
C268: Note: 1) Selling, general, and administrative costs as a proportion of total variable and labor cost has been benchmarked against corresponding expenses as stated in the FY2020 annual report of Asia Can Manufacturing and Bangkok Can Manufacturing in Thailand, Showa Denko, and Crown in Vietnam; this has also been verified through primary research 2) The depreciation costs have been estimated by the 'Straight Line' method; aluminum can manufacturing line and plant building typically have a life of 10–15 and 35–45 years, respectively
B317: =B25 -> Cost Structure Summary – RTD Ice Tea
B318: ='1.1 Summary'!#REF! -> #REF!

Sheet 1.2 Scenario Analysis
B5: Summary – RTD Ice Tea | I5: Carbonated | J5: PET Bottle
I6: Non-Carbonated | J6: Can
B7: Indicates drop-down menu | C7: Indicates input cell | G7: Indicates drop-down menu | H7: Indicates input cell | I7: Big Bag | J7: Carton | K7: Bag in Boxes | L7: Indicates drop-down menu | M7: Indicates input cell
I8: 500 | J8: 4 | K8: 0.4
B9: Product Name | C9: RTD Ice Tea1 | G9: Product Name | H9: RTD Ice Tea | I9: 20 | J9: 3 | K9: 0.25 | L9: Product Name | M9: RTD Ice Tea | AA9: 128
B10: Production Country | C10: ='1.1 Summary'!C9 -> Netherlands | G10: Production Country | H10: Netherlands | L10: Production Country | M10: Portugal
B11: RTD Ice Tea Machinery | C11: ='1.1 Summary'!C12 -> Fully-Automated | G11: RTD Ice Tea Machinery | H11: Fully-Automated | J11: 0.25 | L11: RTD Ice Tea Machinery | M11: Semi-Automated
B12: Facility Type | C12: ='1.1 Summary'!C13 -> New | G12: Facility Type | H12: Intermediate | J12: 0.33 | L12: Facility Type | M12: Intermediate | AA12: 1.5
B13: Product Type | C13: ='1.1 Summary'!C14 -> Non-Carbonated | G13: Product Type | H13: Non-Carbonated | J13: 0.5 | L13: Product Type | M13: Non-Carbonated | AA13: 32
B14: SKU Packing Type | C14: ='1.1 Summary'!C15 -> PET Bottle | G14: SKU Packing Type | H14: PET Bottle | J14: 1 | L14: SKU Packing Type | M14: PET Bottle
B15: SKU Size | C15: ='1.1 Summary'!C16 -> 2 | G15: SKU Size | H15: 2 | I15: Dry Aseptic | J15: France | L15: SKU Size | M15: 2
B16: Number of Units in Multipacks | C16: ='1.1 Summary'!C17 -> 6 | G16: Number of Units in Multipacks | H16: 4 | I16: Wet Aseptic | J16: Netherlands | L16: Number of Units in Multipacks | M16: 4
B17: Tray Combination | C17: ='1.1 Summary'!C18 -> 6*4 | G17: Tray Combination | H17: =IF(H16=4,"4*6",IF(H16=6,"6*4",IF(H16=8,"8*3",IF(H16=12,"12*2","24*1")))) -> 4*6 | J17: Portugal | L17: Tray Combination | M17: =IF(M16=4,"4*6",IF(M16=6,"6*4",IF(M16=8,"8*3",IF(M16=12,"12*2","24*1")))) -> 4*6
B18: PET Bottle Decontamination Process (For Can Packing, Select " – ") | C18: ='1.1 Summary'!C19 -> Dry Aseptic | G18: PET Bottle Decontamination Process (For Can Packing, Select " – ") | H18: Dry Aseptic | J18: Country B | L18: PET Bottle Decontamination Process (For Can Packing, Select " – ") | M18: Dry Aseptic
B19: Scale of Production | C19: ='1.1 Summary'!C20 -> High-scale | G19: Scale of Production | H19: High-scale | L19: Scale of Production | M19: High-scale
B20: Site Complexity | C20: ='1.1 Summary'!C21 -> Low | G20: Site Complexity | H20: Low | L20: Site Complexity | M20: Low
B22: Cost Structure Summary – Scenario 11 | G22: Cost Structure Summary – Scenario 2 | J22: 0.25 | L22: Cost Structure Summary – Scenario 3
J23: 0.33
B24: Parameters | C24: Cost Breakdown* | D24: Cost Breakdown (EUR/MT) | G24: Parameters | H24: Cost Breakdown* | I24: Cost Breakdown (EUR/MT) | J24: 0.5 | L24: Parameters | M24: Cost Breakdown* | N24: Cost Breakdown (EUR/MT)
B25: Total Equipment Cost | C25: =D25/$D$29 -> 0.023571088 | D25: ='1.1 Summary'!D28 -> 2.5086824 | G25: Total Equipment Cost | H25: =I25/$I$29 -> 0.017587103 | I25: =IF(H11="Semi-Automated",('2.1 Cost Model Processes (2)'!$E$12+'2.1 Cost Model Processes (2)'!$E$30+'2.1 Cost Model Processes (2)'!$E$48+'2.1 Cost Model Processes (2)'!$E67+'2.1 Cost Model Processes (2)'!$E86+'2.2 Cost Model Packing (2)'!$E12+'2.2 Cost Model Packing (2)'!$E32+'2.2 Cost Model Packing (2)'!$E51+'2.2 Cost Model Packing (2)'!$E70+'2.2 Cost Model Packing (2)'!$E89+'2.2 Cost Model Packing (2)'!$E108+'2.2 Cost Model Packing (2)'!$E127+'2.2 Cost Model Packing (2)'!$E146+'2.2 Cost Model Packing (2)'!$E165+'2.2 Cost Model Packing (2)'!$E184+'2.2 Cost Model Packing (2)'!$E203),('2.2 Cost Model Packing (2)'!$I203+'2.2 Cost Model Packing (2)'!$I184+'2.2 Cost Model Packing (2)'!$I165+'2.2 Cost Model Packing (2)'!$I146+'2.2 Cost Model Packing (2)'!$I127+'2.2 Cost Model Packing (2)'!$I108+'2.2 Cost Model Packing (2)'!$I89+'2.2 Cost Model Packing (2)'!$I70+'2.2 Cost Model Packing (2)'!$I51+'2.2 Cost Model Packing (2)'!$I32+'2.2 Cost Model Packing (2)'!$I12+'2.1 Cost Model Processes (2)'!$I12+'2.1 Cost Model Processes (2)'!$I30+'2.1 Cost Model Processes (2)'!$I48+'2.1 Cost Model Processes (2)'!$I67+'2.1 Cost Model Processes (2)'!$I86)) -> 1.8815118 | J25: 1 | L25: Total Equipment Cost | M25: =N25/$I$29 -> 0.019288266 | N25: =IF(M11="Semi-Automated",('2.1 Cost Model Processes (3)'!$E$12+'2.1 Cost Model Processes (3)'!$E$30+'2.1 Cost Model Processes (3)'!$E$48+'2.1 Cost Model Processes (3)'!$E67+'2.1 Cost Model Processes (3)'!$E86+'2.2 Cost Model Packing (3)'!$E12+'2.2 Cost Model Packing (3)'!$E32+'2.2 Cost Model Packing (3)'!$E51+'2.2 Cost Model Packing (3)'!$E70+'2.2 Cost Model Packing (3)'!$E89+'2.2 Cost Model Packing (3)'!$E108+'2.2 Cost Model Packing (3)'!$E127+'2.2 Cost Model Packing (3)'!$E146+'2.2 Cost Model Packing (3)'!$E165+'2.2 Cost Model Packing (3)'!$E184+'2.2 Cost Model Packing (3)'!$E203),('2.2 Cost Model Packing (3)'!$I203+'2.2 Cost Model Packing (3)'!$I184+'2.2 Cost Model Packing (3)'!$I165+'2.2 Cost Model Packing (3)'!$I146+'2.2 Cost Model Packing (3)'!$I127+'2.2 Cost Model Packing (3)'!$I108+'2.2 Cost Model Packing (3)'!$I89+'2.2 Cost Model Packing (3)'!$I70+'2.2 Cost Model Packing (3)'!$I51+'2.2 Cost Model Packing (3)'!$I32+'2.2 Cost Model Packing (3)'!$I12+'2.1 Cost Model Processes (3)'!$I12+'2.1 Cost Model Processes (3)'!$I30+'2.1 Cost Model Processes (3)'!$I48+'2.1 Cost Model Processes (3)'!$I67+'2.1 Cost Model Processes (3)'!$I86)) -> 2.0635065
B26: Total Utility Cost | C26: =D26/$D$29 -> 0.20057098 | D26: ='1.1 Summary'!D29 -> 21.346868 | G26: Total Utility Cost | H26: =I26/$I$29 -> 0.20852552 | I26: =IF(H11="Semi-Automated",('2.1 Cost Model Processes (2)'!$E17+'2.1 Cost Model Processes (2)'!$E35+'2.1 Cost Model Processes (2)'!$E53+'2.1 Cost Model Processes (2)'!$E72+'2.1 Cost Model Processes (2)'!$E91+'2.2 Cost Model Packing (2)'!$E17+'2.2 Cost Model Packing (2)'!$E37+'2.2 Cost Model Packing (2)'!$E56+'2.2 Cost Model Packing (2)'!$E75+'2.2 Cost Model Packing (2)'!$E94+'2.2 Cost Model Packing (2)'!$E113+'2.2 Cost Model Packing (2)'!$E132+'2.2 Cost Model Packing (2)'!$E151+'2.2 Cost Model Packing (2)'!$E170+'2.2 Cost Model Packing (2)'!$E189+'2.2 Cost Model Packing (2)'!$E208),('2.2 Cost Model Packing (2)'!$I208+'2.2 Cost Model Packing (2)'!$I189+'2.2 Cost Model Packing (2)'!$I170+'2.2 Cost Model Packing (2)'!$I151+'2.2 Cost Model Packing (2)'!$I132+'2.2 Cost Model Packing (2)'!$I113+'2.2 Cost Model Packing (2)'!$I94+'2.2 Cost Model Packing (2)'!$I75+'2.2 Cost Model Packing (2)'!$I56+'2.2 Cost Model Packing (2)'!$I37+'2.2 Cost Model Packing (2)'!$I17+'2.1 Cost Model Processes (2)'!$I17+'2.1 Cost Model Processes (2)'!$I35+'2.1 Cost Model Processes (2)'!$I53+'2.1 Cost Model Processes (2)'!$I72+'2.1 Cost Model Processes (2)'!$I91)) -> 22.308576 | J26: 1.5 | L26: Total Utility Cost | M26: =N26/$I$29 -> 0.30191888 | N26: =IF(M11="Semi-Automated",('2.1 Cost Model Processes (3)'!$E17+'2.1 Cost Model Processes (3)'!$E35+'2.1 Cost Model Processes (3)'!$E53+'2.1 Cost Model Processes (3)'!$E72+'2.1 Cost Model Processes (3)'!$E91+'2.2 Cost Model Packing (3)'!$E17+'2.2 Cost Model Packing (3)'!$E37+'2.2 Cost Model Packing (3)'!$E56+'2.2 Cost Model Packing (3)'!$E75+'2.2 Cost Model Packing (3)'!$E94+'2.2 Cost Model Packing (3)'!$E113+'2.2 Cost Model Packing (3)'!$E132+'2.2 Cost Model Packing (3)'!$E151+'2.2 Cost Model Packing (3)'!$E170+'2.2 Cost Model Packing (3)'!$E189+'2.2 Cost Model Packing (3)'!$E208),('2.2 Cost Model Packing (3)'!$I208+'2.2 Cost Model Packing (3)'!$I189+'2.2 Cost Model Packing (3)'!$I170+'2.2 Cost Model Packing (3)'!$I151+'2.2 Cost Model Packing (3)'!$I132+'2.2 Cost Model Packing (3)'!$I113+'2.2 Cost Model Packing (3)'!$I94+'2.2 Cost Model Packing (3)'!$I75+'2.2 Cost Model Packing (2)'!$I56+'2.2 Cost Model Packing (3)'!$I37+'2.2 Cost Model Packing (3)'!$I17+'2.1 Cost Model Processes (3)'!$I17+'2.1 Cost Model Processes (3)'!$I35+'2.1 Cost Model Processes (3)'!$I53+'2.1 Cost Model Processes (3)'!$I72+'2.1 Cost Model Processes (3)'!$I91)) -> 32.300029
B27: Total Labour Cost | C27: =D27/$D$29 -> 0.10901249 | D27: ='1.1 Summary'!D30 -> 11.602253 | G27: Total Labour Cost | H27: =I27/$I$29 -> 0.10845003 | I27: =IF(H11="Semi-Automated",('2.1 Cost Model Processes (2)'!$E24+'2.1 Cost Model Processes (2)'!$E42+'2.1 Cost Model Processes (2)'!$E60+'2.1 Cost Model Processes (2)'!$E79+'2.1 Cost Model Processes (2)'!$E98+'2.2 Cost Model Packing (2)'!$E25+'2.2 Cost Model Packing (2)'!$E45+'2.2 Cost Model Packing (2)'!$E64+'2.2 Cost Model Packing (2)'!$E83+'2.2 Cost Model Packing (2)'!$E102+'2.2 Cost Model Packing (2)'!$E121+'2.2 Cost Model Packing (2)'!$E140+'2.2 Cost Model Packing (2)'!$E159+'2.2 Cost Model Packing (2)'!$E178+'2.2 Cost Model Packing (2)'!$E197+'2.2 Cost Model Packing (2)'!$E216),('2.2 Cost Model Packing (2)'!$I216+'2.2 Cost Model Packing (2)'!$I197+'2.2 Cost Model Packing (2)'!$I178+'2.2 Cost Model Packing (2)'!$I159+'2.2 Cost Model Packing (2)'!$I140+'2.2 Cost Model Packing (2)'!$I121+'2.2 Cost Model Packing (2)'!$I102+'2.2 Cost Model Packing (2)'!$I83+'2.2 Cost Model Packing (2)'!$I64+'2.2 Cost Model Packing (2)'!$I45+'2.2 Cost Model Packing (2)'!$I25+'2.1 Cost Model Processes (2)'!I98+'2.1 Cost Model Processes (2)'!$I79+'2.1 Cost Model Processes (2)'!$I60+'2.1 Cost Model Processes (2)'!$I42+'2.1 Cost Model Processes (2)'!$I24)) -> 11.602253 | J27: 2 | L27: Total Labour Cost | M27: =N27/$I$29 -> 0.15868962 | N27: =IF(M11="Semi-Automated",('2.1 Cost Model Processes (3)'!$E24+'2.1 Cost Model Processes (3)'!$E42+'2.1 Cost Model Processes (3)'!$E60+'2.1 Cost Model Processes (3)'!$E79+'2.1 Cost Model Processes (3)'!$E98+'2.2 Cost Model Packing (3)'!$E25+'2.2 Cost Model Packing (3)'!$E45+'2.2 Cost Model Packing (3)'!$E64+'2.2 Cost Model Packing (3)'!$E83+'2.2 Cost Model Packing (3)'!$E102+'2.2 Cost Model Packing (3)'!$E121+'2.2 Cost Model Packing (3)'!$E140+'2.2 Cost Model Packing (3)'!$E159+'2.2 Cost Model Packing (3)'!$E178+'2.2 Cost Model Packing (3)'!$E197+'2.2 Cost Model Packing (3)'!$E216),('2.2 Cost Model Packing (3)'!$I216+'2.2 Cost Model Packing (3)'!$I197+'2.2 Cost Model Packing (3)'!$I178+'2.2 Cost Model Packing (3)'!$I159+'2.2 Cost Model Packing (3)'!$I140+'2.2 Cost Model Packing (3)'!$I121+'2.2 Cost Model Packing (3)'!$I102+'2.2 Cost Model Packing (3)'!$I83+'2.2 Cost Model Packing (3)'!$I64+'2.2 Cost Model Packing (3)'!$I45+'2.2 Cost Model Packing (3)'!$I25+'2.1 Cost Model Processes (3)'!N98+'2.1 Cost Model Processes (3)'!$I79+'2.1 Cost Model Processes (3)'!$I60+'2.1 Cost Model Processes (3)'!$I42+'2.1 Cost Model Processes (3)'!$I24)) -> 16.977009
B28: Total Overhead and Indirect Cost | C28: =D28/$D$29 -> 0.66684544 | D28: ='1.1 Summary'!D31 -> 70.972686 | G28: Total Overhead and Indirect Cost | H28: =I28/$I$29 -> 0.66543735 | I28: =IF(H11="Semi-Automated",('2.1 Cost Model Processes (2)'!$E115+'2.2 Cost Model Packing (2)'!$E232),('2.2 Cost Model Packing (2)'!$I232+'2.1 Cost Model Processes (2)'!$I115)) -> 71.190136 | L28: Total Overhead and Indirect Cost | M28: =N28/$I$29 -> 0.96769662 | N28: =IF(M11="Semi-Automated",('2.1 Cost Model Processes (3)'!$E115+'2.2 Cost Model Packing (3)'!$E232),('2.2 Cost Model Packing (3)'!$I232+'2.1 Cost Model Processes (3)'!$I115)) -> 103.52658
B29: Total Production Cost | C29: =SUM(C25:C28) -> 1 | D29: =SUM(D25:D28) -> 106.43049 | G29: Total Production Cost | H29: =SUM(H25:H28) -> 1 | I29: =SUM(I25:I28) -> 106.98248 | L29: Total Production Cost | M29: =SUM(M25:M28) -> 1.4475934 | N29: =SUM(N25:N28) -> 154.86712
B31: Average Margins Earned by Supplier | C31: Low | D31: =IF(C31="High",20%,IF(C31="Medium",15%,10%)) -> 0.1 | E31: Please click for definition | G31: Average Margins Earned by Supplier | H31: Medium | I31: =IF(H31="High",20%,IF(H31="Medium",15%,10%)) -> 0.15 | L31: Average Margins Earned by Supplier | M31: Medium | N31: =IF(M31="High",20%,IF(M31="Medium",15%,10%)) -> 0.15
B32: Production Cost including Margin Earned by Supplier | D32: =(D31*D29)+D29 -> 117.07354 | G32: Production Cost including Margin Earned by Supplier | I32: =(I31*I29)+I29 -> 123.02985 | L32: Production Cost including Margin Earned by Supplier | N32: =(N31*N29)+N29 -> 178.09719
B34: Purchase Price ($/MT) | D34: 321 | G34: Purchase Price ($/MT) | I34: 321 | L34: Purchase Price ($/MT) | N34: 321
B36: Gap (EUR/MT) | D36: =IF(D34="","Please enter purchase price in cell D32",D34-D32) -> 203.92646 | G36: Gap (EUR/MT) | I36: =IF(I34="","Please enter purchase price in cell D32",I34-I32) -> 197.97015 | L36: Gap (EUR/MT) | N36: =IF(N34="","Please enter purchase price in cell D32",N34-N32) -> 142.90281
B37: Cost Structure Summary-Scenario 1 | G37: Cost Structure Summary-Scenario 2 | L37: Cost Structure Summary-Scenario 3
B49: Note:
B50: 1) Inputs are drawn from 1.1 Summary sheet. Any changes made in the summary sheet will be reflected in the scenario 1
A51: Copyright © 2026 WNS (Holdings) Ltd. All rights reserved.
B142: ='[9]1.1 Summary'!B37 -> Cost Breakdown – Processes – By Cost Type
B143: ='1.2 Scenario Analysis'!#REF! -> #REF!

Sheet Part 2 - Cost Breakdown

Sheet 2.1 Cost Model Processes
C5: Summary – Process Cost
D7: Semi-Automatic | H7: Automatic
B9: Water Treatment Process | C9: Water Treatment
C10: Machinery | D10: Total Hourly Cost (€) | E10: Total Depreciation per MT (€/MT) | F10: Percentage of the Total Cost (%) | H10: Total Hourly Cost (€) | I10: Total Depreciation per MT (€/MT) | J10: Percentage of the Total Cost (%)
C11: Reverse Osmosis Water Treatment Machine | D11: ='3.1 Water Treatment'!F34 -> 1.2239583 | E11: ='3.1 Water Treatment'!G34 -> 0.52811352 | F11: =D11/$D$118 -> 0.0074909111 | H11: ='3.1 Water Treatment'!F38 -> 1.4583333 | I11: ='3.1 Water Treatment'!G38 -> 0.41537458 | J11: =H11/$H$118 -> 0.0083080903
C12: Total Machinery Cost | D12: =SUM(D11:D11) -> 1.2239583 | E12: =SUM(E11:E11) -> 0.52811352 | F12: =SUM(F11:F11) -> 0.0074909111 | H12: =SUM(H11:H11) -> 1.4583333 | I12: =SUM(I11:I11) -> 0.41537458 | J12: =SUM(J11:J11) -> 0.0083080903
C14: Utility | D14: Total Hourly Cost (€) | E14: Total Cost per MT (€/MT) | F14: Percentage of the Total Cost (%) | H14: Total Hourly Cost (€) | I14: Total Cost per MT (€/MT) | J14: Percentage of the Total Cost (%)
C15: Electricity and Natural Gas Cost | D15: ='3.1 Water Treatment'!F44 -> 7.4631322 | E15: ='3.1 Water Treatment'!G44 -> 3.2201922 | F15: =D15/$D$118 -> 0.045676114 | H15: ='3.1 Water Treatment'!F48 -> 8.3290301 | I15: ='3.1 Water Treatment'!G48 -> 2.3723434 | J15: =H15/$H$118 -> 0.047450287
C16: Other Utility Cost | D16: =15%*D15 -> 1.1194698 | E16: =15%*E15 -> 0.48302882 | F16: =D16/$D$118 -> 0.006851417 | H16: =15%*H15 -> 1.2493545 | I16: =15%*I15 -> 0.3558515 | J16: =H16/$H$118 -> 0.007117543
C17: Total Utility Cost | D17: =SUM(D15:D16) -> 8.582602 | E17: =SUM(E15:E16) -> 3.703221 | F17: =SUM(F15:F16) -> 0.052527531 | H17: =SUM(H15:H16) -> 9.5783847 | I17: =SUM(I15:I16) -> 2.7281949 | J17: =SUM(J15:J16) -> 0.05456783
C19: Labour Cost | D19: Total Hourly Cost (€) | E19: Total Cost per MT (€/MT) | F19: Percentage of the Total Cost (%) | H19: Total Hourly Cost (€) | I19: Total Cost per MT (€/MT) | J19: Percentage of the Total Cost (%)
C20: Production Manager | D20: ='3.1 Water Treatment'!F53 -> 2.2505195 | E20: ='3.1 Water Treatment'!G53 -> 0.9710541 | F20: =D20/$D$118 -> 0.013773705 | H20: ='3.1 Water Treatment'!F60 -> 2.2505195 | I20: ='3.1 Water Treatment'!G60 -> 0.64101159 | J20: =H20/$H$118 -> 0.012821156
C21: Shift Supervisor | D21: ='3.1 Water Treatment'!F54 -> 1.8653017 | E21: ='3.1 Water Treatment'!G54 -> 0.80484035 | F21: =D21/$D$118 -> 0.011416082 | H21: ='3.1 Water Treatment'!F61 -> 1.8653017 | I21: ='3.1 Water Treatment'!G61 -> 0.53129068 | J21: =H21/$H$118 -> 0.010626579
C22: Machine Operator | D22: ='3.1 Water Treatment'!F55 -> 1.1616204 | E22: ='3.1 Water Treatment'!G55 -> 0.50121597 | F22: =D22/$D$118 -> 0.0071093886 | H22: ='3.1 Water Treatment'!F62 -> 1.1616204 | I22: ='3.1 Water Treatment'!G62 -> 0.33086236 | J22: =H22/$H$118 -> 0.006617724
C23: Production Worker | D23: ='3.1 Water Treatment'!F56 -> 2.214619 | E23: ='3.1 Water Treatment'!G56 -> 0.95556378 | F23: =D23/$D$118 -> 0.013553986 | H23: ='3.1 Water Treatment'!F63 -> 2.214619 | I23: ='3.1 Water Treatment'!G63 -> 0.63078613 | J23: =H23/$H$118 -> 0.012616632
C24: Total labor Cost | D24: =SUM(D20:D23) -> 7.4920606 | E24: =SUM(E20:E23) -> 3.2326742 | F24: =SUM(F20:F23) -> 0.045853162 | H24: =SUM(H20:H23) -> 7.4920606 | I24: =SUM(I20:I23) -> 2.1339508 | J24: =SUM(J20:J23) -> 0.042682091
C25: Total Water Treatment Process Costs | D25: =SUM(D12,D17,D24) -> 17.298621 | E25: =SUM(E12,E17,E24) -> 7.4640087 | F25: =SUM(F17,F12,F24) -> 0.1058716 | H25: =SUM(H17,H12,H24) -> 18.528779 | I25: =SUM(I17,I12,I24) -> 5.2775202 | J25: =SUM(J24+J12+J17) -> 0.10555801
B27: Syrup Preparation Process | C27: Syrup Preparation
C28: Machinery | D28: Total Hourly Cost (€) | E28: Total Depreciation per MT (€/MT) | F28: Percentage of the Total Cost (%) | H28: Total Hourly Cost (€) | I28: Total Depreciation per MT (€/MT) | J28: Percentage of the Total Cost (%)
C29: Jacket Mixing Tank with High Shear Mixer | D29: ='3.2 Syrup Preparation'!F34 -> 0.15625 | E29: ='3.2 Syrup Preparation'!G34 -> 0.079261027 | F29: =D29/$D$118 -> 0.00095628653 | H29: ='3.2 Syrup Preparation'!F38 -> 1.7708333 | I29: ='3.2 Syrup Preparation'!G38 -> 0.61568158 | J29: =H29/$H$118 -> 0.010088395
C30: Total Machinery Cost | D30: =SUM(D29:D29) -> 0.15625 | E30: =SUM(E29:E29) -> 0.079261027 | F30: =SUM(F29:F29) -> 0.00095628653 | H30: =SUM(H29:H29) -> 1.7708333 | I30: =SUM(I29:I29) -> 0.61568158 | J30: =SUM(J29:J29) -> 0.010088395
C32: Utility | D32: Total Hourly Cost (€) | E32: Total Cost per MT (€/MT) | F32: Percentage of the Total Cost (%) | H32: Total Hourly Cost (€) | I32: Total Cost per MT (€/MT) | J32: Percentage of the Total Cost (%)
C33: Electricity and Natural Gas Cost | D33: ='3.2 Syrup Preparation'!F44 -> 9.8305567 | E33: ='3.2 Syrup Preparation'!G44 -> 4.9867521 | F33: =D33/$D$118 -> 0.060165305 | H33: ='3.2 Syrup Preparation'!F48 -> 10.619698 | I33: ='3.2 Syrup Preparation'!G48 -> 3.6922462 | J33: =H33/$H$118 -> 0.060500168
C34: Other Utility Cost | D34: =15%*D33 -> 1.4745835 | E34: =15%*E33 -> 0.74801282 | F34: =D34/$D$118 -> 0.0090247958 | H34: =15%*H33 -> 1.5929547 | I34: =15%*I33 -> 0.55383693 | J34: =H34/$H$118 -> 0.0090750252
C35: Total Utility Cost | D35: =SUM(D33:D34) -> 11.30514 | E35: =SUM(E33:E34) -> 5.7347649 | F35: =SUM(F33:F34) -> 0.069190101 | H35: =SUM(H33:H34) -> 12.212653 | I35: =SUM(I33:I34) -> 4.2460831 | J35: =SUM(J33:J34) -> 0.069575194
C37: Labour Cost | D37: Total Hourly Cost (€) | E37: Total Cost per MT (€/MT) | F37: Percentage of the Total Cost (%) | H37: Total Hourly Cost (€) | I37: Total Cost per MT (€/MT) | J37: Percentage of the Total Cost (%)
C38: Production Manager | D38: ='3.2 Syrup Preparation'!F53 -> 2.2505195 | E38: ='3.2 Syrup Preparation'!G53 -> 1.1416223 | F38: =D38/$D$118 -> 0.013773705 | H38: ='3.2 Syrup Preparation'!F60 -> 2.2505195 | I38: ='3.2 Syrup Preparation'!G60 -> 0.78245838 | J38: =H38/$H$118 -> 0.012821156
C39: Shift Supervisor | D39: ='3.2 Syrup Preparation'!F54 -> 1.8653017 | E39: ='3.2 Syrup Preparation'!G54 -> 0.94621266 | F39: =D39/$D$118 -> 0.011416082 | H39: ='3.2 Syrup Preparation'!F61 -> 1.8653017 | I39: ='3.2 Syrup Preparation'!G61 -> 0.64852625 | J39: =H39/$H$118 -> 0.010626579
C40: Machine Operator | D40: ='3.2 Syrup Preparation'!F55 -> 1.1616204 | E40: ='3.2 Syrup Preparation'!G55 -> 0.58925586 | F40: =D40/$D$118 -> 0.0071093886 | H40: ='3.2 Syrup Preparation'!F62 -> 2.3232409 | I40: ='3.2 Syrup Preparation'!G62 -> 0.8077421 | J40: =H40/$H$118 -> 0.013235448
C41: Production Worker | D41: ='3.2 Syrup Preparation'!F56 -> 2.214619 | E41: ='3.2 Syrup Preparation'!G56 -> 1.1234111 | F41: =D41/$D$118 -> 0.013553986 | H41: ='3.2 Syrup Preparation'!F63 -> 2.214619 | I41: ='3.2 Syrup Preparation'!G63 -> 0.76997655 | J41: =H41/$H$118 -> 0.012616632
C42: Total labor Cost | D42: =SUM(D38:D41) -> 7.4920606 | E42: =SUM(E38:E41) -> 3.8005019 | F42: =SUM(F38:F41) -> 0.045853162 | H42: =SUM(H38:H41) -> 8.6536811 | I42: =SUM(I38:I41) -> 3.0087033 | J42: =SUM(J38:J41) -> 0.049299815
C43: Total Syrup Preparation Process Costs | D43: =SUM(D30,D35,D42) -> 18.953451 | E43: =SUM(E30,E35,E42) -> 9.6145278 | F43: =SUM(F42,F30,F35) -> 0.11599955 | H43: =SUM(H42,H35,H30) -> 22.637167 | I43: =SUM(I42,I35,I30) -> 7.870468 | J43: =SUM(J30,J35,J42) -> 0.1289634
B45: Mixing Process | C45: Mixing Process
C46: Machinery | D46: Total Hourly Cost (€) | E46: Total Depreciation per MT (€/MT) | F46: Percentage of the Total Cost (%) | H46: Total Hourly Cost (€) | I46: Total Depreciation per MT (€/MT) | J46: Percentage of the Total Cost (%)
C47: Pressure Blending Tank | D47: ='3.4 Mixing'!F34 -> 1.0416667 | E47: ='3.4 Mixing'!G34 -> 0.16001417 | F47: =D47/$D$118 -> 0.0063752435 | H47: ='3.4 Mixing'!F38 -> 1.2239583 | I47: ='3.4 Mixing'!G38 -> 0.065912423 | J47: =H47/$H$118 -> 0.0069728615
C48: Total Machinery Cost | D48: =SUM(D47) -> 1.0416667 | E48: =SUM(E47) -> 0.16001417 | F48: =SUM(F47:F47) -> 0.0063752435 | H48: =SUM(H47:H47) -> 1.2239583 | I48: =SUM(I47:I47) -> 0.065912423 | J48: =SUM(J47:J47) -> 0.0069728615
C50: Utility | D50: Total Hourly Cost (€) | E50: Total Cost per MT (€/MT) | F50: Percentage of the Total Cost (%) | H50: Total Hourly Cost (€) | I50: Total Cost per MT (€/MT) | J50: Percentage of the Total Cost (%)
C51: Electricity and Natural Gas Cost | D51: ='3.4 Mixing'!F44 -> 3.5174246 | E51: ='3.4 Mixing'!G44 -> 0.54032426 | F51: =D51/$D$118 -> 0.021527461 | H51: ='3.4 Mixing'!F48 -> 4.3065661 | I51: ='3.4 Mixing'!G48 -> 0.23191656 | J51: =H51/$H$118 -> 0.024534405
C52: Other Utility Cost | D52: =15%*D51 -> 0.52761368 | E52: =15%*E51 -> 0.081048639 | F52: =D52/$D$118 -> 0.0032291191 | H52: =15%*H51 -> 0.64598491 | I52: =15%*I51 -> 0.034787484 | J52: =H52/$H$118 -> 0.0036801607
C53: Total Utility Cost | D53: =SUM(D51:D52) -> 4.0450383 | E53: =SUM(E51:E52) -> 0.6213729 | F53: =SUM(F51:F52) -> 0.02475658 | H53: =SUM(H51:H52) -> 4.952551 | I53: =SUM(I51:I52) -> 0.26670404 | J53: =SUM(J51:J52) -> 0.028214565
C55: Labour Cost | D55: Total Hourly Cost (€) | E55: Total Cost per MT (€/MT) | F55: Percentage of the Total Cost (%) | H55: Total Hourly Cost (€) | I55: Total Cost per MT (€/MT) | J55: Percentage of the Total Cost (%)
C56: Production Manager | D56: ='3.4 Mixing'!F53 -> 2.2505195 | E56: ='3.4 Mixing'!G53 -> 0.3457104 | F56: =D56/$D$118 -> 0.013773705 | H56: ='3.4 Mixing'!F60 -> 2.2505195 | I56: ='3.4 Mixing'!G60 -> 0.12119464 | J56: =H56/$H$118 -> 0.012821156
C57: Shift Supervisor | D57: ='3.4 Mixing'!F54 -> 1.8653017 | E57: ='3.4 Mixing'!G54 -> 0.28653571 | F57: =D57/$D$118 -> 0.011416082 | H57: ='3.4 Mixing'!F61 -> 1.8653017 | I57: ='3.4 Mixing'!G61 -> 0.10044995 | J57: =H57/$H$118 -> 0.010626579
C58: Machine Operator | D58: ='3.4 Mixing'!F55 -> 1.1616204 | E58: ='3.4 Mixing'!G55 -> 0.1784407 | F58: =D58/$D$118 -> 0.0071093886 | H58: ='3.4 Mixing'!F62 -> 1.1616204 | I58: ='3.4 Mixing'!G62 -> 0.062555412 | J58: =H58/$H$118 -> 0.006617724
C59: Production Worker | D59: ='3.4 Mixing'!F56 -> 2.214619 | E59: ='3.4 Mixing'!G56 -> 0.3401956 | F59: =D59/$D$118 -> 0.013553986 | H59: ='3.4 Mixing'!F63 -> 2.214619 | I59: ='3.4 Mixing'!G63 -> 0.11926134 | J59: =H59/$H$118 -> 0.012616632
C60: Total Labour Cost | D60: =SUM(D56:D59) -> 7.4920606 | E60: =SUM(E56:E59) -> 1.1508824 | F60: =SUM(F56:F59) -> 0.045853162 | H60: =SUM(H56:H59) -> 7.4920606 | I60: =SUM(I56:I59) -> 0.40346134 | J60: =SUM(J56:J59) -> 0.042682091
C62: Total Mixing Process Costs | D62: =SUM(D60,D53,D48) -> 12.578766 | E62: =SUM(E60,E53,E48) -> 1.9322695 | F62: =SUM(F60,F53,F48) -> 0.076984986 | H62: =SUM(H60,H53,H48) -> 13.66857 | I62: =SUM(I60,I53,I48) -> 0.7360778 | J62: =SUM(J60,J53,J48) -> 0.077869518
B64: Pasteurisation Process | C64: Pasteurisation Process
C65: Machinery | D65: Total Hourly Cost (€) | E65: Total Depreciation per MT (€/MT) | F65: Percentage of the Total Cost (%) | H65: Total Hourly Cost (€) | I65: Total Depreciation per MT (€/MT) | J65: Percentage of the Total Cost (%)
C66: Pasteuriser | D66: =IF('1.1 Summary'!$C$15="Can",0,'3.5 Pasteurisation'!F34) -> 2.1223958 | E66: =IF('1.1 Summary'!$C$15="Can",0,'3.5 Pasteurisation'!G34) -> 1.7828331 | F66: =D66/$D$118 -> 0.012989559 | H66: =IF('1.1 Summary'!$C$15="Can",0,'3.5 Pasteurisation'!F38) -> 2.2786458 | I66: =IF('1.1 Summary'!$C$15="Can",0,'3.5 Pasteurisation'!G38) -> 1.2042546 | J66: =H66/$H$118 -> 0.012981391
C67: Total Machinery Cost | D67: =SUM(D66) -> 2.1223958 | E67: =SUM(E66) -> 1.7828331 | F67: =SUM(F66) -> 0.012989559 | H67: =SUM(H66:H66) -> 2.2786458 | I67: =SUM(I66:I66) -> 1.2042546 | J67: =SUM(J66) -> 0.012981391
C69: Utility | D69: Total Hourly Cost (€) | E69: Total Cost per MT (€/MT) | F69: Percentage of the Total Cost (%) | H69: Total Hourly Cost (€) | I69: Total Cost per MT (€/MT) | J69: Percentage of the Total Cost (%)
C70: Electricity and Natural Gas Cost | D70: =IF('1.1 Summary'!$C$15="Can",0,'3.5 Pasteurisation'!F44) -> 19.039647 | E70: =IF('1.1 Summary'!$C$15="Can",0,'3.5 Pasteurisation'!G44) -> 15.993489 | F70: =D70/$D$118 -> 0.11652709 | H70: =IF('1.1 Summary'!$C$15="Can",0,'3.5 Pasteurisation'!F48) -> 19.513132 | I70: =IF('1.1 Summary'!$C$15="Can",0,'3.5 Pasteurisation'!G48) -> 10.312607 | J70: =H70/$H$118 -> 0.11116585
C71: Other Utility Cost | D71: =15%*D70 -> 2.8559471 | E71: =15%*E70 -> 2.3990233 | F71: =D71/$D$118 -> 0.017479064 | H71: =15%*H70 -> 2.9269698 | I71: =15%*I70 -> 1.546891 | J71: =H71/$H$118 -> 0.016674877
C72: Total Utility Cost | D72: =SUM(D70:D71) -> 21.895594 | E72: =SUM(E70:E71) -> 18.392512 | F72: =SUM(F70:F71) -> 0.13400616 | H72: =SUM(H70:H71) -> 22.440102 | I72: =SUM(I70:I71) -> 11.859498 | J72: =SUM(J70:J71) -> 0.12784073
C74: Labour Cost | D74: Total Hourly Cost (€) | E74: Total Cost per MT (€/MT) | F74: Percentage of the Total Cost (%) | H74: Total Hourly Cost (€) | I74: Total Cost per MT (€/MT) | J74: Percentage of the Total Cost (%)
C75: Production Manager | D75: =IF('1.1 Summary'!$C$15="Can",0,'3.5 Pasteurisation'!F53) -> 2.2505195 | E75: =IF('1.1 Summary'!$C$15="Can",0,'3.5 Pasteurisation'!G53) -> 1.8904582 | F75: =D75/$D$118 -> 0.013773705 | H75: =IF('1.1 Summary'!$C$15="Can",0,'3.5 Pasteurisation'!F60) -> 2.2505195 | I75: =IF('1.1 Summary'!$C$15="Can",0,'3.5 Pasteurisation'!G60) -> 1.1893899 | J75: =H75/$H$118 -> 0.012821156
C76: Shift Supervisor | D76: =IF('1.1 Summary'!$C$15="Can",0,'3.5 Pasteurisation'!F54) -> 1.8653017 | E76: =IF('1.1 Summary'!$C$15="Can",0,'3.5 Pasteurisation'!G54) -> 1.5668716 | F76: =D76/$D$118 -> 0.011416082 | H76: =IF('1.1 Summary'!$C$15="Can",0,'3.5 Pasteurisation'!F61) -> 1.8653017 | I76: =IF('1.1 Summary'!$C$15="Can",0,'3.5 Pasteurisation'!G61) -> 0.98580398 | J76: =H76/$H$118 -> 0.010626579
C77: Machine Operator | D77: =IF('1.1 Summary'!$C$15="Can",0,'3.5 Pasteurisation'!F55) -> 1.1616204 | E77: =IF('1.1 Summary'!$C$15="Can",0,'3.5 Pasteurisation'!G55) -> 0.97577247 | F77: =D77/$D$118 -> 0.0071093886 | H77: =IF('1.1 Summary'!$C$15="Can",0,'3.5 Pasteurisation'!F62) -> 1.1616204 | I77: =IF('1.1 Summary'!$C$15="Can",0,'3.5 Pasteurisation'!G62) -> 0.61391144 | J77: =H77/$H$118 -> 0.006617724
C78: Production Worker | D78: =IF('1.1 Summary'!$C$15="Can",0,'3.5 Pasteurisation'!F56) -> 2.214619 | E78: =IF('1.1 Summary'!$C$15="Can",0,'3.5 Pasteurisation'!G56) -> 1.8603015 | F78: =D78/$D$118 -> 0.013553986 | H78: =IF('1.1 Summary'!$C$15="Can",0,'3.5 Pasteurisation'!F63) -> 2.214619 | I78: =IF('1.1 Summary'!$C$15="Can",0,'3.5 Pasteurisation'!G63) -> 1.1704167 | J78: =H78/$H$118 -> 0.012616632
C79: Total labor Cost | D79: =SUM(D75:D78) -> 7.4920606 | E79: =SUM(E75:E78) -> 6.2934038 | F79: =SUM(F75:F78) -> 0.045853162 | H79: =SUM(H75:H78) -> 7.4920606 | I79: =SUM(I75:I78) -> 3.959522 | J79: =SUM(J75:J78) -> 0.042682091
C81: Total Pasteurisation Process Cost | D81: =SUM(D79,D72,D67) -> 31.510051 | E81: =SUM(E79,E72,E67) -> 26.468749 | F81: =SUM(F79,F72,F67) -> 0.19284888 | H81: =SUM(H79,H72,H67) -> 32.210808 | I81: =SUM(I79,I72,I67) -> 17.023275 | J81: =SUM(J79,J72,J67) -> 0.18350421
B83: Carbonation Process | C83: Carbonation Process
C84: Machinery | D84: Total Hourly Cost (€) | E84: Total Depreciation per MT (€/MT) | F84: Percentage of the Total Cost (%) | H84: Total Hourly Cost (€) | I84: Total Depreciation per MT (€/MT) | J84: Percentage of the Total Cost (%)
C85: Carbonation Maker | D85: =IF('1.1 Summary'!$C$14="Non-Carbonated",0,'3.3 Carbonation'!F34) -> 0 | E85: ='3.3 Carbonation'!G34 -> 0 | F85: =D85/$D$118 -> 0 | H85: =IF('1.1 Summary'!$C$14="Non-Carbonated",0,'3.3 Carbonation'!F38) -> 0 | I85: ='3.3 Carbonation'!G38 -> 0 | J85: =H85/$H$118 -> 0
C86: Total Machinery Cost | D86: =SUM(D85) -> 0 | E86: =SUM(E85) -> 0 | F86: =SUM(F85:F85) -> 0 | H86: =SUM(H85) -> 0 | I86: =SUM(I85) -> 0 | J86: =SUM(J85:J85) -> 0
C88: Utility | D88: Total Hourly Cost (€) | E88: Total Cost per MT (€/MT) | F88: Percentage of the Total Cost (%) | H88: Total Hourly Cost (€) | I88: Total Cost per MT (€/MT) | J88: Percentage of the Total Cost (%)
C89: Electricity and Natural Gas Cost | D89: =IF('1.1 Summary'!$C$14="Non-Carbonated",0,'3.3 Carbonation'!F44) -> 0 | E89: ='3.3 Carbonation'!G44 -> 0 | F89: =D89/$D$118 -> 0 | H89: =IF('1.1 Summary'!$C$14="Non-Carbonated",0,'3.3 Carbonation'!F48) -> 0 | I89: ='3.3 Carbonation'!G48 -> 0 | J89: =H89/$H$118 -> 0
C90: Other Utility Cost | D90: =15%*D89 -> 0 | E90: =15%*E89 -> 0 | F90: =D90/$D$118 -> 0 | H90: =15%*H89 -> 0 | I90: =15%*I89 -> 0 | J90: =H90/$H$118 -> 0
C91: Total Utility Cost | D91: =SUM(D89:D90) -> 0 | E91: =SUM(E89:E90) -> 0 | F91: =SUM(F89:F90) -> 0 | H91: =SUM(H89:H90) -> 0 | I91: =SUM(I89:I90) -> 0 | J91: =SUM(J89:J90) -> 0
C93: Labour Cost | D93: Total Hourly Cost (€) | E93: Total Cost per MT (€/MT) | F93: Percentage of the Total Cost (%) | H93: Total Hourly Cost (€) | I93: Total Cost per MT (€/MT) | J93: Percentage of the Total Cost (%)
C94: Production Manager | D94: =IF('1.1 Summary'!$C$14="Non-Carbonated",0,'3.3 Carbonation'!F53) -> 0 | E94: ='3.3 Carbonation'!G53 -> 0 | F94: =D94/$D$118 -> 0 | H94: =IF('1.1 Summary'!$C$14="Non-Carbonated",0,'3.3 Carbonation'!F60) -> 0 | I94: ='3.3 Carbonation'!G60 -> 0 | J94: =H94/$H$118 -> 0
C95: Shift Supervisor | D95: =IF('1.1 Summary'!$C$14="Non-Carbonated",0,'3.3 Carbonation'!F54) -> 0 | E95: ='3.3 Carbonation'!G54 -> 0 | F95: =D95/$D$118 -> 0 | H95: =IF('1.1 Summary'!$C$14="Non-Carbonated",0,'3.3 Carbonation'!F61) -> 0 | I95: ='3.3 Carbonation'!G61 -> 0 | J95: =H95/$H$118 -> 0
C96: Machine Operator | D96: =IF('1.1 Summary'!$C$14="Non-Carbonated",0,'3.3 Carbonation'!F55) -> 0 | E96: ='3.3 Carbonation'!G55 -> 0 | F96: =D96/$D$118 -> 0 | H96: =IF('1.1 Summary'!$C$14="Non-Carbonated",0,'3.3 Carbonation'!F62) -> 0 | I96: ='3.3 Carbonation'!G62 -> 0 | J96: =H96/$H$118 -> 0
C97: Production Worker | D97: =IF('1.1 Summary'!$C$14="Non-Carbonated",0,'3.3 Carbonation'!F56) -> 0 | E97: ='3.3 Carbonation'!G56 -> 0 | F97: =D97/$D$118 -> 0 | H97: =IF('1.1 Summary'!$C$14="Non-Carbonated",0,'3.3 Carbonation'!F63) -> 0 | I97: ='3.3 Carbonation'!G63 -> 0 | J97: =H97/$H$118 -> 0
C98: Total labor Cost | D98: =SUM(D94:D97) -> 0 | E98: =SUM(E94:E97) -> 0 | F98: =SUM(F94:F97) -> 0 | H98: =SUM(H94:H97) -> 0 | I98: =SUM(I94:I97) -> 0 | J98: =SUM(J94:J97) -> 0
C100: Total Carbonation Process Costs | D100: =SUM(D98,D91,D86) -> 0 | E100: =SUM(E98,E91,E86) -> 0 | F100: =SUM(F98,F91,F86) -> 0 | H100: =SUM(H98,H91,H86) -> 0 | I100: =SUM(I98,I91,I86) -> 0 | J100: =SUM(J98,J91,J86) -> 0
C102: Total Process Cost | D102: =SUM(D25,D100,D81,D62,D43) -> 80.340888 | E102: =SUM(E25,E100,E81,E62,E43) -> 45.479555 | F102: =SUM(F43,F100,F81,F62,F25) -> 0.49170502 | H102: =SUM(H25,H43,H62,H81,H100) -> 87.045324 | I102: =SUM(I25,I100,I81,I62,I43) -> 30.907341 | J102: =SUM(J43,J100,J81,J62,J25) -> 0.49589514
B104: Other Overhead Costs | C104: Other Overhead Cost | D104: Total Hourly Cost (€) | E104: Total Cost per MT (€/MT) | F104: Percentage of the Total Cost (%) | H104: Total Hourly Cost (€) | I104: Total Cost per MT (€/MT) | J104: Percentage of the Total Cost (%)
C105: Selling and General Administrative Expenses | D105: ='Assumption & Analysis'!E80*D102 -> 48.204533 | E105: ='Assumption & Analysis'!E80*E102 -> 27.287733 | F105: =D105/$D$118 -> 0.29502301 | H105: ='Assumption & Analysis'!E80*H102 -> 52.227195 | I105: ='Assumption & Analysis'!E80*I102 -> 18.544404 | J105: =H105/H118 -> 0.29753709
C106: Other Depreciation Costs | D106: ='Assumption & Analysis'!$E$82*(SUM('Assumption & Analysis'!$G$31+'Assumption & Analysis'!$G$35+'Assumption & Analysis'!$G$34))/('Labour Data – France'!C$10*3) -> 10.985106 | E106: =(D106*SUM('3.1 Water Treatment'!C27+'3.2 Syrup Preparation'!C27+'3.4 Mixing'!C27+'3.5 Pasteurisation'!C27+'3.3 Carbonation'!C27))/IF('1.1 Summary'!$C$20="Small-scale",'Assumption & Analysis'!E49,IF('1.1 Summary'!$C$20="Medium-scale",'Assumption & Analysis'!E50,'Assumption & Analysis'!E51)) -> 21.227331 | F106: =D106/$D$118 -> 0.067231414 | H106: ='Assumption & Analysis'!$E$82*(SUM('Assumption & Analysis'!$G$31+'Assumption & Analysis'!$G$35+'Assumption & Analysis'!$G$34))/('Labour Data – France'!D$10*3) -> 10.985106 | I106: =(H106*SUM('3.1 Water Treatment'!D27+'3.2 Syrup Preparation'!D27+'3.4 Mixing'!D27+'3.5 Pasteurisation'!D27+'3.3 Carbonation'!D27))/IF('1.1 Summary'!$C$20="Small-scale",'Assumption & Analysis'!E49,IF('1.1 Summary'!$C$20="Medium-scale",'Assumption & Analysis'!E50,'Assumption & Analysis'!E51)) -> 13.345309 | J106: =H106/H118 -> 0.062581885
C107: Total Other Overhead Costs | D107: =SUM(D105:D106) -> 59.189639 | E107: =SUM(E105:E106) -> 48.515064 | F107: =SUM(F105:F106) -> 0.36225442 | H107: =SUM(H105:H106) -> 63.2123 | I107: =SUM(I105:I106) -> 31.889713 | J107: =SUM(J105:J106) -> 0.36011897
B110: Other Indirect Costs | C110: Other Indirect Cost | D110: Total Hourly Cost (€) | E110: Total Cost per MT (€/MT) | F110: Percentage of the Total Cost (%) | H110: Total Hourly Cost (€) | I110: Total Cost per MT (€/MT) | J110: Percentage of the Total Cost (%)
C111: Maintenance and Repair Cost | D111: =('Assumption & Analysis'!$E$87*SUM('Appendix - Equipment'!E14,((SUM('Assumption & Analysis'!$G$31+'Assumption & Analysis'!$G$34+'Assumption & Analysis'!$G$35))/3)))/'Labour Data – France'!C$10 -> 7.3228342 | E111: =(D111*SUM('3.1 Water Treatment'!C27+'3.2 Syrup Preparation'!C27+'3.4 Mixing'!C27+'3.5 Pasteurisation'!C27+'3.3 Carbonation'!C27))/IF('1.1 Summary'!$C$20="Small-scale",'Assumption & Analysis'!$E$49,IF('1.1 Summary'!$C$20="Medium-scale",'Assumption & Analysis'!$E$50,'Assumption & Analysis'!$E$51)) -> 14.150454 | F111: =D111/$D$118 -> 0.044817457 | H111: =('Assumption & Analysis'!$E$87*SUM('Appendix - Equipment'!$I$14,((SUM('Assumption & Analysis'!$G$31+'Assumption & Analysis'!$G$34+'Assumption & Analysis'!$G$35))/3)))/'Labour Data – France'!D$10 -> 7.72023 | I111: =(H111*SUM('3.1 Water Treatment'!D27+'3.2 Syrup Preparation'!D27+'3.4 Mixing'!D27+'3.5 Pasteurisation'!D27+'3.3 Carbonation'!D27))/IF('1.1 Summary'!$C$20="Small-scale",'Assumption & Analysis'!$E$49,IF('1.1 Summary'!$C$20="Medium-scale",'Assumption & Analysis'!$E$50,'Assumption & Analysis'!$E$51)) -> 9.3789591 | J111: =H111/H$118 -> 0.043981967
C112: Finance Cost | D112: =('Assumption & Analysis'!$E$88*SUM('Appendix - Equipment'!E14,((SUM('Assumption & Analysis'!$G$31+'Assumption & Analysis'!$G$34+'Assumption & Analysis'!$G$35))/3)))/'Labour Data – France'!C$10 -> 12.522046 | E112: =(D112*SUM('3.1 Water Treatment'!C27+'3.2 Syrup Preparation'!C27+'3.4 Mixing'!C27+'3.5 Pasteurisation'!C27+'3.3 Carbonation'!C27))/IF('1.1 Summary'!$C$20="Small-scale",'Assumption & Analysis'!$E$49,IF('1.1 Summary'!$C$20="Medium-scale",'Assumption & Analysis'!$E$50,'Assumption & Analysis'!$E$51)) -> 24.197276 | F112: =D112/$D$118 -> 0.076637852 | H112: =('Assumption & Analysis'!$E$88*SUM('Appendix - Equipment'!$I$14,((SUM('Assumption & Analysis'!$G$31+'Assumption & Analysis'!$G$34+'Assumption & Analysis'!$G$35))/3)))/'Labour Data – France'!D$10 -> 13.201593 | I112: =(H112*SUM('3.1 Water Treatment'!D27+'3.2 Syrup Preparation'!D27+'3.4 Mixing'!D27+'3.5 Pasteurisation'!D27+'3.3 Carbonation'!D27))/IF('1.1 Summary'!$C$20="Small-scale",'Assumption & Analysis'!$E$49,IF('1.1 Summary'!$C$20="Medium-scale",'Assumption & Analysis'!$E$50,'Assumption & Analysis'!$E$51)) -> 16.03802 | J112: =H112/H$118 -> 0.075209163
C113: Others (Tax, insurance and other expenses) | D113: ='Assumption & Analysis'!$E$89*D102 -> 4.0170444 | E113: ='Assumption & Analysis'!$E$89*'2.1 Cost Model Processes'!E102 -> 2.2739778 | F113: =D113/$D$118 -> 0.024585251 | H113: ='Assumption & Analysis'!$E$89*H102 -> 4.3522662 | I113: ='Assumption & Analysis'!$E$89*'2.1 Cost Model Processes'!I102 -> 1.545367 | J113: =H113/H$118 -> 0.024794757
C114: Total Other Indirect Costs | D114: =SUM(D111:D113) -> 23.861925 | E114: =SUM(E111:E113) -> 40.621707 | F114: =SUM(F111:F113) -> 0.14604056 | H114: =SUM(H111:H113) -> 25.27409 | I114: =SUM(I111:I113) -> 26.962346 | J114: =SUM(J111:J113) -> 0.14398589
C115: Total Overhead and Indirect Cost | D115: =SUM(D107,D114) -> 83.051564 | E115: =SUM(E107,E114) -> 89.136771 | F115: =SUM(F107,F114) -> 0.50829498 | H115: =SUM(H107,H114) -> 88.48639 | I115: =SUM(I107,I114) -> 58.85206 | J115: =SUM(J107,J114) -> 0.50410486
D117: Total Hourly Cost (€) | E117: Total Cost per MT (€/MT) | F117: Percentage of the Total Cost (%) | H117: Total Hourly Cost (€) | I117: Total Cost per MT (€/MT) | J117: Percentage of the Total Cost (%)
C118: Total Production Cost | D118: =D115+D102 -> 163.39245 | E118: =E115+E102 -> 134.61633 | F118: =F115+F102 -> 1 | H118: =H115+H102 -> 175.53171 | I118: =I115+I102 -> 89.7594 | J118: =J115+J102 -> 1
A121: Copyright © 2025 WNS (Holdings) Ltd. All rights reserved.

Sheet 2.1 Cost Model Processes (2)
C5: Summary – Process Cost
D7: Semi-Automatic | H7: Automatic
B9: Water Treatment Process | C9: Water Treatment
C10: Machinery | D10: Total Hourly Cost (€) | E10: Total Depreciation per MT (€/MT) | F10: Percentage of the Total Cost (%) | H10: Total Hourly Cost (€) | I10: Total Depreciation per MT (€/MT) | J10: Percentage of the Total Cost (%)
C11: Reverse Osmosis Water Treatment Machine | D11: ='3.1 Water Treatment (2)'!F33 -> 0.91796875 | E11: ='3.1 Water Treatment (2)'!G33 -> 0.39608514 | F11: =D11/$D$118 -> 0.0055621048 | H11: ='3.1 Water Treatment (2)'!F37 -> 1.09375 | I11: ='3.1 Water Treatment (2)'!G37 -> 0.31153093 | J11: =H11/$H$118 -> 0.0061895902
C12: Total Machinery Cost | D12: =SUM(D11:D11) -> 0.91796875 | E12: =SUM(E11:E11) -> 0.39608514 | F12: =SUM(F11:F11) -> 0.0055621048 | H12: =SUM(H11:H11) -> 1.09375 | I12: =SUM(I11:I11) -> 0.31153093 | J12: =SUM(J11:J11) -> 0.0061895902
C14: Utility | D14: Total Hourly Cost (€) | E14: Total Cost per MT (€/MT) | F14: Percentage of the Total Cost (%) | H14: Total Hourly Cost (€) | I14: Total Cost per MT (€/MT) | J14: Percentage of the Total Cost (%)
C15: Electricity and Natural Gas Cost | D15: ='3.1 Water Treatment (2)'!F44 -> 7.9681827 | E15: ='3.1 Water Treatment (2)'!G44 -> 3.4381114 | F15: =D15/$D$118 -> 0.048280366 | H15: ='3.1 Water Treatment (2)'!F48 -> 8.897212 | I15: ='3.1 Water Treatment (2)'!G48 -> 2.5341776 | J15: =H15/$H$118 -> 0.050349802
C16: Other Utility Cost | D16: =15%*D15 -> 1.1952274 | E16: =15%*E15 -> 0.51571671 | F16: =D16/$D$118 -> 0.0072420549 | H16: =15%*H15 -> 1.3345818 | I16: =15%*I15 -> 0.38012664 | J16: =H16/$H$118 -> 0.0075524703
C17: Total Utility Cost | D17: =SUM(D15:D16) -> 9.1634102 | E17: =SUM(E15:E16) -> 3.9538281 | F17: =SUM(F15:F16) -> 0.055522421 | H17: =SUM(H15:H16) -> 10.231794 | I17: =SUM(I15:I16) -> 2.9143043 | J17: =SUM(J15:J16) -> 0.057902272
C19: Labour Cost | D19: Total Hourly Cost (€) | E19: Total Cost per MT (€/MT) | F19: Percentage of the Total Cost (%) | H19: Total Hourly Cost (€) | I19: Total Cost per MT (€/MT) | J19: Percentage of the Total Cost (%)
C20: Production Manager | D20: ='3.1 Water Treatment (2)'!F53 -> 2.2505195 | E20: ='3.1 Water Treatment (2)'!G53 -> 0.9710541 | F20: =D20/$D$118 -> 0.013636221 | H20: ='3.1 Water Treatment (2)'!F60 -> 2.2505195 | I20: ='3.1 Water Treatment (2)'!G60 -> 0.64101159 | J20: =H20/$H$118 -> 0.012735811
C21: Shift Supervisor | D21: ='3.1 Water Treatment (2)'!F54 -> 1.8653017 | E21: ='3.1 Water Treatment (2)'!G54 -> 0.80484035 | F21: =D21/$D$118 -> 0.011302132 | H21: ='3.1 Water Treatment (2)'!F61 -> 1.8653017 | I21: ='3.1 Water Treatment (2)'!G61 -> 0.53129068 | J21: =H21/$H$118 -> 0.010555843
C22: Machine Operator | D22: ='3.1 Water Treatment (2)'!F55 -> 1.1616204 | E22: ='3.1 Water Treatment (2)'!G55 -> 0.50121597 | F22: =D22/$D$118 -> 0.0070384255 | H22: ='3.1 Water Treatment (2)'!F62 -> 1.1616204 | I22: ='3.1 Water Treatment (2)'!G62 -> 0.33086236 | J22: =H22/$H$118 -> 0.0065736726
C23: Production Worker | D23: ='3.1 Water Treatment (2)'!F56 -> 2.214619 | E23: ='3.1 Water Treatment (2)'!G56 -> 0.95556378 | F23: =D23/$D$118 -> 0.013418695 | H23: ='3.1 Water Treatment (2)'!F63 -> 2.214619 | I23: ='3.1 Water Treatment (2)'!G63 -> 0.63078613 | J23: =H23/$H$118 -> 0.012532648
C24: Total labor Cost | D24: =SUM(D20:D23) -> 7.4920606 | E24: =SUM(E20:E23) -> 3.2326742 | F24: =SUM(F20:F23) -> 0.045395474 | H24: =SUM(H20:H23) -> 7.4920606 | I24: =SUM(I20:I23) -> 2.1339508 | J24: =SUM(J20:J23) -> 0.042397975
C25: Total Water Treatment Process Costs | D25: =SUM(D12,D17,D24) -> 17.57344 | E25: =SUM(E12,E17,E24) -> 7.5825874 | F25: =SUM(F17,F12,F24) -> 0.10648 | H25: =SUM(H17,H12,H24) -> 18.817604 | I25: =SUM(I17,I12,I24) -> 5.359786 | J25: =SUM(J24+J12+J17) -> 0.10648984
B27: Syrup Preparation Process | C27: Syrup Preparation
C28: Machinery | D28: Total Hourly Cost (€) | E28: Total Depreciation per MT (€/MT) | F28: Percentage of the Total Cost (%) | H28: Total Hourly Cost (€) | I28: Total Depreciation per MT (€/MT) | J28: Percentage of the Total Cost (%)
C29: Jacket Mixing Tank with High Shear Mixer | D29: ='3.2 Syrup Preparation (2)'!F33 -> 0.1171875 | E29: ='3.2 Syrup Preparation (2)'!G33 -> 0.05944577 | F29: =D29/$D$118 -> 0.00071005593 | H29: ='3.2 Syrup Preparation (2)'!F38 -> 1.328125 | I29: ='3.2 Syrup Preparation (2)'!G38 -> 0.46176119 | J29: =H29/$H$118 -> 0.0075159309
C30: Total Machinery Cost | D30: =SUM(D29:D29) -> 0.1171875 | E30: =SUM(E29:E29) -> 0.05944577 | F30: =SUM(F29:F29) -> 0.00071005593 | H30: =SUM(H29:H29) -> 1.328125 | I30: =SUM(I29:I29) -> 0.46176119 | J30: =SUM(J29:J29) -> 0.0075159309
C32: Utility | D32: Total Hourly Cost (€) | E32: Total Cost per MT (€/MT) | F32: Percentage of the Total Cost (%) | H32: Total Hourly Cost (€) | I32: Total Cost per MT (€/MT) | J32: Percentage of the Total Cost (%)
C33: Electricity and Natural Gas Cost | D33: ='3.2 Syrup Preparation (2)'!F44 -> 10.525001 | E33: ='3.2 Syrup Preparation (2)'!G44 -> 5.3390234 | F33: =D33/$D$118 -> 0.063772498 | H33: ='3.2 Syrup Preparation (2)'!F48 -> 11.377274 | I33: ='3.2 Syrup Preparation (2)'!G48 -> 3.9556394 | J33: =H33/$H$118 -> 0.064384607
C34: Other Utility Cost | D34: =15%*D33 -> 1.5787502 | E34: =15%*E33 -> 0.80085351 | F34: =D34/$D$118 -> 0.0095658747 | H34: =15%*H33 -> 1.7065911 | I34: =15%*I33 -> 0.59334591 | J34: =H34/$H$118 -> 0.009657691
C35: Total Utility Cost | D35: =SUM(D33:D34) -> 12.103751 | E35: =SUM(E33:E34) -> 6.1398769 | F35: =SUM(F33:F34) -> 0.073338373 | H35: =SUM(H33:H34) -> 13.083865 | I35: =SUM(I33:I34) -> 4.5489853 | J35: =SUM(J33:J34) -> 0.074042298
C37: Labour Cost | D37: Total Hourly Cost (€) | E37: Total Cost per MT (€/MT) | F37: Percentage of the Total Cost (%) | H37: Total Hourly Cost (€) | I37: Total Cost per MT (€/MT) | J37: Percentage of the Total Cost (%)
C38: Production Manager | D38: ='3.2 Syrup Preparation (2)'!F53 -> 2.2505195 | E38: ='3.2 Syrup Preparation (2)'!G53 -> 1.1416223 | F38: =D38/$D$118 -> 0.013636221 | H38: ='3.2 Syrup Preparation (2)'!F60 -> 2.2505195 | I38: ='3.2 Syrup Preparation (2)'!G60 -> 0.78245838 | J38: =H38/$H$118 -> 0.012735811
C39: Shift Supervisor | D39: ='3.2 Syrup Preparation (2)'!F54 -> 1.8653017 | E39: ='3.2 Syrup Preparation (2)'!G54 -> 0.94621266 | F39: =D39/$D$118 -> 0.011302132 | H39: ='3.2 Syrup Preparation (2)'!F61 -> 1.8653017 | I39: ='3.2 Syrup Preparation (2)'!G61 -> 0.64852625 | J39: =H39/$H$118 -> 0.010555843
C40: Machine Operator | D40: ='3.2 Syrup Preparation (2)'!F55 -> 1.1616204 | E40: ='3.2 Syrup Preparation (2)'!G55 -> 0.58925586 | F40: =D40/$D$118 -> 0.0070384255 | H40: ='3.2 Syrup Preparation (2)'!F62 -> 2.3232409 | I40: ='3.2 Syrup Preparation (2)'!G62 -> 0.8077421 | J40: =H40/$H$118 -> 0.013147345
C41: Production Worker | D41: ='3.2 Syrup Preparation (2)'!F56 -> 2.214619 | E41: ='3.2 Syrup Preparation (2)'!G56 -> 1.1234111 | F41: =D41/$D$118 -> 0.013418695 | H41: ='3.2 Syrup Preparation (2)'!F63 -> 2.214619 | I41: ='3.2 Syrup Preparation (2)'!G63 -> 0.76997655 | J41: =H41/$H$118 -> 0.012532648
C42: Total labor Cost | D42: =SUM(D38:D41) -> 7.4920606 | E42: =SUM(E38:E41) -> 3.8005019 | F42: =SUM(F38:F41) -> 0.045395474 | H42: =SUM(H38:H41) -> 8.6536811 | I42: =SUM(I38:I41) -> 3.0087033 | J42: =SUM(J38:J41) -> 0.048971647
C43: Total Syrup Preparation Process Costs | D43: =SUM(D30,D35,D42) -> 19.713 | E43: =SUM(E30,E35,E42) -> 9.9998246 | F43: =SUM(F42,F30,F35) -> 0.1194439 | H43: =SUM(H42,H35,H30) -> 23.065671 | I43: =SUM(I42,I35,I30) -> 8.0194498 | J43: =SUM(J30,J35,J42) -> 0.13052988
B45: Mixing Process | C45: Mixing Process
C46: Machinery | D46: Total Hourly Cost (€) | E46: Total Depreciation per MT (€/MT) | F46: Percentage of the Total Cost (%) | H46: Total Hourly Cost (€) | I46: Total Depreciation per MT (€/MT) | J46: Percentage of the Total Cost (%)
C47: Pressure Blending Tank | D47: ='3.4 Mixing (2)'!F33 -> 0.78125 | E47: ='3.4 Mixing (2)'!G33 -> 0.12001063 | F47: =D47/$D$118 -> 0.0047337062 | H47: ='3.4 Mixing (2)'!F38 -> 0.91796875 | I47: ='3.4 Mixing (2)'!G38 -> 0.049434317 | J47: =H47/$H$118 -> 0.0051948346
C48: Total Machinery Cost | D48: =SUM(D47) -> 0.78125 | E48: =SUM(E47) -> 0.12001063 | F48: =SUM(F47:F47) -> 0.0047337062 | H48: =SUM(H47:H47) -> 0.91796875 | I48: =SUM(I47:I47) -> 0.049434317 | J48: =SUM(J47:J47) -> 0.0051948346
C50: Utility | D50: Total Hourly Cost (€) | E50: Total Cost per MT (€/MT) | F50: Percentage of the Total Cost (%) | H50: Total Hourly Cost (€) | I50: Total Cost per MT (€/MT) | J50: Percentage of the Total Cost (%)
C51: Electricity and Natural Gas Cost | D51: ='3.4 Mixing (2)'!F44 -> 3.7068185 | E51: ='3.4 Mixing (2)'!G44 -> 0.56941775 | F51: =D51/$D$118 -> 0.022460147 | H51: ='3.4 Mixing (2)'!F48 -> 4.5590914 | I51: ='3.4 Mixing (2)'!G48 -> 0.24551551 | J51: =H51/$H$118 -> 0.025800144
C52: Other Utility Cost | D52: =15%*D51 -> 0.55602278 | E52: =15%*E51 -> 0.085412662 | F52: =D52/$D$118 -> 0.0033690221 | H52: =15%*H51 -> 0.68386371 | I52: =15%*I51 -> 0.036827327 | J52: =H52/$H$118 -> 0.0038700215
C53: Total Utility Cost | D53: =SUM(D51:D52) -> 4.2628413 | E53: =SUM(E51:E52) -> 0.65483041 | F53: =SUM(F51:F52) -> 0.025829169 | H53: =SUM(H51:H52) -> 5.2429551 | I53: =SUM(I51:I52) -> 0.28234284 | J53: =SUM(J51:J52) -> 0.029670165
C55: Labour Cost | D55: Total Hourly Cost (€) | E55: Total Cost per MT (€/MT) | F55: Percentage of the Total Cost (%) | H55: Total Hourly Cost (€) | I55: Total Cost per MT (€/MT) | J55: Percentage of the Total Cost (%)
C56: Production Manager | D56: ='3.4 Mixing (2)'!F53 -> 2.2505195 | E56: ='3.4 Mixing (2)'!G53 -> 0.3457104 | F56: =D56/$D$118 -> 0.013636221 | H56: ='3.4 Mixing (2)'!F60 -> 2.2505195 | I56: ='3.4 Mixing (2)'!G60 -> 0.12119464 | J56: =H56/$H$118 -> 0.012735811
C57: Shift Supervisor | D57: ='3.4 Mixing (2)'!F54 -> 1.8653017 | E57: ='3.4 Mixing (2)'!G54 -> 0.28653571 | F57: =D57/$D$118 -> 0.011302132 | H57: ='3.4 Mixing (2)'!F61 -> 1.8653017 | I57: ='3.4 Mixing (2)'!G61 -> 0.10044995 | J57: =H57/$H$118 -> 0.010555843
C58: Machine Operator | D58: ='3.4 Mixing (2)'!F55 -> 1.1616204 | E58: ='3.4 Mixing (2)'!G55 -> 0.1784407 | F58: =D58/$D$118 -> 0.0070384255 | H58: ='3.4 Mixing (2)'!F62 -> 1.1616204 | I58: ='3.4 Mixing (2)'!G62 -> 0.062555412 | J58: =H58/$H$118 -> 0.0065736726
C59: Production Worker | D59: ='3.4 Mixing (2)'!F56 -> 2.214619 | E59: ='3.4 Mixing (2)'!G56 -> 0.3401956 | F59: =D59/$D$118 -> 0.013418695 | H59: ='3.4 Mixing (2)'!F63 -> 2.214619 | I59: ='3.4 Mixing (2)'!G63 -> 0.11926134 | J59: =H59/$H$118 -> 0.012532648
C60: Total Labour Cost | D60: =SUM(D56:D59) -> 7.4920606 | E60: =SUM(E56:E59) -> 1.1508824 | F60: =SUM(F56:F59) -> 0.045395474 | H60: =SUM(H56:H59) -> 7.4920606 | I60: =SUM(I56:I59) -> 0.40346134 | J60: =SUM(J56:J59) -> 0.042397975
C62: Total Mixing Process Costs | D62: =SUM(D60,D53,D48) -> 12.536152 | E62: =SUM(E60,E53,E48) -> 1.9257235 | F62: =SUM(F60,F53,F48) -> 0.075958349 | H62: =SUM(H60,H53,H48) -> 13.652984 | I62: =SUM(I60,I53,I48) -> 0.7352385 | J62: =SUM(J60,J53,J48) -> 0.077262974
B64: Pasteurisation Process | C64: Pasteurisation Process
C65: Machinery | D65: Total Hourly Cost (€) | E65: Total Depreciation per MT (€/MT) | F65: Percentage of the Total Cost (%) | H65: Total Hourly Cost (€) | I65: Total Depreciation per MT (€/MT) | J65: Percentage of the Total Cost (%)
C66: Pasteuriser | D66: =IF('1.2 Scenario Analysis'!$H$14="Can",0,'3.5 Pasteurisation (2)'!F33) -> 1.5917969 | E66: =IF('1.2 Scenario Analysis'!$H$14="Can",0,'3.5 Pasteurisation (2)'!G33) -> 1.3371249 | F66: =D66/$D$118 -> 0.0096449264 | H66: =IF('1.2 Scenario Analysis'!$H$14="Can",0,'3.5 Pasteurisation (2)'!F38) -> 1.7089844 | I66: =IF('1.2 Scenario Analysis'!$H$14="Can",0,'3.5 Pasteurisation (2)'!G38) -> 0.90319094 | J66: =H66/$H$118 -> 0.0096712346
C67: Total Machinery Cost | D67: =SUM(D66) -> 1.5917969 | E67: =SUM(E66) -> 1.3371249 | F67: =SUM(F66) -> 0.0096449264 | H67: =SUM(H66:H66) -> 1.7089844 | I67: =SUM(I66:I66) -> 0.90319094 | J67: =SUM(J66) -> 0.0096712346
C69: Utility | D69: Total Hourly Cost (€) | E69: Total Cost per MT (€/MT) | F69: Percentage of the Total Cost (%) | H69: Total Hourly Cost (€) | I69: Total Cost per MT (€/MT) | J69: Percentage of the Total Cost (%)
C70: Electricity and Natural Gas Cost | D70: =IF('1.2 Scenario Analysis'!$H$14="Can",0,'3.5 Pasteurisation (2)'!F44) -> 19.506819 | E70: =IF('1.2 Scenario Analysis'!$H$14="Can",0,'3.5 Pasteurisation (2)'!G44) -> 16.385918 | F70: =D70/$D$118 -> 0.11819462 | H70: =IF('1.2 Scenario Analysis'!$H$14="Can",0,'3.5 Pasteurisation (2)'!F48) -> 20.018183 | I70: =IF('1.2 Scenario Analysis'!$H$14="Can",0,'3.5 Pasteurisation (2)'!G48) -> 10.579524 | J70: =H70/$H$118 -> 0.11328397
C71: Other Utility Cost | D71: =15%*D70 -> 2.9260229 | E71: =15%*E70 -> 2.4578877 | F71: =D71/$D$118 -> 0.017729194 | H71: =15%*H70 -> 3.0027274 | I71: =15%*I70 -> 1.5869286 | J71: =H71/$H$118 -> 0.016992596
C72: Total Utility Cost | D72: =SUM(D70:D71) -> 22.432842 | E72: =SUM(E70:E71) -> 18.843805 | F72: =SUM(F70:F71) -> 0.13592382 | H72: =SUM(H70:H71) -> 23.02091 | I72: =SUM(I70:I71) -> 12.166453 | J72: =SUM(J70:J71) -> 0.13027657
C74: Labour Cost | D74: Total Hourly Cost (€) | E74: Total Cost per MT (€/MT) | F74: Percentage of the Total Cost (%) | H74: Total Hourly Cost (€) | I74: Total Cost per MT (€/MT) | J74: Percentage of the Total Cost (%)
C75: Production Manager | D75: =IF('1.2 Scenario Analysis'!$H$14="Can",0,'3.5 Pasteurisation (2)'!F53) -> 2.2505195 | E75: =IF('1.2 Scenario Analysis'!$H$14="Can",0,'3.5 Pasteurisation (2)'!G53) -> 1.8904582 | F75: =D75/$D$118 -> 0.013636221 | H75: =IF('1.2 Scenario Analysis'!$H$14="Can",0,'3.5 Pasteurisation (2)'!F60) -> 2.2505195 | I75: =IF('1.2 Scenario Analysis'!$H$14="Can",0,'3.5 Pasteurisation (2)'!G60) -> 1.1893899 | J75: =H75/$H$118 -> 0.012735811
C76: Shift Supervisor | D76: =IF('1.2 Scenario Analysis'!$H$14="Can",0,'3.5 Pasteurisation (2)'!F54) -> 1.8653017 | E76: =IF('1.2 Scenario Analysis'!$H$14="Can",0,'3.5 Pasteurisation (2)'!G54) -> 1.5668716 | F76: =D76/$D$118 -> 0.011302132 | H76: =IF('1.2 Scenario Analysis'!$H$14="Can",0,'3.5 Pasteurisation (2)'!F61) -> 1.8653017 | I76: =IF('1.2 Scenario Analysis'!$H$14="Can",0,'3.5 Pasteurisation (2)'!G61) -> 0.98580398 | J76: =H76/$H$118 -> 0.010555843
C77: Machine Operator | D77: =IF('1.2 Scenario Analysis'!$H$14="Can",0,'3.5 Pasteurisation (2)'!F55) -> 1.1616204 | E77: =IF('1.2 Scenario Analysis'!$H$14="Can",0,'3.5 Pasteurisation (2)'!G55) -> 0.97577247 | F77: =D77/$D$118 -> 0.0070384255 | H77: =IF('1.2 Scenario Analysis'!$H$14="Can",0,'3.5 Pasteurisation (2)'!F62) -> 1.1616204 | I77: =IF('1.2 Scenario Analysis'!$H$14="Can",0,'3.5 Pasteurisation (2)'!G62) -> 0.61391144 | J77: =H77/$H$118 -> 0.0065736726
C78: Production Worker | D78: =IF('1.2 Scenario Analysis'!$H$14="Can",0,'3.5 Pasteurisation (2)'!F56) -> 2.214619 | E78: =IF('1.2 Scenario Analysis'!$H$14="Can",0,'3.5 Pasteurisation (2)'!G56) -> 1.8603015 | F78: =D78/$D$118 -> 0.013418695 | H78: =IF('1.2 Scenario Analysis'!$H$14="Can",0,'3.5 Pasteurisation (2)'!F63) -> 2.214619 | I78: =IF('1.2 Scenario Analysis'!$H$14="Can",0,'3.5 Pasteurisation (2)'!G63) -> 1.1704167 | J78: =H78/$H$118 -> 0.012532648
C79: Total labor Cost | D79: =SUM(D75:D78) -> 7.4920606 | E79: =SUM(E75:E78) -> 6.2934038 | F79: =SUM(F75:F78) -> 0.045395474 | H79: =SUM(H75:H78) -> 7.4920606 | I79: =SUM(I75:I78) -> 3.959522 | J79: =SUM(J75:J78) -> 0.042397975
C81: Total Pasteurisation Process Cost | D81: =SUM(D79,D72,D67) -> 31.516699 | E81: =SUM(E79,E72,E67) -> 26.474334 | F81: =SUM(F79,F72,F67) -> 0.19096422 | H81: =SUM(H79,H72,H67) -> 32.221955 | I81: =SUM(I79,I72,I67) -> 17.029166 | J81: =SUM(J79,J72,J67) -> 0.18234578
B83: Carbonation Process | C83: Carbonation Process
C84: Machinery | D84: Total Hourly Cost (€) | E84: Total Depreciation per MT (€/MT) | F84: Percentage of the Total Cost (%) | H84: Total Hourly Cost (€) | I84: Total Depreciation per MT (€/MT) | J84: Percentage of the Total Cost (%)
C85: Carbonation Maker | D85: =IF('1.2 Scenario Analysis'!$H$13="Non-Carbonated",0,'3.3 Carbonation (2)'!F34) -> 0 | E85: =IF('1.2 Scenario Analysis'!$H$13="Non-Carbonated",0,'3.3 Carbonation (2)'!G34) -> 0 | F85: =D85/$D$118 -> 0 | H85: =IF('1.2 Scenario Analysis'!$H$13="Non-Carbonated",0,'3.3 Carbonation (2)'!F38) -> 0 | I85: =IF('1.2 Scenario Analysis'!$H$13="Non-Carbonated",0,'3.3 Carbonation (2)'!G38) -> 0 | J85: =H85/$H$118 -> 0
C86: Total Machinery Cost | D86: =SUM(D85) -> 0 | E86: =SUM(E85) -> 0 | F86: =SUM(F85:F85) -> 0 | H86: =SUM(H85) -> 0 | I86: =SUM(I85) -> 0 | J86: =SUM(J85:J85) -> 0
C88: Utility | D88: Total Hourly Cost (€) | E88: Total Cost per MT (€/MT) | F88: Percentage of the Total Cost (%) | H88: Total Hourly Cost (€) | I88: Total Cost per MT (€/MT) | J88: Percentage of the Total Cost (%)
C89: Electricity and Natural Gas Cost | D89: =IF('1.2 Scenario Analysis'!$H$13="Non-Carbonated",0,'3.3 Carbonation (2)'!F44) -> 0 | E89: =IF('1.2 Scenario Analysis'!$H$13="Non-Carbonated",0,'3.3 Carbonation (2)'!G44) -> 0 | F89: =D89/$D$118 -> 0 | H89: =IF('1.2 Scenario Analysis'!$H$13="Non-Carbonated",0,'3.3 Carbonation (2)'!F48) -> 0 | I89: =IF('1.2 Scenario Analysis'!$H$13="Non-Carbonated",0,'3.3 Carbonation (2)'!G48) -> 0 | J89: =H89/$H$118 -> 0
C90: Other Utility Cost | D90: =15%*D89 -> 0 | E90: =15%*E89 -> 0 | F90: =D90/$D$118 -> 0 | H90: =15%*H89 -> 0 | I90: =15%*I89 -> 0 | J90: =H90/$H$118 -> 0
C91: Total Utility Cost | D91: =SUM(D89:D90) -> 0 | E91: =SUM(E89:E90) -> 0 | F91: =SUM(F89:F90) -> 0 | H91: =SUM(H89:H90) -> 0 | I91: =SUM(I89:I90) -> 0 | J91: =SUM(J89:J90) -> 0
C93: Labour Cost | D93: Total Hourly Cost (€) | E93: Total Cost per MT (€/MT) | F93: Percentage of the Total Cost (%) | H93: Total Hourly Cost (€) | I93: Total Cost per MT (€/MT) | J93: Percentage of the Total Cost (%)
C94: Production Manager | D94: =IF('1.2 Scenario Analysis'!$H$13="Non-Carbonated",0,'3.3 Carbonation (2)'!F53) -> 0 | E94: =IF('1.2 Scenario Analysis'!$H$13="Non-Carbonated",0,'3.3 Carbonation (2)'!G53) -> 0 | F94: =D94/$D$118 -> 0 | H94: =IF('1.2 Scenario Analysis'!$H$13="Non-Carbonated",0,'3.3 Carbonation (2)'!F60) -> 0 | I94: =IF('1.2 Scenario Analysis'!$H$13="Non-Carbonated",0,'3.3 Carbonation (2)'!G60) -> 0 | J94: =H94/$H$118 -> 0
C95: Shift Supervisor | D95: =IF('1.2 Scenario Analysis'!$H$13="Non-Carbonated",0,'3.3 Carbonation (2)'!F54) -> 0 | E95: =IF('1.2 Scenario Analysis'!$H$13="Non-Carbonated",0,'3.3 Carbonation (2)'!G54) -> 0 | F95: =D95/$D$118 -> 0 | H95: =IF('1.2 Scenario Analysis'!$H$13="Non-Carbonated",0,'3.3 Carbonation (2)'!F61) -> 0 | I95: =IF('1.2 Scenario Analysis'!$H$13="Non-Carbonated",0,'3.3 Carbonation (2)'!G61) -> 0 | J95: =H95/$H$118 -> 0
C96: Machine Operator | D96: =IF('1.2 Scenario Analysis'!$H$13="Non-Carbonated",0,'3.3 Carbonation (2)'!F55) -> 0 | E96: =IF('1.2 Scenario Analysis'!$H$13="Non-Carbonated",0,'3.3 Carbonation (2)'!G55) -> 0 | F96: =D96/$D$118 -> 0 | H96: =IF('1.2 Scenario Analysis'!$H$13="Non-Carbonated",0,'3.3 Carbonation (2)'!F62) -> 0 | I96: =IF('1.2 Scenario Analysis'!$H$13="Non-Carbonated",0,'3.3 Carbonation (2)'!G62) -> 0 | J96: =H96/$H$118 -> 0
C97: Production Worker | D97: =IF('1.2 Scenario Analysis'!$H$13="Non-Carbonated",0,'3.3 Carbonation (2)'!F56) -> 0 | E97: =IF('1.2 Scenario Analysis'!$H$13="Non-Carbonated",0,'3.3 Carbonation (2)'!G56) -> 0 | F97: =D97/$D$118 -> 0 | H97: =IF('1.2 Scenario Analysis'!$H$13="Non-Carbonated",0,'3.3 Carbonation (2)'!F63) -> 0 | I97: =IF('1.2 Scenario Analysis'!$H$13="Non-Carbonated",0,'3.3 Carbonation (2)'!G63) -> 0 | J97: =H97/$H$118 -> 0
C98: Total labor Cost | D98: =SUM(D94:D97) -> 0 | E98: =SUM(E94:E97) -> 0 | F98: =SUM(F94:F97) -> 0 | H98: =SUM(H94:H97) -> 0 | I98: =SUM(I94:I97) -> 0 | J98: =SUM(J94:J97) -> 0
C100: Total Carbonation Process Costs | D100: =SUM(D98,D91,D86) -> 0 | E100: =SUM(E98,E91,E86) -> 0 | F100: =SUM(F98,F91,F86) -> 0 | H100: =SUM(H98,H91,H86) -> 0 | I100: =SUM(I98,I91,I86) -> 0 | J100: =SUM(J98,J91,J86) -> 0
C102: Total Process Cost | D102: =SUM(D25,D100,D81,D62,D43) -> 81.33929 | E102: =SUM(E25,E100,E81,E62,E43) -> 45.982469 | F102: =SUM(F43,F100,F81,F62,F25) -> 0.49284647 | H102: =SUM(H25,H43,H62,H81,H100) -> 87.758215 | I102: =SUM(I25,I100,I81,I62,I43) -> 31.14364 | J102: =SUM(J43,J100,J81,J62,J25) -> 0.49662847
B104: Other Overhead Costs | C104: Other Overhead Cost | D104: Total Hourly Cost (€) | E104: Total Cost per MT (€/MT) | F104: Percentage of the Total Cost (%) | H104: Total Hourly Cost (€) | I104: Total Cost per MT (€/MT) | J104: Percentage of the Total Cost (%)
C105: Selling and General Administrative Expenses | D105: ='Assumption & Analysis'!E80*D102 -> 48.803574 | E105: ='Assumption & Analysis'!E80*E102 -> 27.589482 | F105: =D105/$D$118 -> 0.29570788 | H105: ='Assumption & Analysis'!E80*H102 -> 52.654929 | I105: ='Assumption & Analysis'!E80*I102 -> 18.686184 | J105: =H105/H118 -> 0.29797708
C106: Other Depreciation Costs | D106: ='Assumption & Analysis'!$E$82*(SUM('Assumption & Analysis (2)'!G31,'Assumption & Analysis (2)'!G34,'Assumption & Analysis (2)'!G35))/('Labour Data – France'!C$10*3) -> 10.985106 | E106: =(D106*SUM('3.1 Water Treatment (2)'!C27,'3.2 Syrup Preparation (2)'!C27,'3.3 Carbonation (2)'!C27,'3.4 Mixing (2)'!C27,'3.5 Pasteurisation (2)'!C27))/IF('1.2 Scenario Analysis'!$H$19="Small-scale",'Assumption & Analysis'!E49,IF('1.2 Scenario Analysis'!$H$19="Medium-scale",'Assumption & Analysis'!E50,'Assumption & Analysis'!E51)) -> 21.227331 | F106: =D106/$D$118 -> 0.066560336 | H106: ='Assumption & Analysis'!$E$82*(SUM('Assumption & Analysis (2)'!G31,'Assumption & Analysis (2)'!G34,'Assumption & Analysis (2)'!G35))/('Labour Data – France'!D$10*3) -> 10.985106 | I106: =(H106*SUM('3.1 Water Treatment (2)'!D27,'3.2 Syrup Preparation (2)'!D27,'3.3 Carbonation (2)'!D27,'3.4 Mixing (2)'!D27,'3.5 Pasteurisation (2)'!D27))/IF('1.2 Scenario Analysis'!H19="Small-scale",'Assumption & Analysis'!E49,IF('1.2 Scenario Analysis'!H19="Medium-scale",'Assumption & Analysis'!E50,'Assumption & Analysis'!E51)) -> 13.345309 | J106: =H106/H118 -> 0.062165304
C107: Total Other Overhead Costs | D107: =SUM(D105:D106) -> 59.78868 | E107: =SUM(E105:E106) -> 48.816813 | F107: =SUM(F105:F106) -> 0.36226822 | H107: =SUM(H105:H106) -> 63.640035 | I107: =SUM(I105:I106) -> 32.031493 | J107: =SUM(J105:J106) -> 0.36014238
B110: Other Indirect Costs | C110: Other Indirect Cost | D110: Total Hourly Cost (€) | E110: Total Cost per MT (€/MT) | F110: Percentage of the Total Cost (%) | H110: Total Hourly Cost (€) | I110: Total Cost per MT (€/MT) | J110: Percentage of the Total Cost (%)
C111: Maintenance and Repair Cost | D111: =('Assumption & Analysis'!$E$87*SUM('Appendix - Equipment'!E14,((SUM('Assumption & Analysis (2)'!G31,'Assumption & Analysis (2)'!G34,'Assumption & Analysis (2)'!G35))/3)))/'Labour Data – France'!C$10 -> 7.3228342 | E111: =(D111*SUM('3.1 Water Treatment (2)'!C27,'3.2 Syrup Preparation (2)'!C27,'3.3 Carbonation (2)'!C27,'3.4 Mixing (2)'!C27,'3.5 Pasteurisation (2)'!C27))/IF('1.2 Scenario Analysis'!H19="Small-scale",'Assumption & Analysis'!$E$49,IF('1.2 Scenario Analysis'!H19="Medium-scale",'Assumption & Analysis'!$E$50,'Assumption & Analysis'!$E$51)) -> 14.150454 | F111: =D111/$D$118 -> 0.044370107 | H111: =('Assumption & Analysis'!$E$87*SUM('Appendix - Equipment'!$I$14,((SUM('Assumption & Analysis (2)'!G31,'Assumption & Analysis (2)'!G34,'Assumption & Analysis (2)'!G35))/3)))/'Labour Data – France'!D$10 -> 7.72023 | I111: =(H111*SUM('3.1 Water Treatment (2)'!D27,'3.2 Syrup Preparation (2)'!D27,'3.3 Carbonation (2)'!D27,'3.4 Mixing (2)'!D27,'3.5 Pasteurisation (2)'!D27))/IF('1.2 Scenario Analysis'!H19="Small-scale",'Assumption & Analysis'!$E$49,IF('1.2 Scenario Analysis'!H19="Medium-scale",'Assumption & Analysis'!$E$50,'Assumption & Analysis'!$E$51)) -> 9.3789591 | J111: =H111/H$118 -> 0.043689198
C112: Finance Cost | D112: =('Assumption & Analysis'!$E$88*SUM('Appendix - Equipment'!E14,((SUM('Assumption & Analysis (2)'!G31,'Assumption & Analysis (2)'!G34,'Assumption & Analysis (2)'!G35))/3)))/'Labour Data – France'!C$10 -> 12.522046 | E112: =(D112*SUM('3.1 Water Treatment (2)'!C27,'3.2 Syrup Preparation (2)'!C27,'3.3 Carbonation (2)'!C27,'3.4 Mixing (2)'!C27,'3.5 Pasteurisation (2)'!C27))/IF('1.2 Scenario Analysis'!H19="Small-scale",'Assumption & Analysis'!$E$49,IF('1.2 Scenario Analysis'!H19="Medium-scale",'Assumption & Analysis'!$E$50,'Assumption & Analysis'!$E$51)) -> 24.197276 | F112: =D112/$D$118 -> 0.075872882 | H112: =('Assumption & Analysis'!$E$88*SUM('Appendix - Equipment'!$I$14,((SUM('Assumption & Analysis (2)'!G31,'Assumption & Analysis (2)'!G34,'Assumption & Analysis (2)'!G35))/3)))/'Labour Data – France'!D$10 -> 13.201593 | I112: =(H112*SUM('3.1 Water Treatment (2)'!D27,'3.2 Syrup Preparation (2)'!D27,'3.3 Carbonation (2)'!D27,'3.4 Mixing (2)'!D27,'3.5 Pasteurisation (2)'!D27))/IF('1.2 Scenario Analysis'!H19="Small-scale",'Assumption & Analysis'!$E$49,IF('1.2 Scenario Analysis'!H19="Medium-scale",'Assumption & Analysis'!$E$50,'Assumption & Analysis'!$E$51)) -> 16.03802 | J112: =H112/H$118 -> 0.074708528
C113: Others (Tax, insurance and other expenses) | D113: ='Assumption & Analysis'!$E$89*D102 -> 4.0669645 | E113: ='Assumption & Analysis'!$E$89*'2.1 Cost Model Processes (2)'!E102 -> 2.2991235 | F113: =D113/$D$118 -> 0.024642323 | H113: ='Assumption & Analysis'!$E$89*H102 -> 4.3879108 | I113: ='Assumption & Analysis'!$E$89*'2.1 Cost Model Processes (2)'!I102 -> 1.557182 | J113: =H113/H$118 -> 0.024831423
C114: Total Other Indirect Costs | D114: =SUM(D111:D113) -> 23.911845 | E114: =SUM(E111:E113) -> 40.646853 | F114: =SUM(F111:F113) -> 0.14488531 | H114: =SUM(H111:H113) -> 25.309734 | I114: =SUM(I111:I113) -> 26.974161 | J114: =SUM(J111:J113) -> 0.14322915
C115: Total Overhead and Indirect Cost | D115: =SUM(D107,D114) -> 83.700525 | E115: =SUM(E107,E114) -> 89.463666 | F115: =SUM(F107,F114) -> 0.50715353 | H115: =SUM(H107,H114) -> 88.949769 | I115: =SUM(I107,I114) -> 59.005654 | J115: =SUM(J107,J114) -> 0.50337153
D117: Total Hourly Cost (€) | E117: Total Cost per MT (€/MT) | F117: Percentage of the Total Cost (%) | H117: Total Hourly Cost (€) | I117: Total Cost per MT (€/MT) | J117: Percentage of the Total Cost (%)
C118: Total Production Cost | D118: =D115+D102 -> 165.03982 | E118: =E115+E102 -> 135.44614 | F118: =F115+F102 -> 1 | H118: =H115+H102 -> 176.70798 | I118: =I115+I102 -> 90.149294 | J118: =J115+J102 -> 1
A121: Copyright © 2025 WNS (Holdings) Ltd. All rights reserved.

Sheet 2.1 Cost Model Processes (3)
C5: Summary – Process Cost
D7: Semi-Automatic | H7: Automatic
B9: Water Treatment Process | C9: Water Treatment
C10: Machinery | D10: Total Hourly Cost (€) | E10: Total Depreciation per MT (€/MT) | F10: Percentage of the Total Cost (%) | H10: Total Hourly Cost (€) | I10: Total Depreciation per MT (€/MT) | J10: Percentage of the Total Cost (%)
C11: Reverse Osmosis Water Treatment Machine | D11: ='3.1 Water Treatment (3)'!F33 -> 0.91796875 | E11: ='3.1 Water Treatment (3)'!G33 -> 0.39608514 | F11: =D11/$D$118 -> 0.0055649051 | H11: ='3.1 Water Treatment (3)'!F37 -> 1.09375 | I11: ='3.1 Water Treatment (3)'!G37 -> 0.31153093 | J11: =H11/$H$118 -> 0.0061925005
C12: Total Machinery Cost | D12: =SUM(D11:D11) -> 0.91796875 | E12: =SUM(E11:E11) -> 0.39608514 | F12: =SUM(F11:F11) -> 0.0055649051 | H12: =SUM(H11:H11) -> 1.09375 | I12: =SUM(I11:I11) -> 0.31153093 | J12: =SUM(J11:J11) -> 0.0061925005
C14: Utility | D14: Total Hourly Cost (€) | E14: Total Cost per MT (€/MT) | F14: Percentage of the Total Cost (%) | H14: Total Hourly Cost (€) | I14: Total Cost per MT (€/MT) | J14: Percentage of the Total Cost (%)
C15: Electricity and Natural Gas Cost | D15: ='3.1 Water Treatment (3)'!F44 -> 7.9681827 | E15: ='3.1 Water Treatment (3)'!G44 -> 3.4381114 | F15: =D15/$D$118 -> 0.048304674 | H15: ='3.1 Water Treatment (3)'!F48 -> 8.897212 | I15: ='3.1 Water Treatment (3)'!G48 -> 2.5341776 | J15: =H15/$H$118 -> 0.050373477
C16: Other Utility Cost | D16: =15%*D15 -> 1.1952274 | E16: =15%*E15 -> 0.51571671 | F16: =D16/$D$118 -> 0.0072457011 | H16: =15%*H15 -> 1.3345818 | I16: =15%*I15 -> 0.38012664 | J16: =H16/$H$118 -> 0.0075560215
C17: Total Utility Cost | D17: =SUM(D15:D16) -> 9.1634102 | E17: =SUM(E15:E16) -> 3.9538281 | F17: =SUM(F15:F16) -> 0.055550375 | H17: =SUM(H15:H16) -> 10.231794 | I17: =SUM(I15:I16) -> 2.9143043 | J17: =SUM(J15:J16) -> 0.057929498
C19: Labour Cost | D19: Total Hourly Cost (€) | E19: Total Cost per MT (€/MT) | F19: Percentage of the Total Cost (%) | H19: Total Hourly Cost (€) | I19: Total Cost per MT (€/MT) | J19: Percentage of the Total Cost (%)
C20: Production Manager | D20: ='3.1 Water Treatment (3)'!F53 -> 2.2505195 | E20: ='3.1 Water Treatment (3)'!G53 -> 0.9710541 | F20: =D20/$D$118 -> 0.013643087 | H20: ='3.1 Water Treatment (3)'!F60 -> 2.2505195 | I20: ='3.1 Water Treatment (3)'!G60 -> 0.64101159 | J20: =H20/$H$118 -> 0.012741799
C21: Shift Supervisor | D21: ='3.1 Water Treatment (3)'!F54 -> 1.8653017 | E21: ='3.1 Water Treatment (3)'!G54 -> 0.80484035 | F21: =D21/$D$118 -> 0.011307822 | H21: ='3.1 Water Treatment (3)'!F61 -> 1.8653017 | I21: ='3.1 Water Treatment (3)'!G61 -> 0.53129068 | J21: =H21/$H$118 -> 0.010560806
C22: Machine Operator | D22: ='3.1 Water Treatment (3)'!F55 -> 1.1616204 | E22: ='3.1 Water Treatment (3)'!G55 -> 0.50121597 | F22: =D22/$D$118 -> 0.0070419691 | H22: ='3.1 Water Treatment (3)'!F62 -> 1.1616204 | I22: ='3.1 Water Treatment (3)'!G62 -> 0.33086236 | J22: =H22/$H$118 -> 0.0065767636
C23: Production Worker | D23: ='3.1 Water Treatment (3)'!F56 -> 2.214619 | E23: ='3.1 Water Treatment (3)'!G56 -> 0.95556378 | F23: =D23/$D$118 -> 0.013425451 | H23: ='3.1 Water Treatment (3)'!F63 -> 2.214619 | I23: ='3.1 Water Treatment (3)'!G63 -> 0.63078613 | J23: =H23/$H$118 -> 0.012538541
C24: Total labor Cost | D24: =SUM(D20:D23) -> 7.4920606 | E24: =SUM(E20:E23) -> 3.2326742 | F24: =SUM(F20:F23) -> 0.045418329 | H24: =SUM(H20:H23) -> 7.4920606 | I24: =SUM(I20:I23) -> 2.1339508 | J24: =SUM(J20:J23) -> 0.04241791
C25: Total Water Treatment Process Costs | D25: =SUM(D12,D17,D24) -> 17.57344 | E25: =SUM(E12,E17,E24) -> 7.5825874 | F25: =SUM(F17,F12,F24) -> 0.10653361 | H25: =SUM(H17,H12,H24) -> 18.817604 | I25: =SUM(I17,I12,I24) -> 5.359786 | J25: =SUM(J24+J12+J17) -> 0.10653991
B27: Syrup Preparation Process | C27: Syrup Preparation
C28: Machinery | D28: Total Hourly Cost (€) | E28: Total Depreciation per MT (€/MT) | F28: Percentage of the Total Cost (%) | H28: Total Hourly Cost (€) | I28: Total Depreciation per MT (€/MT) | J28: Percentage of the Total Cost (%)
C29: Jacket Mixing Tank with High Shear Mixer | D29: ='3.2 Syrup Preparation (3)'!F33 -> 0.1171875 | E29: ='3.2 Syrup Preparation (3)'!G33 -> 0.05944577 | F29: =D29/$D$118 -> 0.00071041342 | H29: ='3.2 Syrup Preparation (3)'!F38 -> 1.328125 | I29: ='3.2 Syrup Preparation (3)'!G38 -> 0.46176119 | J29: =H29/$H$118 -> 0.0075194649
C30: Total Machinery Cost | D30: =SUM(D29:D29) -> 0.1171875 | E30: =SUM(E29:E29) -> 0.05944577 | F30: =SUM(F29:F29) -> 0.00071041342 | H30: =SUM(H29:H29) -> 1.328125 | I30: =SUM(I29:I29) -> 0.46176119 | J30: =SUM(J29:J29) -> 0.0075194649
C32: Utility | D32: Total Hourly Cost (€) | E32: Total Cost per MT (€/MT) | F32: Percentage of the Total Cost (%) | H32: Total Hourly Cost (€) | I32: Total Cost per MT (€/MT) | J32: Percentage of the Total Cost (%)
C33: Electricity and Natural Gas Cost | D33: ='3.2 Syrup Preparation (3)'!F44 -> 10.525001 | E33: ='3.2 Syrup Preparation (3)'!G44 -> 5.3390234 | F33: =D33/$D$118 -> 0.063804605 | H33: ='3.2 Syrup Preparation (3)'!F48 -> 11.377274 | I33: ='3.2 Syrup Preparation (3)'!G48 -> 3.9556394 | J33: =H33/$H$118 -> 0.064414881
C34: Other Utility Cost | D34: =15%*D33 -> 1.5787502 | E34: =15%*E33 -> 0.80085351 | F34: =D34/$D$118 -> 0.0095706908 | H34: =15%*H33 -> 1.7065911 | I34: =15%*I33 -> 0.59334591 | J34: =H34/$H$118 -> 0.0096622322
C35: Total Utility Cost | D35: =SUM(D33:D34) -> 12.103751 | E35: =SUM(E33:E34) -> 6.1398769 | F35: =SUM(F33:F34) -> 0.073375296 | H35: =SUM(H33:H34) -> 13.083865 | I35: =SUM(I33:I34) -> 4.5489853 | J35: =SUM(J33:J34) -> 0.074077113
C37: Labour Cost | D37: Total Hourly Cost (€) | E37: Total Cost per MT (€/MT) | F37: Percentage of the Total Cost (%) | H37: Total Hourly Cost (€) | I37: Total Cost per MT (€/MT) | J37: Percentage of the Total Cost (%)
C38: Production Manager | D38: ='3.2 Syrup Preparation (3)'!F53 -> 2.2505195 | E38: ='3.2 Syrup Preparation (3)'!G53 -> 1.1416223 | F38: =D38/$D$118 -> 0.013643087 | H38: ='3.2 Syrup Preparation (3)'!F60 -> 2.2505195 | I38: ='3.2 Syrup Preparation (3)'!G60 -> 0.78245838 | J38: =H38/$H$118 -> 0.012741799
C39: Shift Supervisor | D39: ='3.2 Syrup Preparation (3)'!F54 -> 1.8653017 | E39: ='3.2 Syrup Preparation (3)'!G54 -> 0.94621266 | F39: =D39/$D$118 -> 0.011307822 | H39: ='3.2 Syrup Preparation (3)'!F61 -> 1.8653017 | I39: ='3.2 Syrup Preparation (3)'!G61 -> 0.64852625 | J39: =H39/$H$118 -> 0.010560806
C40: Machine Operator | D40: ='3.2 Syrup Preparation (3)'!F55 -> 1.1616204 | E40: ='3.2 Syrup Preparation (3)'!G55 -> 0.58925586 | F40: =D40/$D$118 -> 0.0070419691 | H40: ='3.2 Syrup Preparation (3)'!F62 -> 2.3232409 | I40: ='3.2 Syrup Preparation (3)'!G62 -> 0.8077421 | J40: =H40/$H$118 -> 0.013153527
C41: Production Worker | D41: ='3.2 Syrup Preparation (3)'!F56 -> 2.214619 | E41: ='3.2 Syrup Preparation (3)'!G56 -> 1.1234111 | F41: =D41/$D$118 -> 0.013425451 | H41: ='3.2 Syrup Preparation (3)'!F63 -> 2.214619 | I41: ='3.2 Syrup Preparation (3)'!G63 -> 0.76997655 | J41: =H41/$H$118 -> 0.012538541
C42: Total labor Cost | D42: =SUM(D38:D41) -> 7.4920606 | E42: =SUM(E38:E41) -> 3.8005019 | F42: =SUM(F38:F41) -> 0.045418329 | H42: =SUM(H38:H41) -> 8.6536811 | I42: =SUM(I38:I41) -> 3.0087033 | J42: =SUM(J38:J41) -> 0.048994674
C43: Total Syrup Preparation Process Costs | D43: =SUM(D30,D35,D42) -> 19.713 | E43: =SUM(E30,E35,E42) -> 9.9998246 | F43: =SUM(F42,F30,F35) -> 0.11950404 | H43: =SUM(H42,H35,H30) -> 23.065671 | I43: =SUM(I42,I35,I30) -> 8.0194498 | J43: =SUM(J30,J35,J42) -> 0.13059125
B45: Mixing Process | C45: Mixing Process
C46: Machinery | D46: Total Hourly Cost (€) | E46: Total Depreciation per MT (€/MT) | F46: Percentage of the Total Cost (%) | H46: Total Hourly Cost (€) | I46: Total Depreciation per MT (€/MT) | J46: Percentage of the Total Cost (%)
C47: Pressure Blending Tank | D47: ='3.4 Mixing (3)'!F33 -> 0.78125 | E47: ='3.4 Mixing (3)'!G33 -> 0.12001063 | F47: =D47/$D$118 -> 0.0047360895 | H47: ='3.4 Mixing (3)'!F38 -> 0.91796875 | I47: ='3.4 Mixing (3)'!G38 -> 0.049434317 | J47: =H47/$H$118 -> 0.0051972772
C48: Total Machinery Cost | D48: =SUM(D47) -> 0.78125 | E48: =SUM(E47) -> 0.12001063 | F48: =SUM(F47:F47) -> 0.0047360895 | H48: =SUM(H47:H47) -> 0.91796875 | I48: =SUM(I47:I47) -> 0.049434317 | J48: =SUM(J47:J47) -> 0.0051972772
C50: Utility | D50: Total Hourly Cost (€) | E50: Total Cost per MT (€/MT) | F50: Percentage of the Total Cost (%) | H50: Total Hourly Cost (€) | I50: Total Cost per MT (€/MT) | J50: Percentage of the Total Cost (%)
C51: Electricity and Natural Gas Cost | D51: ='3.4 Mixing (3)'!F44 -> 3.7068185 | E51: ='3.4 Mixing (3)'!G44 -> 0.56941775 | F51: =D51/$D$118 -> 0.022471455 | H51: ='3.4 Mixing (3)'!F48 -> 4.5590914 | I51: ='3.4 Mixing (3)'!G48 -> 0.24551551 | J51: =H51/$H$118 -> 0.025812275
C52: Other Utility Cost | D52: =15%*D51 -> 0.55602278 | E52: =15%*E51 -> 0.085412662 | F52: =D52/$D$118 -> 0.0033707183 | H52: =15%*H51 -> 0.68386371 | I52: =15%*I51 -> 0.036827327 | J52: =H52/$H$118 -> 0.0038718413
C53: Total Utility Cost | D53: =SUM(D51:D52) -> 4.2628413 | E53: =SUM(E51:E52) -> 0.65483041 | F53: =SUM(F51:F52) -> 0.025842173 | H53: =SUM(H51:H52) -> 5.2429551 | I53: =SUM(I51:I52) -> 0.28234284 | J53: =SUM(J51:J52) -> 0.029684116
C55: Labour Cost | D55: Total Hourly Cost (€) | E55: Total Cost per MT (€/MT) | F55: Percentage of the Total Cost (%) | H55: Total Hourly Cost (€) | I55: Total Cost per MT (€/MT) | J55: Percentage of the Total Cost (%)
C56: Production Manager | D56: ='3.4 Mixing (3)'!F53 -> 2.2505195 | E56: ='3.4 Mixing (3)'!G53 -> 0.3457104 | F56: =D56/$D$118 -> 0.013643087 | H56: ='3.4 Mixing (3)'!F60 -> 2.2505195 | I56: ='3.4 Mixing (3)'!G60 -> 0.12119464 | J56: =H56/$H$118 -> 0.012741799
C57: Shift Supervisor | D57: ='3.4 Mixing (3)'!F54 -> 1.8653017 | E57: ='3.4 Mixing (3)'!G54 -> 0.28653571 | F57: =D57/$D$118 -> 0.011307822 | H57: ='3.4 Mixing (3)'!F61 -> 1.8653017 | I57: ='3.4 Mixing (3)'!G61 -> 0.10044995 | J57: =H57/$H$118 -> 0.010560806
C58: Machine Operator | D58: ='3.4 Mixing (3)'!F55 -> 1.1616204 | E58: ='3.4 Mixing (3)'!G55 -> 0.1784407 | F58: =D58/$D$118 -> 0.0070419691 | H58: ='3.4 Mixing (3)'!F62 -> 1.1616204 | I58: ='3.4 Mixing (3)'!G62 -> 0.062555412 | J58: =H58/$H$118 -> 0.0065767636
C59: Production Worker | D59: ='3.4 Mixing (3)'!F56 -> 2.214619 | E59: ='3.4 Mixing (3)'!G56 -> 0.3401956 | F59: =D59/$D$118 -> 0.013425451 | H59: ='3.4 Mixing (3)'!F63 -> 2.214619 | I59: ='3.4 Mixing (3)'!G63 -> 0.11926134 | J59: =H59/$H$118 -> 0.012538541
C60: Total Labour Cost | D60: =SUM(D56:D59) -> 7.4920606 | E60: =SUM(E56:E59) -> 1.1508824 | F60: =SUM(F56:F59) -> 0.045418329 | H60: =SUM(H56:H59) -> 7.4920606 | I60: =SUM(I56:I59) -> 0.40346134 | J60: =SUM(J56:J59) -> 0.04241791
C62: Total Mixing Process Costs | D62: =SUM(D60,D53,D48) -> 12.536152 | E62: =SUM(E60,E53,E48) -> 1.9257235 | F62: =SUM(F60,F53,F48) -> 0.075996592 | H62: =SUM(H60,H53,H48) -> 13.652984 | I62: =SUM(I60,I53,I48) -> 0.7352385 | J62: =SUM(J60,J53,J48) -> 0.077299304
B64: Pasteurisation Process | C64: Pasteurisation Process
C65: Machinery | D65: Total Hourly Cost (€) | E65: Total Depreciation per MT (€/MT) | F65: Percentage of the Total Cost (%) | H65: Total Hourly Cost (€) | I65: Total Depreciation per MT (€/MT) | J65: Percentage of the Total Cost (%)
C66: Pasteuriser | D66: =IF('1.2 Scenario Analysis'!$M$14="Can",0,'3.5 Pasteurisation (3)'!F33) -> 1.5917969 | E66: =IF('1.2 Scenario Analysis'!$M$14="Can",0,'3.5 Pasteurisation (3)'!G33) -> 1.3371249 | F66: =D66/$D$118 -> 0.0096497823 | H66: =IF('1.2 Scenario Analysis'!$M$14="Can",0,'3.5 Pasteurisation (3)'!F38) -> 1.7089844 | I66: =IF('1.2 Scenario Analysis'!$M$14="Can",0,'3.5 Pasteurisation (3)'!G38) -> 0.90319094 | J66: =H66/$H$118 -> 0.0096757821
C67: Total Machinery Cost | D67: =SUM(D66) -> 1.5917969 | E67: =SUM(E66) -> 1.3371249 | F67: =SUM(F66) -> 0.0096497823 | H67: =SUM(H66:H66) -> 1.7089844 | I67: =SUM(I66:I66) -> 0.90319094 | J67: =SUM(J66) -> 0.0096757821
C69: Utility | D69: Total Hourly Cost (€) | E69: Total Cost per MT (€/MT) | F69: Percentage of the Total Cost (%) | H69: Total Hourly Cost (€) | I69: Total Cost per MT (€/MT) | J69: Percentage of the Total Cost (%)
C70: Electricity and Natural Gas Cost | D70: =IF('1.2 Scenario Analysis'!$M$14="Can",0,'3.5 Pasteurisation (3)'!F44) -> 19.506819 | E70: =IF('1.2 Scenario Analysis'!$M$14="Can",0,'3.5 Pasteurisation (3)'!G44) -> 16.385918 | F70: =D70/$D$118 -> 0.11825413 | H70: =IF('1.2 Scenario Analysis'!$M$14="Can",0,'3.5 Pasteurisation (3)'!F48) -> 20.018183 | I70: =IF('1.2 Scenario Analysis'!$M$14="Can",0,'3.5 Pasteurisation (3)'!G48) -> 10.579524 | J70: =H70/$H$118 -> 0.11333724
C71: Other Utility Cost | D71: =15%*D70 -> 2.9260229 | E71: =15%*E70 -> 2.4578877 | F71: =D71/$D$118 -> 0.01773812 | H71: =15%*H70 -> 3.0027274 | I71: =15%*I70 -> 1.5869286 | J71: =H71/$H$118 -> 0.017000586
C72: Total Utility Cost | D72: =SUM(D70:D71) -> 22.432842 | E72: =SUM(E70:E71) -> 18.843805 | F72: =SUM(F70:F71) -> 0.13599225 | H72: =SUM(H70:H71) -> 23.02091 | I72: =SUM(I70:I71) -> 12.166453 | J72: =SUM(J70:J71) -> 0.13033783
C74: Labour Cost | D74: Total Hourly Cost (€) | E74: Total Cost per MT (€/MT) | F74: Percentage of the Total Cost (%) | H74: Total Hourly Cost (€) | I74: Total Cost per MT (€/MT) | J74: Percentage of the Total Cost (%)
C75: Production Manager | D75: =IF('1.2 Scenario Analysis'!$M$14="Can",0,'3.5 Pasteurisation (3)'!F53) -> 2.2505195 | E75: =IF('1.2 Scenario Analysis'!$M$14="Can",0,'3.5 Pasteurisation (3)'!G53) -> 1.8904582 | F75: =D75/$D$118 -> 0.013643087 | H75: =IF('1.2 Scenario Analysis'!$M$14="Can",0,'3.5 Pasteurisation (3)'!F60) -> 2.2505195 | I75: =IF('1.2 Scenario Analysis'!$M$14="Can",0,'3.5 Pasteurisation (3)'!G60) -> 1.1893899 | J75: =H75/$H$118 -> 0.012741799
C76: Shift Supervisor | D76: =IF('1.2 Scenario Analysis'!$M$14="Can",0,'3.5 Pasteurisation (3)'!F54) -> 1.8653017 | E76: =IF('1.2 Scenario Analysis'!$M$14="Can",0,'3.5 Pasteurisation (3)'!G54) -> 1.5668716 | F76: =D76/$D$118 -> 0.011307822 | H76: =IF('1.2 Scenario Analysis'!$M$14="Can",0,'3.5 Pasteurisation (3)'!F61) -> 1.8653017 | I76: =IF('1.2 Scenario Analysis'!$M$14="Can",0,'3.5 Pasteurisation (3)'!G61) -> 0.98580398 | J76: =H76/$H$118 -> 0.010560806
C77: Machine Operator | D77: =IF('1.2 Scenario Analysis'!$M$14="Can",0,'3.5 Pasteurisation (3)'!F55) -> 1.1616204 | E77: =IF('1.2 Scenario Analysis'!$M$14="Can",0,'3.5 Pasteurisation (3)'!G55) -> 0.97577247 | F77: =D77/$D$118 -> 0.0070419691 | H77: =IF('1.2 Scenario Analysis'!$M$14="Can",0,'3.5 Pasteurisation (3)'!F62) -> 1.1616204 | I77: =IF('1.2 Scenario Analysis'!$M$14="Can",0,'3.5 Pasteurisation (3)'!G62) -> 0.61391144 | J77: =H77/$H$118 -> 0.0065767636
C78: Production Worker | D78: =IF('1.2 Scenario Analysis'!$M$14="Can",0,'3.5 Pasteurisation (3)'!F56) -> 2.214619 | E78: =IF('1.2 Scenario Analysis'!$M$14="Can",0,'3.5 Pasteurisation (3)'!G56) -> 1.8603015 | F78: =D78/$D$118 -> 0.013425451 | H78: =IF('1.2 Scenario Analysis'!$M$14="Can",0,'3.5 Pasteurisation (3)'!F63) -> 2.214619 | I78: =IF('1.2 Scenario Analysis'!$M$14="Can",0,'3.5 Pasteurisation (3)'!G63) -> 1.1704167 | J78: =H78/$H$118 -> 0.012538541
C79: Total labor Cost | D79: =SUM(D75:D78) -> 7.4920606 | E79: =SUM(E75:E78) -> 6.2934038 | F79: =SUM(F75:F78) -> 0.045418329 | H79: =SUM(H75:H78) -> 7.4920606 | I79: =SUM(I75:I78) -> 3.959522 | J79: =SUM(J75:J78) -> 0.04241791
C81: Total Pasteurisation Process Cost | D81: =SUM(D79,D72,D67) -> 31.516699 | E81: =SUM(E79,E72,E67) -> 26.474334 | F81: =SUM(F79,F72,F67) -> 0.19106036 | H81: =SUM(H79,H72,H67) -> 32.221955 | I81: =SUM(I79,I72,I67) -> 17.029166 | J81: =SUM(J79,J72,J67) -> 0.18243152
B83: Carbonation Process | C83: Carbonation Process
C84: Machinery | D84: Total Hourly Cost (€) | E84: Total Depreciation per MT (€/MT) | F84: Percentage of the Total Cost (%) | H84: Total Hourly Cost (€) | I84: Total Depreciation per MT (€/MT) | J84: Percentage of the Total Cost (%)
C85: Carbonation Maker | D85: =IF('1.2 Scenario Analysis'!$M$13="Non-Carbonated",0,'3.3 Carbonation (3)'!F34) -> 0 | E85: =IF('1.2 Scenario Analysis'!$M$13="Non-Carbonated",0,'3.3 Carbonation (3)'!G34) -> 0 | F85: =D85/$D$118 -> 0 | H85: =IF('1.2 Scenario Analysis'!$M$13="Non-Carbonated",0,'3.3 Carbonation (3)'!F38) -> 0 | I85: =IF('1.2 Scenario Analysis'!$M$13="Non-Carbonated",0,'3.3 Carbonation (3)'!G38) -> 0 | J85: =H85/$H$118 -> 0
C86: Total Machinery Cost | D86: =SUM(D85) -> 0 | E86: =SUM(E85) -> 0 | F86: =SUM(F85:F85) -> 0 | H86: =SUM(H85) -> 0 | I86: =SUM(I85) -> 0 | J86: =SUM(J85:J85) -> 0
C88: Utility | D88: Total Hourly Cost (€) | E88: Total Cost per MT (€/MT) | F88: Percentage of the Total Cost (%) | H88: Total Hourly Cost (€) | I88: Total Cost per MT (€/MT) | J88: Percentage of the Total Cost (%)
C89: Electricity and Natural Gas Cost | D89: =IF('1.2 Scenario Analysis'!$M$13="Non-Carbonated",0,'3.3 Carbonation (3)'!F44) -> 0 | E89: =IF('1.2 Scenario Analysis'!$M$13="Non-Carbonated",0,'3.3 Carbonation (3)'!G44) -> 0 | F89: =D89/$D$118 -> 0 | H89: =IF('1.2 Scenario Analysis'!$M$13="Non-Carbonated",0,'3.3 Carbonation (3)'!F48) -> 0 | I89: =IF('1.2 Scenario Analysis'!$M$13="Non-Carbonated",0,'3.3 Carbonation (3)'!G48) -> 0 | J89: =H89/$H$118 -> 0
C90: Other Utility Cost | D90: =15%*D89 -> 0 | E90: =15%*E89 -> 0 | F90: =D90/$D$118 -> 0 | H90: =15%*H89 -> 0 | I90: =15%*I89 -> 0 | J90: =H90/$H$118 -> 0
C91: Total Utility Cost | D91: =SUM(D89:D90) -> 0 | E91: =SUM(E89:E90) -> 0 | F91: =SUM(F89:F90) -> 0 | H91: =SUM(H89:H90) -> 0 | I91: =SUM(I89:I90) -> 0 | J91: =SUM(J89:J90) -> 0
C93: Labour Cost | D93: Total Hourly Cost (€) | E93: Total Cost per MT (€/MT) | F93: Percentage of the Total Cost (%) | H93: Total Hourly Cost (€) | I93: Total Cost per MT (€/MT) | J93: Percentage of the Total Cost (%)
C94: Production Manager | D94: =IF('1.2 Scenario Analysis'!$M$13="Non-Carbonated",0,'3.3 Carbonation (3)'!F53) -> 0 | E94: =IF('1.2 Scenario Analysis'!$M$13="Non-Carbonated",0,'3.3 Carbonation (3)'!G53) -> 0 | F94: =D94/$D$118 -> 0 | H94: =IF('1.2 Scenario Analysis'!$M$13="Non-Carbonated",0,'3.3 Carbonation (3)'!F60) -> 0 | I94: =IF('1.2 Scenario Analysis'!$M$13="Non-Carbonated",0,'3.3 Carbonation (3)'!G60) -> 0 | J94: =H94/$H$118 -> 0
C95: Shift Supervisor | D95: =IF('1.2 Scenario Analysis'!$M$13="Non-Carbonated",0,'3.3 Carbonation (3)'!F54) -> 0 | E95: =IF('1.2 Scenario Analysis'!$M$13="Non-Carbonated",0,'3.3 Carbonation (3)'!G54) -> 0 | F95: =D95/$D$118 -> 0 | H95: =IF('1.2 Scenario Analysis'!$M$13="Non-Carbonated",0,'3.3 Carbonation (3)'!F61) -> 0 | I95: =IF('1.2 Scenario Analysis'!$M$13="Non-Carbonated",0,'3.3 Carbonation (3)'!G61) -> 0 | J95: =H95/$H$118 -> 0
C96: Machine Operator | D96: =IF('1.2 Scenario Analysis'!$M$13="Non-Carbonated",0,'3.3 Carbonation (3)'!F55) -> 0 | E96: =IF('1.2 Scenario Analysis'!$M$13="Non-Carbonated",0,'3.3 Carbonation (3)'!G55) -> 0 | F96: =D96/$D$118 -> 0 | H96: =IF('1.2 Scenario Analysis'!$M$13="Non-Carbonated",0,'3.3 Carbonation (3)'!F62) -> 0 | I96: =IF('1.2 Scenario Analysis'!$M$13="Non-Carbonated",0,'3.3 Carbonation (3)'!G62) -> 0 | J96: =H96/$H$118 -> 0
C97: Production Worker | D97: =IF('1.2 Scenario Analysis'!$M$13="Non-Carbonated",0,'3.3 Carbonation (3)'!F56) -> 0 | E97: =IF('1.2 Scenario Analysis'!$M$13="Non-Carbonated",0,'3.3 Carbonation (3)'!G56) -> 0 | F97: =D97/$D$118 -> 0 | H97: =IF('1.2 Scenario Analysis'!$M$13="Non-Carbonated",0,'3.3 Carbonation (3)'!F63) -> 0 | I97: =IF('1.2 Scenario Analysis'!$M$13="Non-Carbonated",0,'3.3 Carbonation (3)'!G63) -> 0 | J97: =H97/$H$118 -> 0
C98: Total labor Cost | D98: =SUM(D94:D97) -> 0 | E98: =SUM(E94:E97) -> 0 | F98: =SUM(F94:F97) -> 0 | H98: =SUM(H94:H97) -> 0 | I98: =SUM(I94:I97) -> 0 | J98: =SUM(J94:J97) -> 0
C100: Total Carbonation Process Costs | D100: =SUM(D98,D91,D86) -> 0 | E100: =SUM(E98,E91,E86) -> 0 | F100: =SUM(F98,F91,F86) -> 0 | H100: =SUM(H98,H91,H86) -> 0 | I100: =SUM(I98,I91,I86) -> 0 | J100: =SUM(J98,J91,J86) -> 0
C102: Total Process Cost | D102: =SUM(D25,D100,D81,D62,D43) -> 81.33929 | E102: =SUM(E25,E100,E81,E62,E43) -> 45.982469 | F102: =SUM(F43,F100,F81,F62,F25) -> 0.4930946 | H102: =SUM(H25,H43,H62,H81,H100) -> 87.758215 | I102: =SUM(I25,I100,I81,I62,I43) -> 31.14364 | J102: =SUM(J43,J100,J81,J62,J25) -> 0.49686199
B104: Other Overhead Costs | C104: Other Overhead Cost | D104: Total Hourly Cost (€) | E104: Total Cost per MT (€/MT) | F104: Percentage of the Total Cost (%) | H104: Total Hourly Cost (€) | I104: Total Cost per MT (€/MT) | J104: Percentage of the Total Cost (%)
C105: Selling and General Administrative Expenses | D105: ='Assumption & Analysis'!E80*D102 -> 48.803574 | E105: ='Assumption & Analysis'!E80*E102 -> 27.589482 | F105: =D105/$D$118 -> 0.29585676 | H105: ='Assumption & Analysis'!E80*H102 -> 52.654929 | I105: ='Assumption & Analysis'!E80*I102 -> 18.686184 | J105: =H105/H118 -> 0.29811719
C106: Other Depreciation Costs | D106: ='Assumption & Analysis'!$E$82*(SUM('Assumption & Analysis (3)'!G31,'Assumption & Analysis (3)'!G34,'Assumption & Analysis (3)'!G35))/('Labour Data – France'!C$10*3) -> 10.953479 | E106: =(D106*SUM('3.1 Water Treatment (3)'!C27,'3.2 Syrup Preparation (3)'!C27,'3.3 Carbonation (3)'!C27,'3.4 Mixing (3)'!C27,'3.5 Pasteurisation (3)'!C27))/IF('1.2 Scenario Analysis'!$M$19="Small-scale",'Assumption & Analysis'!E49,IF('1.2 Scenario Analysis'!$M$19="Medium-scale",'Assumption & Analysis'!E50,'Assumption & Analysis'!E51)) -> 21.166218 | F106: =D106/$D$118 -> 0.066402123 | H106: ='Assumption & Analysis'!$E$82*(SUM('Assumption & Analysis (3)'!G31,'Assumption & Analysis (3)'!G34,'Assumption & Analysis (3)'!G35))/('Labour Data – France'!D$10*3) -> 10.953479 | I106: =(H106*SUM('3.1 Water Treatment (3)'!D27,'3.2 Syrup Preparation (3)'!D27,'3.3 Carbonation (3)'!D27,'3.4 Mixing (3)'!D27,'3.5 Pasteurisation (3)'!D27))/IF('1.2 Scenario Analysis'!M19="Small-scale",'Assumption & Analysis'!E49,IF('1.2 Scenario Analysis'!M19="Medium-scale",'Assumption & Analysis'!E50,'Assumption & Analysis'!E51)) -> 13.306888 | J106: =H106/H118 -> 0.062015477
C107: Total Other Overhead Costs | D107: =SUM(D105:D106) -> 59.757054 | E107: =SUM(E105:E106) -> 48.755699 | F107: =SUM(F105:F106) -> 0.36225888 | H107: =SUM(H105:H106) -> 63.608409 | I107: =SUM(I105:I106) -> 31.993072 | J107: =SUM(J105:J106) -> 0.36013267
B110: Other Indirect Costs | C110: Other Indirect Cost | D110: Total Hourly Cost (€) | E110: Total Cost per MT (€/MT) | F110: Percentage of the Total Cost (%) | H110: Total Hourly Cost (€) | I110: Total Cost per MT (€/MT) | J110: Percentage of the Total Cost (%)
C111: Maintenance and Repair Cost | D111: =('Assumption & Analysis'!$E$87*SUM('Appendix - Equipment'!E14,((SUM('Assumption & Analysis (3)'!G31,'Assumption & Analysis (3)'!G34,'Assumption & Analysis (3)'!G35))/3)))/'Labour Data – France'!C$10 -> 7.3038585 | E111: =(D111*SUM('3.1 Water Treatment (3)'!C27,'3.2 Syrup Preparation (3)'!C27,'3.3 Carbonation (3)'!C27,'3.4 Mixing (3)'!C27,'3.5 Pasteurisation (3)'!C27))/IF('1.2 Scenario Analysis'!M19="Small-scale",'Assumption & Analysis'!$E$49,IF('1.2 Scenario Analysis'!M19="Medium-scale",'Assumption & Analysis'!$E$50,'Assumption & Analysis'!$E$51)) -> 14.113785 | F111: =D111/$D$118 -> 0.044277411 | H111: =('Assumption & Analysis'!$E$87*SUM('Appendix - Equipment'!$I$14,((SUM('Assumption & Analysis (3)'!G31,'Assumption & Analysis (3)'!G34,'Assumption & Analysis (3)'!G35))/3)))/'Labour Data – France'!D$10 -> 7.7012543 | I111: =(H111*SUM('3.1 Water Treatment (3)'!D27,'3.2 Syrup Preparation (3)'!D27,'3.3 Carbonation (3)'!D27,'3.4 Mixing (3)'!D27,'3.5 Pasteurisation (3)'!D27))/IF('1.2 Scenario Analysis'!M19="Small-scale",'Assumption & Analysis'!$E$49,IF('1.2 Scenario Analysis'!M19="Medium-scale",'Assumption & Analysis'!$E$50,'Assumption & Analysis'!$E$51)) -> 9.3559064 | J111: =H111/H$118 -> 0.043602306
C112: Finance Cost | D112: =('Assumption & Analysis'!$E$88*SUM('Appendix - Equipment'!E14,((SUM('Assumption & Analysis (3)'!G31,'Assumption & Analysis (3)'!G34,'Assumption & Analysis (3)'!G35))/3)))/'Labour Data – France'!C$10 -> 12.489598 | E112: =(D112*SUM('3.1 Water Treatment (3)'!C27,'3.2 Syrup Preparation (3)'!C27,'3.3 Carbonation (3)'!C27,'3.4 Mixing (3)'!C27,'3.5 Pasteurisation (3)'!C27))/IF('1.2 Scenario Analysis'!M19="Small-scale",'Assumption & Analysis'!$E$49,IF('1.2 Scenario Analysis'!M19="Medium-scale",'Assumption & Analysis'!$E$50,'Assumption & Analysis'!$E$51)) -> 24.134573 | F112: =D112/$D$118 -> 0.075714373 | H112: =('Assumption & Analysis'!$E$88*SUM('Appendix - Equipment'!$I$14,((SUM('Assumption & Analysis (3)'!G31,'Assumption & Analysis (3)'!G34,'Assumption & Analysis (3)'!G35))/3)))/'Labour Data – France'!D$10 -> 13.169145 | I112: =(H112*SUM('3.1 Water Treatment (3)'!D27,'3.2 Syrup Preparation (3)'!D27,'3.3 Carbonation (3)'!D27,'3.4 Mixing (3)'!D27,'3.5 Pasteurisation (3)'!D27))/IF('1.2 Scenario Analysis'!M19="Small-scale",'Assumption & Analysis'!$E$49,IF('1.2 Scenario Analysis'!M19="Medium-scale",'Assumption & Analysis'!$E$50,'Assumption & Analysis'!$E$51)) -> 15.9986 | J112: =H112/H$118 -> 0.074559942
C113: Others (Tax, insurance and other expenses) | D113: ='Assumption & Analysis'!$E$89*D102 -> 4.0669645 | E113: ='Assumption & Analysis'!$E$89*'2.1 Cost Model Processes (3)'!E102 -> 2.2991235 | F113: =D113/$D$118 -> 0.02465473 | H113: ='Assumption & Analysis'!$E$89*H102 -> 4.3879108 | I113: ='Assumption & Analysis'!$E$89*'2.1 Cost Model Processes (3)'!I102 -> 1.557182 | J113: =H113/H$118 -> 0.024843099
C114: Total Other Indirect Costs | D114: =SUM(D111:D113) -> 23.860421 | E114: =SUM(E111:E113) -> 40.547482 | F114: =SUM(F111:F113) -> 0.14464651 | H114: =SUM(H111:H113) -> 25.25831 | I114: =SUM(I111:I113) -> 26.911688 | J114: =SUM(J111:J113) -> 0.14300535
C115: Total Overhead and Indirect Cost | D115: =SUM(D107,D114) -> 83.617475 | E115: =SUM(E107,E114) -> 89.303181 | F115: =SUM(F107,F114) -> 0.5069054 | H115: =SUM(H107,H114) -> 88.866719 | I115: =SUM(I107,I114) -> 58.90476 | J115: =SUM(J107,J114) -> 0.50313801
D117: Total Hourly Cost (€) | E117: Total Cost per MT (€/MT) | F117: Percentage of the Total Cost (%) | H117: Total Hourly Cost (€) | I117: Total Cost per MT (€/MT) | J117: Percentage of the Total Cost (%)
C118: Total Production Cost | D118: =D115+D102 -> 164.95677 | E118: =E115+E102 -> 135.28565 | F118: =F115+F102 -> 1 | H118: =H115+H102 -> 176.62493 | I118: =I115+I102 -> 90.0484 | J118: =J115+J102 -> 1
A121: Copyright © 2025 WNS (Holdings) Ltd. All rights reserved.

Sheet 2.2 Cost Model Packing
C5: Summary – Packing Cost
D7: Semi-Automatic | H7: Automatic
C8: Dry Aseptic Cleaning Process
B9: Dry Aseptic Cleaning Process | C9: Machinery | D9: Total Hourly Cost (€) | E9: Total Depreciation per MT (€/MT) | F9: Percentage of the Total Cost (%) | H9: Total Hourly Cost (€) | I9: Total Depreciation per MT (€/MT) | J9: Percentage of the Total Cost (%)
C10: Preform Steriliser | D10: ='4.1 Dry Aseptic Cleaning'!F34 -> 0.37760417 | E10: =IF('1.1 Summary'!C15="Can",0,'4.1 Dry Aseptic Cleaning'!G34) -> 0.020070516 | F10: =D10/$D$235 -> 0.0015992035 | H10: ='4.1 Dry Aseptic Cleaning'!F39 -> 0.45572917 | I10: =IF('1.1 Summary'!$C$15="Can",0,'4.1 Dry Aseptic Cleaning'!G39) -> 0.019957999 | J10: =H10/H$235 -> 0.0018575227
C11: Air Jet and Vacuum Cleaning Machines | D11: ='4.1 Dry Aseptic Cleaning'!F35 -> 0.25390625 | E11: =IF('1.1 Summary'!C15="Can",0,'4.1 Dry Aseptic Cleaning'!G35) -> 0.013495692 | F11: =D11/$D$235 -> 0.0010753265 | H11: ='4.1 Dry Aseptic Cleaning'!F40 -> 0.3125 | I11: =IF('1.1 Summary'!$C$15="Can",0,'4.1 Dry Aseptic Cleaning'!G40) -> 0.013685485 | J11: =H11/H$235 -> 0.0012737299
C12: Total Machinery Cost | D12: =SUM(D10:D11) -> 0.63151042 | E12: =SUM(E10:E11) -> 0.033566208 | F12: =SUM(F10:F11) -> 0.0026745299 | H12: =SUM(H10:H11) -> 0.76822917 | I12: =SUM(I10:I11) -> 0.033643485 | J12: =SUM(J10:J11) -> 0.0031312526
C14: Utility | D14: Total Hourly Cost (€) | E14: Total Cost per MT (€/MT) | F14: Percentage of the Total Cost (%) | H14: Total Hourly Cost (€) | I14: Total Cost per MT (€/MT) | J14: Total Cost per MT (€/MT)
C15: Electricity and Natural Gas Cost | D15: ='4.1 Dry Aseptic Cleaning'!F47 -> 4.3065661 | E15: =IF('1.1 Summary'!C15="Can",0,'4.1 Dry Aseptic Cleaning'!G47) -> 0.22890373 | F15: =D15/$D$235 -> 0.018238876 | H15: ='4.1 Dry Aseptic Cleaning'!F52 -> 4.9378793 | I15: =IF('1.1 Summary'!C15="Can",0,'4.1 Dry Aseptic Cleaning'!G52) -> 0.21624728 | J15: =H15/$H$235 -> 0.020126478
C16: Other Utility Cost | D16: =15%*D15 -> 0.64598491 | E16: =15%*E15 -> 0.03433556 | F16: =D16/$D$235 -> 0.0027358313 | H16: =15%*H15 -> 0.7406819 | I16: =15%*I15 -> 0.032437092 | J16: =H16/$H$235 -> 0.0030189717
C17: Total Utility Cost | D17: =SUM(D15:D16) -> 4.952551 | E17: =SUM(E15:E16) -> 0.2632393 | F17: =SUM(F15:F16) -> 0.020974707 | H17: =SUM(H15:H16) -> 5.6785612 | I17: =SUM(I15:I16) -> 0.24868437 | J17: =SUM(J15:J16) -> 0.02314545
C20: Labour Cost | D20: Total Hourly Cost (€) | E20: Total Cost per MT (€/MT) | F20: Percentage of the Total Cost (%) | H20: Total Hourly Cost (€) | I20: Total Cost per MT (€/MT) | J20: Percentage of the Total Cost (%)
C21: Production Manager | D21: ='4.1 Dry Aseptic Cleaning'!F58 -> 2.2505195 | E21: =IF('1.1 Summary'!$C$15="Can",0,'4.1 Dry Aseptic Cleaning'!G58) -> 0.1196202 | F21: =D21/$D$235 -> 0.0095312468 | H21: ='4.1 Dry Aseptic Cleaning'!F65 -> 2.2505195 | I21: =IF('1.1 Summary'!$C$15="Can",0,'4.1 Dry Aseptic Cleaning'!G65) -> 0.098558243 | J21: =H21/$H$235 -> 0.0091729723
C22: Shift Supervisor | D22: ='4.1 Dry Aseptic Cleaning'!F59 -> 1.8653017 | E22: =IF('1.1 Summary'!$C$15="Can",0,'4.1 Dry Aseptic Cleaning'!G59) -> 0.099145007 | F22: =D22/$D$235 -> 0.0078997988 | H22: ='4.1 Dry Aseptic Cleaning'!F66 -> 1.8653017 | I22: =IF('1.1 Summary'!$C$15="Can",0,'4.1 Dry Aseptic Cleaning'!G66) -> 0.081688189 | J22: =H22/$H$235 -> 0.0076028495
C23: Machine Operator | D23: ='4.1 Dry Aseptic Cleaning'!F60 -> 1.1616204 | E23: =IF('1.1 Summary'!$C$15="Can",0,'4.1 Dry Aseptic Cleaning'!G60) -> 0.061742756 | F23: =D23/$D$235 -> 0.0049196158 | H23: ='4.1 Dry Aseptic Cleaning'!F67 -> 1.1616204 | I23: =IF('1.1 Summary'!$C$15="Can",0,'4.1 Dry Aseptic Cleaning'!G67) -> 0.050871486 | J23: =H23/$H$235 -> 0.0047346901
C24: Production Worker | D24: ='4.1 Dry Aseptic Cleaning'!F61 -> 2.214619 | E24: =IF('1.1 Summary'!$C$15="Can",0,'4.1 Dry Aseptic Cleaning'!G61) -> 0.11771201 | F24: =D24/$D$235 -> 0.0093792037 | H24: ='4.1 Dry Aseptic Cleaning'!F68 -> 2.214619 | I24: =IF('1.1 Summary'!$C$15="Can",0,'4.1 Dry Aseptic Cleaning'!G68) -> 0.096986035 | J24: =H24/$H$235 -> 0.0090266444
C25: Total labor Cost | D25: =SUM(D21:D24) -> 7.4920606 | E25: =SUM(E21:E24) -> 0.39821998 | F25: =SUM(F21:F24) -> 0.031729865 | H25: =SUM(H21:H24) -> 7.4920606 | I25: =SUM(I21:I24) -> 0.32810395 | J25: =SUM(J21:J24) -> 0.030537156
C26: Total Dry Aseptic Cleaning Cost | D26: =D25+D17+D12 -> 13.076122 | E26: =E25+E17+E12 -> 0.69502548 | F26: =SUM(F25,F17,F12) -> 0.055379102 | H26: =H25+H17+H12 -> 13.938851 | I26: =I25+I17+I12 -> 0.61043181 | J26: =SUM(J25,J17,J12) -> 0.056813858
D28: Semi-Automatic | H28: Automatic
C29: PET Bottle Blowing Process
B30: PET Bottle Blowing Process | C30: Machinery | D30: Total Hourly Cost (€) | E30: Total Depreciation per MT (€/MT) | F30: Percentage of the Total Cost (%) | H30: Total Hourly Cost (€) | I30: Total Depreciation per MT (€/MT) | J30: Percentage of the Total Cost (%)
C31: PET Bottle Blowing Machine | D31: =IF('1.1 Summary'!$C$15="Can",0,'4.2 PET Bottle Blowing'!F34) -> 0.67708333 | E31: =IF('1.1 Summary'!$C$15="Can",0,'4.2 PET Bottle Blowing'!G34) -> 0.050004026 | F31: =D31/$D$235 -> 0.0028675372 | H31: =IF('1.1 Summary'!$C$15="Can",0,'4.2 PET Bottle Blowing'!F38) -> 0.71614583 | I31: =IF('1.1 Summary'!$C$15="Can",0,'4.2 PET Bottle Blowing'!G38) -> 0.042221739 | J31: =H31/H$235 -> 0.0029189643
C32: Total Machinery Cost | D32: =SUM(D31:D31) -> 0.67708333 | E32: =SUM(E31:E31) -> 0.050004026 | F32: =SUM(F31:F31) -> 0.0028675372 | H32: =SUM(H31:H31) -> 0.71614583 | I32: =SUM(I31:I31) -> 0.042221739 | J32: =SUM(J31:J31) -> 0.0029189643
C34: Utility | D34: Total Hourly Cost (€) | E34: Total Cost per MT (€/MT) | F34: Percentage of the Total Cost (%) | H34: Total Hourly Cost (€) | I34: Total Cost per MT (€/MT) | J34: Total Cost per MT (€/MT)
C35: Electricity and Natural Gas Cost | D35: =IF('1.1 Summary'!$C$15="Can",0,'4.2 PET Bottle Blowing'!F45) -> 12.197981 | E35: =IF('1.1 Summary'!$C$15="Can",0,'4.2 PET Bottle Blowing'!G45) -> 0.90084653 | F35: =D35/$D$235 -> 0.05166006 | H35: =IF('1.1 Summary'!$C$15="Can",0,'4.2 PET Bottle Blowing'!F49) -> 12.671466 | I35: =IF('1.1 Summary'!$C$15="Can",0,'4.2 PET Bottle Blowing'!G49) -> 0.74707038 | J35: =H35/$H$235 -> 0.05164808
C36: Other Utility Cost | D36: =15%*D35 -> 1.8296972 | E36: =15%*E35 -> 0.13512698 | F36: =D36/$D$235 -> 0.007749009 | H36: =15%*H35 -> 1.9007199 | I36: =15%*I35 -> 0.11206056 | J36: =H36/$H$235 -> 0.007747212
C37: Total Utility Cost | D37: =SUM(D35:D36) -> 14.027679 | E37: =SUM(E35:E36) -> 1.0359735 | F37: =SUM(F35:F36) -> 0.059409069 | H37: =SUM(H35:H36) -> 14.572186 | I37: =SUM(I35:I36) -> 0.85913094 | J37: =SUM(J35:J36) -> 0.059395292
C40: Labour Cost | D40: Total Hourly Cost (€) | E40: Total Cost per MT (€/MT) | F40: Percentage of the Total Cost (%) | H40: Total Hourly Cost (€) | I40: Total Cost per MT (€/MT) | J40: Percentage of the Total Cost (%)
C41: Production Manager | D41: =IF('1.1 Summary'!$C$15="Can",0,'4.2 PET Bottle Blowing'!F54) -> 2.2505195 | E41: =IF('1.1 Summary'!$C$15="Can",0,'4.2 PET Bottle Blowing'!G54) -> 0.16620559 | F41: =D41/$D$235 -> 0.0095312468 | H41: =IF('1.1 Summary'!$C$15="Can",0,'4.2 PET Bottle Blowing'!F61) -> 2.2505195 | I41: =IF('1.1 Summary'!$C$15="Can",0,'4.2 PET Bottle Blowing'!G61) -> 0.13268365 | J41: =H41/$H$235 -> 0.0091729723
C42: Shift Supervisor | D42: =IF('1.1 Summary'!$C$15="Can",0,'4.2 PET Bottle Blowing'!F55) -> 1.8653017 | E42: =IF('1.1 Summary'!$C$15="Can",0,'4.2 PET Bottle Blowing'!G55) -> 0.13775645 | F42: =D42/$D$235 -> 0.0078997988 | H42: =IF('1.1 Summary'!$C$15="Can",0,'4.2 PET Bottle Blowing'!F62) -> 1.8653017 | I42: =IF('1.1 Summary'!$C$15="Can",0,'4.2 PET Bottle Blowing'!G62) -> 0.10997241 | J42: =H42/$H$235 -> 0.0076028495
C43: Machine Operator | D43: =IF('1.1 Summary'!$C$15="Can",0,'4.2 PET Bottle Blowing'!F56) -> 1.1616204 | E43: =IF('1.1 Summary'!$C$15="Can",0,'4.2 PET Bottle Blowing'!G56) -> 0.085788108 | F43: =D43/$D$235 -> 0.0049196158 | H43: =IF('1.1 Summary'!$C$15="Can",0,'4.2 PET Bottle Blowing'!F63) -> 1.1616204 | I43: =IF('1.1 Summary'!$C$15="Can",0,'4.2 PET Bottle Blowing'!G63) -> 0.068485542 | J43: =H43/$H$235 -> 0.0047346901
C44: Production Worker | D44: =IF('1.1 Summary'!$C$15="Can",0,'4.2 PET Bottle Blowing'!F57) -> 2.214619 | E44: =IF('1.1 Summary'!$C$15="Can",0,'4.2 PET Bottle Blowing'!G57) -> 0.16355426 | F44: =D44/$D$235 -> 0.0093792037 | H44: =IF('1.1 Summary'!$C$15="Can",0,'4.2 PET Bottle Blowing'!F64) -> 2.214619 | I44: =IF('1.1 Summary'!$C$15="Can",0,'4.2 PET Bottle Blowing'!G64) -> 0.13056707 | J44: =H44/$H$235 -> 0.0090266444
C45: Total labor Cost | D45: =SUM(D41:D44) -> 7.4920606 | E45: =SUM(E41:E44) -> 0.5533044 | F45: =SUM(F41:F44) -> 0.031729865 | H45: =SUM(H41:H44) -> 7.4920606 | I45: =SUM(I41:I44) -> 0.44170868 | J45: =SUM(J41:J44) -> 0.030537156
C46: Total PET Bottle Blowing Cost | D46: =D45+D37+D32 -> 22.196822 | E46: =E45+E37+E32 -> 1.6392819 | F46: =SUM(F45,F37,F32) -> 0.094006472 | H46: =H45+H37+H32 -> 22.780393 | I46: =I45+I37+I32 -> 1.3430614 | J46: =SUM(J45,J37,J32) -> 0.092851412
C48: Wet Aseptic Cleaning Process
B49: Wet Aseptic Cleaning Process | C49: Machinery | D49: Total Hourly Cost (€) | E49: Total Depreciation per MT (€/MT) | F49: Percentage of the Total Cost (%) | H49: Total Hourly Cost (€) | I49: Total Depreciation per MT (€/MT) | J49: Percentage of the Total Cost (%)
C50: PET Bottle Washing and Rinsing Machine | D50: =IF('1.1 Summary'!C19="Wet Aseptic",'4.3 Wet Aseptic Cleaning'!F33,0) -> 0 | E50: ='4.3 Wet Aseptic Cleaning'!G33 -> 0 | F50: =D50/$D$235 -> 0 | H50: =IF('1.1 Summary'!C19="Wet Aseptic",'4.3 Wet Aseptic Cleaning'!F37,0) -> 0 | I50: ='4.3 Wet Aseptic Cleaning'!G37 -> 0 | J50: =H50/H$235 -> 0
C51: Total Machinery Cost | D51: =SUM(D50:D50) -> 0 | E51: =SUM(E50:E50) -> 0 | F51: =SUM(F50:F50) -> 0 | H51: =SUM(H50:H50) -> 0 | I51: =SUM(I50:I50) -> 0 | J51: =SUM(J50:J50) -> 0
C53: Utility | D53: Total Hourly Cost (€) | E53: Total Cost per MT (€/MT) | F53: Percentage of the Total Cost (%) | H53: Total Hourly Cost (€) | I53: Total Cost per MT (€/MT) | J53: Percentage of the Total Cost (%)
C54: Electricity and Natural Gas Cost | D54: =IF('1.1 Summary'!C19="Wet Aseptic",'4.3 Wet Aseptic Cleaning'!F43,0) -> 0 | E54: =IF('1.1 Summary'!$C$15="Can",0,'4.3 Wet Aseptic Cleaning'!G43) -> 0 | F54: =D54/$D$235 -> 0 | H54: =IF('1.1 Summary'!C19="Wet Aseptic",'4.3 Wet Aseptic Cleaning'!F47,0) -> 0 | I54: ='4.3 Wet Aseptic Cleaning'!G47 -> 0 | J54: =H54/$H$235 -> 0
C55: Other Utility Cost | D55: =15%*D54 -> 0 | E55: =15%*E54 -> 0 | F55: =D55/$D$235 -> 0 | H55: =15%*H54 -> 0 | I55: =15%*I54 -> 0 | J55: =H55/$H$235 -> 0
C56: Total Utility Cost | D56: =SUM(D54:D55) -> 0 | E56: =SUM(E54:E55) -> 0 | F56: =SUM(F54:F55) -> 0 | H56: =SUM(H54:H55) -> 0 | I56: =SUM(I54:I55) -> 0 | J56: =SUM(J54:J55) -> 0
C59: Labour Cost | D59: Total Hourly Cost (€) | E59: Total Cost per MT (€/MT) | F59: Percentage of the Total Cost (%) | H59: Total Hourly Cost (€) | I59: Total Cost per MT (€/MT) | J59: Percentage of the Total Cost (%)
C60: Production Manager | D60: =IF('1.1 Summary'!$C$19="Wet Aseptic",'4.3 Wet Aseptic Cleaning'!F53,0) -> 0 | E60: ='4.3 Wet Aseptic Cleaning'!G53 -> 0 | F60: =D60/$D$235 -> 0 | H60: =IF('1.1 Summary'!C19="Wet Aseptic",'4.3 Wet Aseptic Cleaning'!F60,0) -> 0 | I60: ='4.3 Wet Aseptic Cleaning'!G60 -> 0 | J60: =H60/$H$235 -> 0
C61: Shift Supervisor | D61: =IF('1.1 Summary'!$C$19="Wet Aseptic",'4.3 Wet Aseptic Cleaning'!F54,0) -> 0 | E61: ='4.3 Wet Aseptic Cleaning'!G54 -> 0 | F61: =D61/$D$235 -> 0 | H61: =IF('1.1 Summary'!C20="Wet Aseptic",'4.3 Wet Aseptic Cleaning'!F61,0) -> 0 | I61: ='4.3 Wet Aseptic Cleaning'!G61 -> 0 | J61: =H61/$H$235 -> 0
C62: Machine Operator | D62: =IF('1.1 Summary'!$C$19="Wet Aseptic",'4.3 Wet Aseptic Cleaning'!F55,0) -> 0 | E62: ='4.3 Wet Aseptic Cleaning'!G55 -> 0 | F62: =D62/$D$235 -> 0 | H62: =IF('1.1 Summary'!C21="Wet Aseptic",'4.3 Wet Aseptic Cleaning'!F62,0) -> 0 | I62: ='4.3 Wet Aseptic Cleaning'!G62 -> 0 | J62: =H62/$H$235 -> 0
C63: Production Worker | D63: =IF('1.1 Summary'!$C$19="Wet Aseptic",'4.3 Wet Aseptic Cleaning'!F56,0) -> 0 | E63: ='4.3 Wet Aseptic Cleaning'!G56 -> 0 | F63: =D63/$D$235 -> 0 | H63: =IF('1.1 Summary'!C22="Wet Aseptic",'4.3 Wet Aseptic Cleaning'!F63,0) -> 0 | I63: ='4.3 Wet Aseptic Cleaning'!G63 -> 0 | J63: =H63/$H$235 -> 0
C64: Total labor Cost | D64: =SUM(D60:D63) -> 0 | E64: =SUM(E60:E63) -> 0 | F64: =SUM(F60:F63) -> 0 | H64: =SUM(H60:H63) -> 0 | I64: =SUM(I60:I63) -> 0 | J64: =SUM(J60:J63) -> 0
C65: Total Wet Aseptic Cleaning Cost | D65: =D64+D56+D51 -> 0 | E65: =E64+E56+E51 -> 0 | F65: =SUM(F64,F56,F51) -> 0 | H65: =H64+H56+H51 -> 0 | I65: =I64+I56+I51 -> 0 | J65: =SUM(J64,J56,J51) -> 0
C67: Can Filling & Closing Process
B68: Can Filling & Closing Process | C68: Machinery | D68: Total Hourly Cost (€) | E68: Total Depreciation per MT (€/MT) | F68: Percentage of the Total Cost (%) | H68: Total Hourly Cost (€) | I68: Total Depreciation per MT (€/MT) | J68: Percentage of the Total Cost (%)
C69: Can Filling and Sealing Machine | D69: =IF('1.1 Summary'!$C$15="Can",'4.4 Can Filling & Closing'!F34,0) -> 0 | E69: ='4.4 Can Filling & Closing'!G34 -> 0 | F69: =D69/$D$235 -> 0 | H69: =IF('1.1 Summary'!$C$15="Can",'4.4 Can Filling & Closing'!F38,0) -> 0 | I69: ='4.4 Can Filling & Closing'!G38 -> 0 | J69: =H69/H$235 -> 0
C70: Total Machinery Cost | D70: =SUM(D69:D69) -> 0 | E70: =SUM(E69:E69) -> 0 | F70: =SUM(F69:F69) -> 0 | H70: =SUM(H69:H69) -> 0 | I70: =SUM(I69:I69) -> 0 | J70: =SUM(J69:J69) -> 0
C72: Utility | D72: Total Hourly Cost (€) | E72: Total Cost per MT (€/MT) | F72: Percentage of the Total Cost (%) | H72: Total Hourly Cost (€) | I72: Total Cost per MT (€/MT) | J72: Percentage of the Total Cost (%)
C73: Electricity and Natural Gas Cost | D73: =IF('1.1 Summary'!$C$15="Can",'4.4 Can Filling & Closing'!F44,0) -> 0 | E73: =IF('1.1 Summary'!$C$15="Can",'4.4 Can Filling & Closing'!G44,0) -> 0 | F73: =D73/$D$235 -> 0 | H73: =IF('1.1 Summary'!$C$15="Can",'4.4 Can Filling & Closing'!F48,0) -> 0 | I73: ='4.4 Can Filling & Closing'!G48 -> 0 | J73: =H73/$H$235 -> 0
C74: Other Utility Cost | D74: =15%*D73 -> 0 | E74: =15%*E73 -> 0 | F74: =D74/$D$235 -> 0 | H74: =15%*H73 -> 0 | I74: =15%*I73 -> 0 | J74: =H74/$H$235 -> 0
C75: Total Utility Cost | D75: =SUM(D73:D74) -> 0 | E75: =SUM(E73:E74) -> 0 | F75: =SUM(F73:F74) -> 0 | H75: =SUM(H73:H74) -> 0 | I75: =SUM(I73:I74) -> 0 | J75: =SUM(J73:J74) -> 0
C78: Labour Cost | D78: Total Hourly Cost (€) | E78: Total Cost per MT (€/MT) | F78: Percentage of the Total Cost (%) | H78: Total Hourly Cost (€) | I78: Total Cost per MT (€/MT) | J78: Percentage of the Total Cost (%)
C79: Production Manager | D79: =IF('1.1 Summary'!$C$15="Can",'4.4 Can Filling & Closing'!F54,0) -> 0 | E79: ='4.4 Can Filling & Closing'!G54 -> 0 | F79: =D79/$D$235 -> 0 | H79: =IF('1.1 Summary'!$C$15="Can",'4.4 Can Filling & Closing'!F61,0) -> 0 | I79: ='4.4 Can Filling & Closing'!G61 -> 0 | J79: =H79/$H$235 -> 0
C80: Shift Supervisor | D80: =IF('1.1 Summary'!$C$15="Can",'4.4 Can Filling & Closing'!F55,0) -> 0 | E80: ='4.4 Can Filling & Closing'!G55 -> 0 | F80: =D80/$D$235 -> 0 | H80: =IF('1.1 Summary'!$C$15="Can",'4.4 Can Filling & Closing'!F62,0) -> 0 | I80: ='4.4 Can Filling & Closing'!G62 -> 0 | J80: =H80/$H$235 -> 0
C81: Machine Operator | D81: =IF('1.1 Summary'!$C$15="Can",'4.4 Can Filling & Closing'!F56,0) -> 0 | E81: ='4.4 Can Filling & Closing'!G56 -> 0 | F81: =D81/$D$235 -> 0 | H81: =IF('1.1 Summary'!$C$15="Can",'4.4 Can Filling & Closing'!F63,0) -> 0 | I81: ='4.4 Can Filling & Closing'!G63 -> 0 | J81: =H81/$H$235 -> 0
C82: Production Worker | D82: =IF('1.1 Summary'!$C$15="Can",'4.4 Can Filling & Closing'!F57,0) -> 0 | E82: ='4.4 Can Filling & Closing'!G57 -> 0 | F82: =D82/$D$235 -> 0 | H82: =IF('1.1 Summary'!$C$15="Can",'4.4 Can Filling & Closing'!F64,0) -> 0 | I82: ='4.4 Can Filling & Closing'!G64 -> 0 | J82: =H82/$H$235 -> 0
C83: Total labor Cost | D83: =SUM(D79:D82) -> 0 | E83: =SUM(E79:E82) -> 0 | F83: =SUM(F79:F82) -> 0 | H83: =SUM(H79:H82) -> 0 | I83: =SUM(I79:I82) -> 0 | J83: =SUM(J79:J82) -> 0
C84: Total Aseptic Filling, Closing Packing Cost | D84: =D83+D75+D70 -> 0 | E84: =E83+E75+E70 -> 0 | F84: =SUM(F83,F75,F70) -> 0 | H84: =H83+H75+H70 -> 0 | I84: =I83+I75+I70 -> 0 | J84: =SUM(J83,J75,J70) -> 0
C86: Aseptic Filling, Closing Process
B87: Aseptic Filling, Closing Process | C87: Machinery | D87: Total Hourly Cost (€) | E87: Total Depreciation per MT (€/MT) | F87: Percentage of the Total Cost (%) | H87: Total Hourly Cost (€) | I87: Total Depreciation per MT (€/MT) | J87: Percentage of the Total Cost (%)
C88: Aseptic Liquid Filling and Capping Machine | D88: =IF('1.1 Summary'!$C$15="Can",0,'4.5 Aseptic Filling & Closing'!F34) -> 0.72916667 | E88: =IF('1.1 Summary'!$C$15="Can",0,'4.5 Aseptic Filling & Closing'!G34) -> 0.028083763 | F88: =D88/$D$235 -> 0.003088117 | H88: =IF('1.1 Summary'!$C$15="Can",0,'4.5 Aseptic Filling & Closing'!F38) -> 0.84635417 | I88: =IF('1.1 Summary'!$C$15="Can",0,'4.5 Aseptic Filling & Closing'!G38) -> 0.029031319 | J88: =H88/H$235 -> 0.003449685
C89: Total Machinery Cost | D89: =SUM(D88:D88) -> 0.72916667 | E89: =SUM(E88:E88) -> 0.028083763 | F89: =SUM(F88:F88) -> 0.003088117 | H89: =SUM(H88:H88) -> 0.84635417 | I89: =SUM(I88:I88) -> 0.029031319 | J89: =SUM(J88:J88) -> 0.003449685
C91: Utility | D91: Total Hourly Cost (€) | E91: Total Cost per MT (€/MT) | F91: Percentage of the Total Cost (%) | H91: Total Hourly Cost (€) | I91: Total Cost per MT (€/MT) | J91: Percentage of the Total Cost (%)
C92: Electricity and Natural Gas Cost | D92: =IF('1.1 Summary'!$C$15="Can",0,'4.5 Aseptic Filling & Closing'!F44) -> 3.0439397 | E92: =IF('1.1 Summary'!$C$15="Can",0,'4.5 Aseptic Filling & Closing'!G44) -> 0.11723695 | F92: =D92/$D$235 -> 0.012891486 | H92: =IF('1.1 Summary'!$C$15="Can",0,'4.5 Aseptic Filling & Closing'!F48) -> 3.5174246 | I92: =IF('1.1 Summary'!$C$15="Can",0,'4.5 Aseptic Filling & Closing'!G48) -> 0.12065336 | J92: =H92/$H$235 -> 0.014336796
C93: Other Utility Cost | D93: =15%*D92 -> 0.45659095 | E93: =15%*E92 -> 0.017585543 | F93: =D93/$D$235 -> 0.0019337229 | H93: =15%*H92 -> 0.52761368 | I93: =15%*I92 -> 0.018098004 | J93: =H93/$H$235 -> 0.0021505194
C94: Total Utility Cost | D94: =SUM(D92:D93) -> 3.5005306 | E94: =SUM(E92:E93) -> 0.1348225 | F94: =SUM(F92:F93) -> 0.014825209 | H94: =SUM(H92:H93) -> 4.0450383 | I94: =SUM(I92:I93) -> 0.13875136 | J94: =SUM(J92:J93) -> 0.016487315
C97: Labour Cost | D97: Total Hourly Cost (€) | E97: Total Cost per MT (€/MT) | F97: Percentage of the Total Cost (%) | H97: Total Hourly Cost (€) | I97: Total Cost per MT (€/MT) | J97: Percentage of the Total Cost (%)
C98: Production Manager | D98: =IF('1.1 Summary'!$C$15="Can",0,'4.5 Aseptic Filling & Closing'!F53) -> 2.2505195 | E98: =IF('1.1 Summary'!$C$15="Can",0,'4.5 Aseptic Filling & Closing'!G53) -> 0.086678474 | F98: =D98/$D$235 -> 0.0095312468 | H98: =IF('1.1 Summary'!$C$15="Can",0,'4.5 Aseptic Filling & Closing'!F60) -> 2.2505195 | I98: =IF('1.1 Summary'!$C$15="Can",0,'4.5 Aseptic Filling & Closing'!G60) -> 0.077196462 | J98: =H98/$H$235 -> 0.0091729723
C99: Shift Supervisor | D99: =IF('1.1 Summary'!$C$15="Can",0,'4.5 Aseptic Filling & Closing'!F54) -> 1.8653017 | E99: =IF('1.1 Summary'!$C$15="Can",0,'4.5 Aseptic Filling & Closing'!G54) -> 0.071841861 | F99: =D99/$D$235 -> 0.0078997988 | H99: =IF('1.1 Summary'!$C$15="Can",0,'4.5 Aseptic Filling & Closing'!F61) -> 1.8653017 | I99: =IF('1.1 Summary'!$C$15="Can",0,'4.5 Aseptic Filling & Closing'!G61) -> 0.063982869 | J99: =H99/$H$235 -> 0.0076028495
C100: Machine Operator | D100: =IF('1.1 Summary'!$C$15="Can",0,'4.5 Aseptic Filling & Closing'!F55) -> 1.1616204 | E100: =IF('1.1 Summary'!$C$15="Can",0,'4.5 Aseptic Filling & Closing'!G55) -> 0.044739665 | F100: =D100/$D$235 -> 0.0049196158 | H100: =IF('1.1 Summary'!$C$15="Can",0,'4.5 Aseptic Filling & Closing'!F62) -> 1.1616204 | I100: =IF('1.1 Summary'!$C$15="Can",0,'4.5 Aseptic Filling & Closing'!G62) -> 0.039845462 | J100: =H100/$H$235 -> 0.0047346901
C101: Production Worker | D101: =IF('1.1 Summary'!$C$15="Can",0,'4.5 Aseptic Filling & Closing'!F56) -> 2.214619 | E101: =IF('1.1 Summary'!$C$15="Can",0,'4.5 Aseptic Filling & Closing'!G56) -> 0.085295773 | F101: =D101/$D$235 -> 0.0093792037 | H101: =IF('1.1 Summary'!$C$15="Can",0,'4.5 Aseptic Filling & Closing'!F63) -> 2.214619 | I101: =IF('1.1 Summary'!$C$15="Can",0,'4.5 Aseptic Filling & Closing'!G63) -> 0.075965019 | J101: =H101/$H$235 -> 0.0090266444
C102: Total labor Cost | D102: =SUM(D98:D101) -> 7.4920606 | E102: =SUM(E98:E101) -> 0.28855577 | F102: =SUM(F98:F101) -> 0.031729865 | H102: =SUM(H98:H101) -> 7.4920606 | I102: =SUM(I98:I101) -> 0.25698981 | J102: =SUM(J98:J101) -> 0.030537156
C103: Total Aseptic Filling, Closing Packing Cost | D103: =D102+D94+D89 -> 11.721758 | E103: =E102+E94+E89 -> 0.45146203 | F103: =SUM(F102,F94,F89) -> 0.049643191 | H103: =H102+H94+H89 -> 12.383453 | I103: =I102+I94+I89 -> 0.4247725 | J103: =SUM(J102,J94,J89) -> 0.050474157
C105: Nitrogenation Process
B106: Nitrogenation Process | C106: Machinery | D106: Total Hourly Cost (€) | E106: Total Depreciation per MT (€/MT) | F106: Percentage of the Total Cost (%) | H106: Total Hourly Cost (€) | I106: Total Depreciation per MT (€/MT) | J106: Percentage of the Total Cost (%)
C107: Nitrogen Injection System | D107: =IF('1.1 Summary'!$C$14="Non-Carbonated",'4.6 Nitrogenation'!F33,0) -> 0.33854167 | E107: ='4.6 Nitrogenation'!G33 -> 0.012791654 | F107: =D107/$D$235 -> 0.0014337686 | H107: =IF('1.1 Summary'!$C$14="Non-Carbonated",'4.6 Nitrogenation'!F37,0) -> 0.37760417 | I107: ='4.6 Nitrogenation'!G37 -> 0.01270849 | J107: =H107/H$235 -> 0.0015390903
C108: Total Machinery Cost | D108: =SUM(D107:D107) -> 0.33854167 | E108: =SUM(E107:E107) -> 0.012791654 | F108: =SUM(F107:F107) -> 0.0014337686 | H108: =SUM(H107:H107) -> 0.37760417 | I108: =SUM(I107:I107) -> 0.01270849 | J108: =SUM(J107:J107) -> 0.0015390903
C110: Utility | D110: Total Hourly Cost (€) | E110: Total Cost per MT (€/MT) | F110: Percentage of the Total Cost (%) | H110: Total Hourly Cost (€) | I110: Total Cost per MT (€/MT) | J110: Percentage of the Total Cost (%)
C111: Electricity and Natural Gas Cost | D111: =IF('1.1 Summary'!$C$14="Non-Carbonated",'4.6 Nitrogenation'!F43,0) -> 3.0439397 | E111: ='4.6 Nitrogenation'!G43 -> 0.11501397 | F111: =D111/$D$235 -> 0.012891486 | H111: =IF('1.1 Summary'!$C$14="Non-Carbonated",'4.6 Nitrogenation'!F47,0) -> 3.5174246 | I111: ='4.6 Nitrogenation'!G47 -> 0.11838099 | J111: =H111/$H$235 -> 0.014336796
C112: Other Utility Cost | D112: =15%*D111 -> 0.45659095 | E112: =15%*E111 -> 0.017252096 | F112: =D112/$D$235 -> 0.0019337229 | H112: =15%*H111 -> 0.52761368 | I112: =15%*I111 -> 0.017757148 | J112: =H112/$H$235 -> 0.0021505194
C113: Total Utility Cost | D113: =SUM(D111:D112) -> 3.5005306 | E113: =SUM(E111:E112) -> 0.13226607 | F113: =SUM(F111:F112) -> 0.014825209 | H113: =SUM(H111:H112) -> 4.0450383 | I113: =SUM(I111:I112) -> 0.13613814 | J113: =SUM(J111:J112) -> 0.016487315
C116: Labour Cost | D116: Total Hourly Cost (€) | E116: Total Cost per MT (€/MT) | F116: Percentage of the Total Cost (%) | H116: Total Hourly Cost (€) | I116: Total Cost per MT (€/MT) | J116: Percentage of the Total Cost (%)
C117: Production Manager | D117: =IF('1.1 Summary'!$C$14="Non-Carbonated",'4.6 Nitrogenation'!F53,0) -> 2.2505195 | E117: ='4.6 Nitrogenation'!G53 -> 0.085034926 | F117: =D117/$D$235 -> 0.0095312468 | H117: =IF('1.1 Summary'!$C$14="Non-Carbonated",'4.6 Nitrogenation'!F60,0) -> 2.2505195 | I117: ='4.6 Nitrogenation'!G60 -> 0.075742554 | J117: =H117/$H$235 -> 0.0091729723
C118: Shift Supervisor | D118: =IF('1.1 Summary'!$C$14="Non-Carbonated",'4.6 Nitrogenation'!F54,0) -> 1.8653017 | E118: ='4.6 Nitrogenation'!G54 -> 0.070479636 | F118: =D118/$D$235 -> 0.0078997988 | H118: =IF('1.1 Summary'!$C$14="Non-Carbonated",'4.6 Nitrogenation'!F61,0) -> 1.8653017 | I118: ='4.6 Nitrogenation'!G61 -> 0.062777824 | J118: =H118/$H$235 -> 0.0076028495
C119: Machine Operator | D119: =IF('1.1 Summary'!$C$14="Non-Carbonated",'4.6 Nitrogenation'!F55,0) -> 1.1616204 | E119: ='4.6 Nitrogenation'!G55 -> 0.043891337 | F119: =D119/$D$235 -> 0.0049196158 | H119: =IF('1.1 Summary'!$C$14="Non-Carbonated",'4.6 Nitrogenation'!F62,0) -> 1.1616204 | I119: ='4.6 Nitrogenation'!G62 -> 0.039095018 | J119: =H119/$H$235 -> 0.0047346901
C120: Production Worker | D120: =IF('1.1 Summary'!$C$14="Non-Carbonated",'4.6 Nitrogenation'!F56,0) -> 2.214619 | E120: ='4.6 Nitrogenation'!G56 -> 0.083678442 | F120: =D120/$D$235 -> 0.0093792037 | H120: =IF('1.1 Summary'!$C$14="Non-Carbonated",'4.6 Nitrogenation'!F63,0) -> 2.214619 | I120: ='4.6 Nitrogenation'!G63 -> 0.074534303 | J120: =H120/$H$235 -> 0.0090266444
C121: Total labor Cost | D121: =SUM(D117:D120) -> 7.4920606 | E121: =SUM(E117:E120) -> 0.28308434 | F121: =SUM(F117:F120) -> 0.031729865 | H121: =SUM(H117:H120) -> 7.4920606 | I121: =SUM(I117:I120) -> 0.2521497 | J121: =SUM(J117:J120) -> 0.030537156
C122: Total Nitrogenation Cost | D122: =D121+D113+D108 -> 11.331133 | E122: =E121+E113+E108 -> 0.42814206 | F122: =SUM(F121,F113,F108) -> 0.047988843 | H122: =H121+H113+H108 -> 11.914703 | I122: =I121+I113+I108 -> 0.40099633 | J122: =SUM(J121,J113,J108) -> 0.048563562
C124: Can Pasteurisation Process
B125: Can Pasteurisation Process | C125: Machinery | D125: Total Hourly Cost (€) | E125: Total Depreciation per MT (€/MT) | F125: Percentage of the Total Cost (%) | H125: Total Hourly Cost (€) | I125: Total Depreciation per MT (€/MT) | J125: Percentage of the Total Cost (%)
C126: Steam Heating Tunnel Pasteuriser | D126: =IF('1.1 Summary'!$C$15="Can",'4.7 Can Pasteurisation'!F33,0) -> 0 | E126: =IF('1.1 Summary'!$C$15="Can",'4.7 Can Pasteurisation'!G33,0) -> 0 | F126: =D126/$D$235 -> 0 | H126: =IF('1.1 Summary'!$C$15="Can",'4.7 Can Pasteurisation'!F37,0) -> 0 | I126: =IF('1.1 Summary'!$C$15="Can",'4.7 Can Pasteurisation'!G37,0) -> 0 | J126: =H126/H$235 -> 0
C127: Total Machinery Cost | D127: =SUM(D126:D126) -> 0 | E127: =SUM(E126:E126) -> 0 | F127: =SUM(F126:F126) -> 0 | H127: =SUM(H126:H126) -> 0 | I127: =SUM(I126:I126) -> 0 | J127: =SUM(J126:J126) -> 0
C129: Utility | D129: Total Hourly Cost (€) | E129: Total Cost per MT (€/MT) | F129: Percentage of the Total Cost (%) | H129: Total Hourly Cost (€) | I129: Total Cost per MT (€/MT) | J129: Percentage of the Total Cost (%)
C130: Electricity and Natural Gas Cost | D130: =IF('1.1 Summary'!$C$15="Can",'4.7 Can Pasteurisation'!F43,0) -> 0 | E130: =IF('1.1 Summary'!$C$15="Can",'4.7 Can Pasteurisation'!G43,0) -> 0 | F130: =D130/$D$235 -> 0 | H130: =IF('1.1 Summary'!$C$15="Can",'4.7 Can Pasteurisation'!F47,0) -> 0 | I130: =IF('1.1 Summary'!$C$15="Can",'4.7 Can Pasteurisation'!G47,0) -> 0 | J130: =H130/$H$235 -> 0
...

Sheet 2.2 Cost Model Packing (2)
C5: Summary – Packing Cost
D7: Semi-Automatic | H7: Automatic
C8: Dry Aseptic Cleaning Process
B9: Dry Aseptic Cleaning Process | C9: Machinery | D9: Total Hourly Cost (€) | E9: Total Depreciation per MT (€/MT) | F9: Percentage of the Total Cost (%) | H9: Total Hourly Cost (€) | I9: Total Depreciation per MT (€/MT) | J9: Percentage of the Total Cost (%)
C10: Preform Steriliser | D10: ='4.1 Dry Aseptic Cleaning (2)'!F34 -> 0.28320312 | E10: ='4.1 Dry Aseptic Cleaning (2)'!G34 -> 0.015052887 | F10: =D10/$D$235 -> 0.0011769018 | H10: ='4.1 Dry Aseptic Cleaning (2)'!F39 -> 0.34179688 | I10: ='4.1 Dry Aseptic Cleaning (2)'!G39 -> 0.014968499 | J10: =H10/H$235 -> 0.0013672417
C11: Air Jet and Vacuum Cleaning Machines | D11: ='4.1 Dry Aseptic Cleaning (2)'!F35 -> 0.19042969 | E11: ='4.1 Dry Aseptic Cleaning (2)'!G35 -> 0.010121769 | F11: =D11/$D$235 -> 0.00079136499 | H11: ='4.1 Dry Aseptic Cleaning (2)'!F40 -> 0.234375 | I11: ='4.1 Dry Aseptic Cleaning (2)'!G40 -> 0.010264114 | J11: =H11/H$235 -> 0.00093753718
C12: Total Machinery Cost | D12: =SUM(D10:D11) -> 0.47363281 | E12: =SUM(E10:E11) -> 0.025174656 | F12: =SUM(F10:F11) -> 0.0019682668 | H12: =SUM(H10:H11) -> 0.57617188 | I12: =SUM(I10:I11) -> 0.025232613 | J12: =SUM(J10:J11) -> 0.0023047789
C14: Utility | D14: Total Hourly Cost (€) | E14: Total Cost per MT (€/MT) | F14: Percentage of the Total Cost (%) | H14: Total Hourly Cost (€) | I14: Total Cost per MT (€/MT) | J14: Total Cost per MT (€/MT)
C15: Electricity and Natural Gas Cost | D15: ='4.1 Dry Aseptic Cleaning (2)'!F47 -> 4.5590914 | E15: ='4.1 Dry Aseptic Cleaning (2)'!G47 -> 0.24232603 | F15: =D15/$D$235 -> 0.018946128 | H15: ='4.1 Dry Aseptic Cleaning (2)'!F52 -> 5.2409096 | I15: ='4.1 Dry Aseptic Cleaning (2)'!G52 -> 0.22951805 | J15: =H15/$H$235 -> 0.02096447
C16: Other Utility Cost | D16: =15%*D15 -> 0.68386371 | E16: =15%*E15 -> 0.036348904 | F16: =D16/$D$235 -> 0.0028419193 | H16: =15%*H15 -> 0.78613645 | I16: =15%*I15 -> 0.034427708 | J16: =H16/$H$235 -> 0.0031446705
C17: Total Utility Cost | D17: =SUM(D15:D16) -> 5.2429551 | E17: =SUM(E15:E16) -> 0.27867493 | F17: =SUM(F15:F16) -> 0.021788048 | H17: =SUM(H15:H16) -> 6.0270461 | I17: =SUM(I15:I16) -> 0.26394576 | J17: =SUM(J15:J16) -> 0.02410914
C20: Labour Cost | D20: Total Hourly Cost (€) | E20: Total Cost per MT (€/MT) | F20: Percentage of the Total Cost (%) | H20: Total Hourly Cost (€) | I20: Total Cost per MT (€/MT) | J20: Percentage of the Total Cost (%)
C21: Production Manager | D21: ='4.1 Dry Aseptic Cleaning (2)'!F58 -> 2.2505195 | E21: ='4.1 Dry Aseptic Cleaning (2)'!G58 -> 0.1196202 | F21: =D21/$D$235 -> 0.0093524404 | H21: ='4.1 Dry Aseptic Cleaning (2)'!F65 -> 2.2505195 | I21: ='4.1 Dry Aseptic Cleaning (2)'!G65 -> 0.098558243 | J21: =H21/$H$235 -> 0.0090024348
C22: Shift Supervisor | D22: ='4.1 Dry Aseptic Cleaning (2)'!F59 -> 1.8653017 | E22: ='4.1 Dry Aseptic Cleaning (2)'!G59 -> 0.099145007 | F22: =D22/$D$235 -> 0.0077515984 | H22: ='4.1 Dry Aseptic Cleaning (2)'!F66 -> 1.8653017 | I22: ='4.1 Dry Aseptic Cleaning (2)'!G66 -> 0.081688189 | J22: =H22/$H$235 -> 0.0074615027
C23: Machine Operator | D23: ='4.1 Dry Aseptic Cleaning (2)'!F60 -> 1.1616204 | E23: ='4.1 Dry Aseptic Cleaning (2)'!G60 -> 0.061742756 | F23: =D23/$D$235 -> 0.0048273237 | H23: ='4.1 Dry Aseptic Cleaning (2)'!F67 -> 1.1616204 | I23: ='4.1 Dry Aseptic Cleaning (2)'!G67 -> 0.050871486 | J23: =H23/$H$235 -> 0.004646666
C24: Production Worker | D24: ='4.1 Dry Aseptic Cleaning (2)'!F61 -> 2.214619 | E24: ='4.1 Dry Aseptic Cleaning (2)'!G61 -> 0.11771201 | F24: =D24/$D$235 -> 0.0092032496 | H24: ='4.1 Dry Aseptic Cleaning (2)'!F68 -> 2.214619 | I24: ='4.1 Dry Aseptic Cleaning (2)'!G68 -> 0.096986035 | J24: =H24/$H$235 -> 0.0088588273
C25: Total labor Cost | D25: =SUM(D21:D24) -> 7.4920606 | E25: =SUM(E21:E24) -> 0.39821998 | F25: =SUM(F21:F24) -> 0.031134612 | H25: =SUM(H21:H24) -> 7.4920606 | I25: =SUM(I21:I24) -> 0.32810395 | J25: =SUM(J21:J24) -> 0.029969431
C26: Total Dry Aseptic Cleaning Cost | D26: =D25+D17+D12 -> 13.208649 | E26: =E25+E17+E12 -> 0.70206956 | F26: =SUM(F25,F17,F12) -> 0.054890927 | H26: =H25+H17+H12 -> 14.095279 | I26: =I25+I17+I12 -> 0.61728233 | J26: =SUM(J25,J17,J12) -> 0.05638335
D28: Semi-Automatic | H28: Automatic
C29: PET Bottle Blowing Process
B30: PET Bottle Blowing Process | C30: Machinery | D30: Total Hourly Cost (€) | E30: Total Depreciation per MT (€/MT) | F30: Percentage of the Total Cost (%) | H30: Total Hourly Cost (€) | I30: Total Depreciation per MT (€/MT) | J30: Percentage of the Total Cost (%)
C31: PET Bottle Blowing Machine | D31: =IF('1.2 Scenario Analysis'!$H$14="Can",0,'4.2 PET Bottle Blowing (2)'!F35) -> 0.5078125 | E31: =IF('1.2 Scenario Analysis'!$H$14="Can",0,'4.2 PET Bottle Blowing (2)'!G35) -> 0.037503019 | F31: =D31/$D$235 -> 0.0021103066 | H31: =IF('1.2 Scenario Analysis'!$H$14="Can",0,'4.2 PET Bottle Blowing (2)'!F38) -> 0.53710938 | I31: =IF('1.2 Scenario Analysis'!$H$14="Can",0,'4.2 PET Bottle Blowing (2)'!G38) -> 0.031666304 | J31: =H31/H$235 -> 0.0021485227
C32: Total Machinery Cost | D32: =SUM(D31:D31) -> 0.5078125 | E32: =SUM(E31:E31) -> 0.037503019 | F32: =SUM(F31:F31) -> 0.0021103066 | H32: =SUM(H31:H31) -> 0.53710938 | I32: =SUM(I31:I31) -> 0.031666304 | J32: =SUM(J31:J31) -> 0.0021485227
C34: Utility | D34: Total Hourly Cost (€) | E34: Total Cost per MT (€/MT) | F34: Percentage of the Total Cost (%) | H34: Total Hourly Cost (€) | I34: Total Cost per MT (€/MT) | J34: Total Cost per MT (€/MT)
C35: Electricity and Natural Gas Cost | D35: =IF('1.2 Scenario Analysis'!$H$14="Can",0,'4.2 PET Bottle Blowing (2)'!F45) -> 13.08182 | E35: =IF('1.2 Scenario Analysis'!$H$14="Can",0,'4.2 PET Bottle Blowing (2)'!G45) -> 0.96611986 | F35: =D35/$D$235 -> 0.054363867 | H35: =IF('1.2 Scenario Analysis'!$H$14="Can",0,'4.2 PET Bottle Blowing (2)'!F49) -> 13.593184 | I35: =IF('1.2 Scenario Analysis'!$H$14="Can",0,'4.2 PET Bottle Blowing (2)'!G49) -> 0.80141198 | J35: =H35/$H$235 -> 0.05437489
C36: Other Utility Cost | D36: =15%*D35 -> 1.962273 | E36: =15%*E35 -> 0.14491798 | F36: =D36/$D$235 -> 0.00815458 | H36: =15%*H35 -> 2.0389775 | I36: =15%*I35 -> 0.1202118 | J36: =H36/$H$235 -> 0.0081562335
C37: Total Utility Cost | D37: =SUM(D35:D36) -> 15.044093 | E37: =SUM(E35:E36) -> 1.1110378 | F37: =SUM(F35:F36) -> 0.062518447 | H37: =SUM(H35:H36) -> 15.632161 | I37: =SUM(I35:I36) -> 0.92162378 | J37: =SUM(J35:J36) -> 0.062531124
C40: Labour Cost | D40: Total Hourly Cost (€) | E40: Total Cost per MT (€/MT) | F40: Percentage of the Total Cost (%) | H40: Total Hourly Cost (€) | I40: Total Cost per MT (€/MT) | J40: Percentage of the Total Cost (%)
C41: Production Manager | D41: =IF('1.2 Scenario Analysis'!$H$14="Can",0,'4.2 PET Bottle Blowing (2)'!F54) -> 2.2505195 | E41: =IF('1.2 Scenario Analysis'!$H$14="Can",0,'4.2 PET Bottle Blowing (2)'!G54) -> 0.16620559 | F41: =D41/$D$235 -> 0.0093524404 | H41: =IF('1.2 Scenario Analysis'!$H$14="Can",0,'4.2 PET Bottle Blowing (2)'!F61) -> 2.2505195 | I41: =IF('1.2 Scenario Analysis'!$H$14="Can",0,'4.2 PET Bottle Blowing (2)'!G61) -> 0.13268365 | J41: =H41/$H$235 -> 0.0090024348
C42: Shift Supervisor | D42: =IF('1.2 Scenario Analysis'!$H$14="Can",0,'4.2 PET Bottle Blowing (2)'!F55) -> 1.8653017 | E42: =IF('1.2 Scenario Analysis'!$H$14="Can",0,'4.2 PET Bottle Blowing (2)'!G55) -> 0.13775645 | F42: =D42/$D$235 -> 0.0077515984 | H42: =IF('1.2 Scenario Analysis'!$H$14="Can",0,'4.2 PET Bottle Blowing (2)'!F62) -> 1.8653017 | I42: =IF('1.2 Scenario Analysis'!$H$14="Can",0,'4.2 PET Bottle Blowing (2)'!G62) -> 0.10997241 | J42: =H42/$H$235 -> 0.0074615027
C43: Machine Operator | D43: =IF('1.2 Scenario Analysis'!$H$14="Can",0,'4.2 PET Bottle Blowing (2)'!F56) -> 1.1616204 | E43: =IF('1.2 Scenario Analysis'!$H$14="Can",0,'4.2 PET Bottle Blowing (2)'!G56) -> 0.085788108 | F43: =D43/$D$235 -> 0.0048273237 | H43: =IF('1.2 Scenario Analysis'!$H$14="Can",0,'4.2 PET Bottle Blowing (2)'!F63) -> 1.1616204 | I43: =IF('1.2 Scenario Analysis'!$H$14="Can",0,'4.2 PET Bottle Blowing (2)'!G63) -> 0.068485542 | J43: =H43/$H$235 -> 0.004646666
C44: Production Worker | D44: =IF('1.2 Scenario Analysis'!$H$14="Can",0,'4.2 PET Bottle Blowing (2)'!F57) -> 2.214619 | E44: =IF('1.2 Scenario Analysis'!$H$14="Can",0,'4.2 PET Bottle Blowing (2)'!G57) -> 0.16355426 | F44: =D44/$D$235 -> 0.0092032496 | H44: =IF('1.2 Scenario Analysis'!$H$14="Can",0,'4.2 PET Bottle Blowing (2)'!F64) -> 2.214619 | I44: =IF('1.2 Scenario Analysis'!$H$14="Can",0,'4.2 PET Bottle Blowing (2)'!G64) -> 0.13056707 | J44: =H44/$H$235 -> 0.0088588273
C45: Total labor Cost | D45: =SUM(D41:D44) -> 7.4920606 | E45: =SUM(E41:E44) -> 0.5533044 | F45: =SUM(F41:F44) -> 0.031134612 | H45: =SUM(H41:H44) -> 7.4920606 | I45: =SUM(I41:I44) -> 0.44170868 | J45: =SUM(J41:J44) -> 0.029969431
C46: Total PET Bottle Blowing Cost | D46: =D45+D37+D32 -> 23.043966 | E46: =E45+E37+E32 -> 1.7018453 | F46: =SUM(F45,F37,F32) -> 0.095763366 | H46: =H45+H37+H32 -> 23.661331 | I46: =I45+I37+I32 -> 1.3949988 | J46: =SUM(J45,J37,J32) -> 0.094649077
C48: Wet Aseptic Cleaning Process
B49: Wet Aseptic Cleaning Process | C49: Machinery | D49: Total Hourly Cost (€) | E49: Total Depreciation per MT (€/MT) | F49: Percentage of the Total Cost (%) | H49: Total Hourly Cost (€) | I49: Total Depreciation per MT (€/MT) | J49: Percentage of the Total Cost (%)
C50: PET Bottle Washing and Rinsing Machine | D50: =IF('1.2 Scenario Analysis'!$H$18="Wet Aseptic",'4.3 Wet Aseptic Cleaning (2)'!F34,0) -> 0 | E50: =IF('1.2 Scenario Analysis'!$H$18="Wet Aseptic",'4.3 Wet Aseptic Cleaning (2)'!G34,0) -> 0 | F50: =D50/$D$235 -> 0 | H50: =IF('1.2 Scenario Analysis'!$H$18="Wet Aseptic",'4.3 Wet Aseptic Cleaning (2)'!F37,0) -> 0 | I50: =IF('1.2 Scenario Analysis'!$H$18="Wet Aseptic",'4.3 Wet Aseptic Cleaning (2)'!G37,0) -> 0 | J50: =H50/H$235 -> 0
C51: Total Machinery Cost | D51: =SUM(D50:D50) -> 0 | E51: =SUM(E50:E50) -> 0 | F51: =SUM(F50:F50) -> 0 | H51: =SUM(H50:H50) -> 0 | I51: =SUM(I50:I50) -> 0 | J51: =SUM(J50:J50) -> 0
C53: Utility | D53: Total Hourly Cost (€) | E53: Total Cost per MT (€/MT) | F53: Percentage of the Total Cost (%) | H53: Total Hourly Cost (€) | I53: Total Cost per MT (€/MT) | J53: Percentage of the Total Cost (%)
C54: Electricity and Natural Gas Cost | D54: =IF('1.2 Scenario Analysis'!$H$18="Wet Aseptic",'4.3 Wet Aseptic Cleaning (2)'!F43,0) -> 0 | E54: =IF('1.2 Scenario Analysis'!$H$18="Wet Aseptic",'4.3 Wet Aseptic Cleaning (2)'!G43,0) -> 0 | F54: =D54/$D$235 -> 0 | H54: =IF('1.2 Scenario Analysis'!$H$18="Wet Aseptic",'4.3 Wet Aseptic Cleaning (2)'!F47,0) -> 0 | I54: =IF('1.2 Scenario Analysis'!$H$18="Wet Aseptic",'4.3 Wet Aseptic Cleaning (2)'!G47,0) -> 0 | J54: =H54/$H$235 -> 0
C55: Other Utility Cost | D55: =15%*D54 -> 0 | E55: =15%*E54 -> 0 | F55: =D55/$D$235 -> 0 | H55: =15%*H54 -> 0 | I55: =15%*I54 -> 0 | J55: =H55/$H$235 -> 0
C56: Total Utility Cost | D56: =SUM(D54:D55) -> 0 | E56: =SUM(E54:E55) -> 0 | F56: =SUM(F54:F55) -> 0 | H56: =SUM(H54:H55) -> 0 | I56: =SUM(I54:I55) -> 0 | J56: =SUM(J54:J55) -> 0
C59: Labour Cost | D59: Total Hourly Cost (€) | E59: Total Cost per MT (€/MT) | F59: Percentage of the Total Cost (%) | H59: Total Hourly Cost (€) | I59: Total Cost per MT (€/MT) | J59: Percentage of the Total Cost (%)
C60: Production Manager | D60: =IF('1.2 Scenario Analysis'!$H$18="Wet Aseptic",'4.3 Wet Aseptic Cleaning (2)'!F53,0) -> 0 | E60: =IF('1.2 Scenario Analysis'!$H$18="Wet Aseptic",'4.3 Wet Aseptic Cleaning (2)'!G53,0) -> 0 | F60: =D60/$D$235 -> 0 | H60: =IF('1.2 Scenario Analysis'!$H$18="Wet Aseptic",'4.3 Wet Aseptic Cleaning (2)'!F60,0) -> 0 | I60: =IF('1.2 Scenario Analysis'!$H$18="Wet Aseptic",'4.3 Wet Aseptic Cleaning (2)'!G60,0) -> 0 | J60: =H60/$H$235 -> 0
C61: Shift Supervisor | D61: =IF('1.2 Scenario Analysis'!$H$18="Wet Aseptic",'4.3 Wet Aseptic Cleaning (2)'!F54,0) -> 0 | E61: =IF('1.2 Scenario Analysis'!$H$18="Wet Aseptic",'4.3 Wet Aseptic Cleaning (2)'!G54,0) -> 0 | F61: =D61/$D$235 -> 0 | H61: =IF('1.2 Scenario Analysis'!$H$18="Wet Aseptic",'4.3 Wet Aseptic Cleaning (2)'!F61,0) -> 0 | I61: =IF('1.2 Scenario Analysis'!$H$18="Wet Aseptic",'4.3 Wet Aseptic Cleaning (2)'!G61,0) -> 0 | J61: =H61/$H$235 -> 0
C62: Machine Operator | D62: =IF('1.2 Scenario Analysis'!$H$18="Wet Aseptic",'4.3 Wet Aseptic Cleaning (2)'!F55,0) -> 0 | E62: =IF('1.2 Scenario Analysis'!$H$18="Wet Aseptic",'4.3 Wet Aseptic Cleaning (2)'!G55,0) -> 0 | F62: =D62/$D$235 -> 0 | H62: =IF('1.2 Scenario Analysis'!$H$18="Wet Aseptic",'4.3 Wet Aseptic Cleaning (2)'!F62,0) -> 0 | I62: =IF('1.2 Scenario Analysis'!$H$18="Wet Aseptic",'4.3 Wet Aseptic Cleaning (2)'!G62,0) -> 0 | J62: =H62/$H$235 -> 0
C63: Production Worker | D63: =IF('1.2 Scenario Analysis'!$H$18="Wet Aseptic",'4.3 Wet Aseptic Cleaning (2)'!F56,0) -> 0 | E63: =IF('1.2 Scenario Analysis'!$H$18="Wet Aseptic",'4.3 Wet Aseptic Cleaning (2)'!G56,0) -> 0 | F63: =D63/$D$235 -> 0 | H63: =IF('1.2 Scenario Analysis'!$H$18="Wet Aseptic",'4.3 Wet Aseptic Cleaning (2)'!F63,0) -> 0 | I63: =IF('1.2 Scenario Analysis'!$H$18="Wet Aseptic",'4.3 Wet Aseptic Cleaning (2)'!G63,0) -> 0 | J63: =H63/$H$235 -> 0
C64: Total labor Cost | D64: =SUM(D60:D63) -> 0 | E64: =SUM(E60:E63) -> 0 | F64: =SUM(F60:F63) -> 0 | H64: =SUM(H60:H63) -> 0 | I64: =SUM(I60:I63) -> 0 | J64: =SUM(J60:J63) -> 0
C65: Total Wet Aseptic Cleaning Cost | D65: =D64+D56+D51 -> 0 | E65: =E64+E56+E51 -> 0 | F65: =SUM(F64,F56,F51) -> 0 | H65: =H64+H56+H51 -> 0 | I65: =I64+I56+I51 -> 0 | J65: =SUM(J64,J56,J51) -> 0
C67: Can Filling & Closing Process
B68: Can Filling & Closing Process | C68: Machinery | D68: Total Hourly Cost (€) | E68: Total Depreciation per MT (€/MT) | F68: Percentage of the Total Cost (%) | H68: Total Hourly Cost (€) | I68: Total Depreciation per MT (€/MT) | J68: Percentage of the Total Cost (%)
C69: Can Filling and Sealing Machine | D69: =IF('1.2 Scenario Analysis'!$H$14="Can",'4.4 Can Filling & Closing (2)'!F34,0) -> 0 | E69: =IF('1.2 Scenario Analysis'!$H$14="Can",'4.4 Can Filling & Closing (2)'!G34,0) -> 0 | F69: =D69/$D$235 -> 0 | H69: =IF('1.2 Scenario Analysis'!$H$14="Can",'4.4 Can Filling & Closing (2)'!F38,0) -> 0 | I69: =IF('1.2 Scenario Analysis'!$H$14="Can",'4.4 Can Filling & Closing (2)'!G38,0) -> 0 | J69: =H69/H$235 -> 0
C70: Total Machinery Cost | D70: =SUM(D69:D69) -> 0 | E70: =SUM(E69:E69) -> 0 | F70: =SUM(F69:F69) -> 0 | H70: =SUM(H69:H69) -> 0 | I70: =SUM(I69:I69) -> 0 | J70: =SUM(J69:J69) -> 0
C72: Utility | D72: Total Hourly Cost (€) | E72: Total Cost per MT (€/MT) | F72: Percentage of the Total Cost (%) | H72: Total Hourly Cost (€) | I72: Total Cost per MT (€/MT) | J72: Percentage of the Total Cost (%)
C73: Electricity and Natural Gas Cost | D73: =IF('1.2 Scenario Analysis'!$H$14="Can",'4.4 Can Filling & Closing (2)'!F44,0) -> 0 | E73: =IF('1.2 Scenario Analysis'!$H$14="Can",'4.4 Can Filling & Closing (2)'!G44,0) -> 0 | F73: =D73/$D$235 -> 0 | H73: =IF('1.2 Scenario Analysis'!$H$14="Can",'4.4 Can Filling & Closing (2)'!F48,0) -> 0 | I73: =IF('1.2 Scenario Analysis'!$H$14="Can",'4.4 Can Filling & Closing (2)'!G48,0) -> 0 | J73: =H73/$H$235 -> 0
C74: Other Utility Cost | D74: =15%*D73 -> 0 | E74: =15%*E73 -> 0 | F74: =D74/$D$235 -> 0 | H74: =15%*H73 -> 0 | I74: =15%*I73 -> 0 | J74: =H74/$H$235 -> 0
C75: Total Utility Cost | D75: =SUM(D73:D74) -> 0 | E75: =SUM(E73:E74) -> 0 | F75: =SUM(F73:F74) -> 0 | H75: =SUM(H73:H74) -> 0 | I75: =SUM(I73:I74) -> 0 | J75: =SUM(J73:J74) -> 0
C78: Labour Cost | D78: Total Hourly Cost (€) | E78: Total Cost per MT (€/MT) | F78: Percentage of the Total Cost (%) | H78: Total Hourly Cost (€) | I78: Total Cost per MT (€/MT) | J78: Percentage of the Total Cost (%)
C79: Production Manager | D79: =IF('1.2 Scenario Analysis'!$H$14="Can",'4.4 Can Filling & Closing (2)'!F54,0) -> 0 | E79: =IF('1.2 Scenario Analysis'!$H$14="Can",'4.4 Can Filling & Closing (2)'!G54,0) -> 0 | F79: =D79/$D$235 -> 0 | H79: =IF('1.2 Scenario Analysis'!$H$14="Can",'4.4 Can Filling & Closing (2)'!F61,0) -> 0 | I79: =IF('1.2 Scenario Analysis'!$H$14="Can",'4.4 Can Filling & Closing (2)'!G61,0) -> 0 | J79: =H79/$H$235 -> 0
C80: Shift Supervisor | D80: =IF('1.2 Scenario Analysis'!$H$14="Can",'4.4 Can Filling & Closing (2)'!F55,0) -> 0 | E80: =IF('1.2 Scenario Analysis'!$H$14="Can",'4.4 Can Filling & Closing (2)'!G55,0) -> 0 | F80: =D80/$D$235 -> 0 | H80: =IF('1.2 Scenario Analysis'!$H$14="Can",'4.4 Can Filling & Closing (2)'!F62,0) -> 0 | I80: =IF('1.2 Scenario Analysis'!$H$14="Can",'4.4 Can Filling & Closing (2)'!G62,0) -> 0 | J80: =H80/$H$235 -> 0
C81: Machine Operator | D81: =IF('1.2 Scenario Analysis'!$H$14="Can",'4.4 Can Filling & Closing (2)'!F56,0) -> 0 | E81: =IF('1.2 Scenario Analysis'!$H$14="Can",'4.4 Can Filling & Closing (2)'!G56,0) -> 0 | F81: =D81/$D$235 -> 0 | H81: =IF('1.2 Scenario Analysis'!$H$14="Can",'4.4 Can Filling & Closing (2)'!F63,0) -> 0 | I81: =IF('1.2 Scenario Analysis'!$H$14="Can",'4.4 Can Filling & Closing (2)'!G63,0) -> 0 | J81: =H81/$H$235 -> 0
C82: Production Worker | D82: =IF('1.2 Scenario Analysis'!$H$14="Can",'4.4 Can Filling & Closing (2)'!F57,0) -> 0 | E82: =IF('1.2 Scenario Analysis'!$H$14="Can",'4.4 Can Filling & Closing (2)'!G57,0) -> 0 | F82: =D82/$D$235 -> 0 | H82: =IF('1.2 Scenario Analysis'!$H$14="Can",'4.4 Can Filling & Closing (2)'!F64,0) -> 0 | I82: =IF('1.2 Scenario Analysis'!$H$14="Can",'4.4 Can Filling & Closing (2)'!G64,0) -> 0 | J82: =H82/$H$235 -> 0
C83: Total labor Cost | D83: =SUM(D79:D82) -> 0 | E83: =SUM(E79:E82) -> 0 | F83: =SUM(F79:F82) -> 0 | H83: =SUM(H79:H82) -> 0 | I83: =SUM(I79:I82) -> 0 | J83: =SUM(J79:J82) -> 0
C84: Total Aseptic Filling, Closing Packing Cost | D84: =D83+D75+D70 -> 0 | E84: =E83+E75+E70 -> 0 | F84: =SUM(F83,F75,F70) -> 0 | H84: =H83+H75+H70 -> 0 | I84: =I83+I75+I70 -> 0 | J84: =SUM(J83,J75,J70) -> 0
C86: Aseptic Filling, Closing Process
B87: Aseptic Filling, Closing Process | C87: Machinery | D87: Total Hourly Cost (€) | E87: Total Depreciation per MT (€/MT) | F87: Percentage of the Total Cost (%) | H87: Total Hourly Cost (€) | I87: Total Depreciation per MT (€/MT) | J87: Percentage of the Total Cost (%)
C88: Aseptic Liquid Filling and Capping Machine | D88: =IF('1.2 Scenario Analysis'!$H$14="Can",0,'4.5 Aseptic Filling & Closi (2)'!F33) -> 0.546875 | E88: =IF('1.2 Scenario Analysis'!$H$14="Can",0,'4.5 Aseptic Filling & Closi (2)'!G33) -> 0.021062822 | F88: =D88/$D$235 -> 0.0022726379 | H88: =IF('1.2 Scenario Analysis'!$H$14="Can",0,'4.5 Aseptic Filling & Closi (2)'!F38) -> 0.63476562 | I88: =IF('1.2 Scenario Analysis'!$H$14="Can",0,'4.5 Aseptic Filling & Closi (2)'!G38) -> 0.021773489 | J88: =H88/H$235 -> 0.0025391632
C89: Total Machinery Cost | D89: =SUM(D88:D88) -> 0.546875 | E89: =SUM(E88:E88) -> 0.021062822 | F89: =SUM(F88:F88) -> 0.0022726379 | H89: =SUM(H88:H88) -> 0.63476562 | I89: =SUM(I88:I88) -> 0.021773489 | J89: =SUM(J88:J88) -> 0.0025391632
C91: Utility | D91: Total Hourly Cost (€) | E91: Total Cost per MT (€/MT) | F91: Percentage of the Total Cost (%) | H91: Total Hourly Cost (€) | I91: Total Cost per MT (€/MT) | J91: Percentage of the Total Cost (%)
C92: Electricity and Natural Gas Cost | D92: =IF('1.2 Scenario Analysis'!$H$14="Can",0,'4.5 Aseptic Filling & Closi (2)'!F44) -> 3.1954548 | E92: =IF('1.2 Scenario Analysis'!$H$14="Can",0,'4.5 Aseptic Filling & Closi (2)'!G44) -> 0.12307254 | F92: =D92/$D$235 -> 0.01327929 | H92: =IF('1.2 Scenario Analysis'!$H$14="Can",0,'4.5 Aseptic Filling & Closi (2)'!F48) -> 3.7068185 | I92: =IF('1.2 Scenario Analysis'!$H$14="Can",0,'4.5 Aseptic Filling & Closi (2)'!G48) -> 0.12714988 | J92: =H92/$H$235 -> 0.014827862
C93: Other Utility Cost | D93: =15%*D92 -> 0.47931822 | E93: =15%*E92 -> 0.018460881 | F93: =D93/$D$235 -> 0.0019918935 | H93: =15%*H92 -> 0.55602278 | I93: =15%*I92 -> 0.019072482 | J93: =H93/$H$235 -> 0.0022241793
C94: Total Utility Cost | D94: =SUM(D92:D93) -> 3.674773 | E94: =SUM(E92:E93) -> 0.14153342 | F94: =SUM(F92:F93) -> 0.015271184 | H94: =SUM(H92:H93) -> 4.2628413 | I94: =SUM(I92:I93) -> 0.14622236 | J94: =SUM(J92:J93) -> 0.017052041
C97: Labour Cost | D97: Total Hourly Cost (€) | E97: Total Cost per MT (€/MT) | F97: Percentage of the Total Cost (%) | H97: Total Hourly Cost (€) | I97: Total Cost per MT (€/MT) | J97: Percentage of the Total Cost (%)
C98: Production Manager | D98: =IF('1.2 Scenario Analysis'!$H$14="Can",0,'4.5 Aseptic Filling & Closi (2)'!F53) -> 2.2505195 | E98: =IF('1.2 Scenario Analysis'!$H$14="Can",0,'4.5 Aseptic Filling & Closi (2)'!G53) -> 0.086678474 | F98: =D98/$D$235 -> 0.0093524404 | H98: =IF('1.2 Scenario Analysis'!$H$14="Can",0,'4.5 Aseptic Filling & Closi (2)'!F60) -> 2.2505195 | I98: =IF('1.2 Scenario Analysis'!$H$14="Can",0,'4.5 Aseptic Filling & Closi (2)'!G60) -> 0.077196462 | J98: =H98/$H$235 -> 0.0090024348
C99: Shift Supervisor | D99: =IF('1.2 Scenario Analysis'!$H$14="Can",0,'4.5 Aseptic Filling & Closi (2)'!F54) -> 1.8653017 | E99: =IF('1.2 Scenario Analysis'!$H$14="Can",0,'4.5 Aseptic Filling & Closi (2)'!G54) -> 0.071841861 | F99: =D99/$D$235 -> 0.0077515984 | H99: =IF('1.2 Scenario Analysis'!$H$14="Can",0,'4.5 Aseptic Filling & Closi (2)'!F61) -> 1.8653017 | I99: =IF('1.2 Scenario Analysis'!$H$14="Can",0,'4.5 Aseptic Filling & Closi (2)'!G61) -> 0.063982869 | J99: =H99/$H$235 -> 0.0074615027
C100: Machine Operator | D100: =IF('1.2 Scenario Analysis'!$H$14="Can",0,'4.5 Aseptic Filling & Closi (2)'!F55) -> 1.1616204 | E100: =IF('1.2 Scenario Analysis'!$H$14="Can",0,'4.5 Aseptic Filling & Closi (2)'!G55) -> 0.044739665 | F100: =D100/$D$235 -> 0.0048273237 | H100: =IF('1.2 Scenario Analysis'!$H$14="Can",0,'4.5 Aseptic Filling & Closi (2)'!F62) -> 1.1616204 | I100: =IF('1.2 Scenario Analysis'!$H$14="Can",0,'4.5 Aseptic Filling & Closi (2)'!G62) -> 0.039845462 | J100: =H100/$H$235 -> 0.004646666
C101: Production Worker | D101: =IF('1.2 Scenario Analysis'!$H$14="Can",0,'4.5 Aseptic Filling & Closi (2)'!F56) -> 2.214619 | E101: =IF('1.2 Scenario Analysis'!$H$14="Can",0,'4.5 Aseptic Filling & Closi (2)'!G56) -> 0.085295773 | F101: =D101/$D$235 -> 0.0092032496 | H101: =IF('1.2 Scenario Analysis'!$H$14="Can",0,'4.5 Aseptic Filling & Closi (2)'!F63) -> 2.214619 | I101: =IF('1.2 Scenario Analysis'!$H$14="Can",0,'4.5 Aseptic Filling & Closi (2)'!G63) -> 0.075965019 | J101: =H101/$H$235 -> 0.0088588273
C102: Total labor Cost | D102: =SUM(D98:D101) -> 7.4920606 | E102: =SUM(E98:E101) -> 0.28855577 | F102: =SUM(F98:F101) -> 0.031134612 | H102: =SUM(H98:H101) -> 7.4920606 | I102: =SUM(I98:I101) -> 0.25698981 | J102: =SUM(J98:J101) -> 0.029969431
C103: Total Aseptic Filling, Closing Packing Cost | D103: =D102+D94+D89 -> 11.713709 | E103: =E102+E94+E89 -> 0.45115202 | F103: =SUM(F102,F94,F89) -> 0.048678434 | H103: =H102+H94+H89 -> 12.389668 | I103: =I102+I94+I89 -> 0.42498566 | J103: =SUM(J102,J94,J89) -> 0.049560635
C105: Nitrogenation Process
B106: Nitrogenation Process | C106: Machinery | D106: Total Hourly Cost (€) | E106: Total Depreciation per MT (€/MT) | F106: Percentage of the Total Cost (%) | H106: Total Hourly Cost (€) | I106: Total Depreciation per MT (€/MT) | J106: Percentage of the Total Cost (%)
C107: Nitrogen Injection System | D107: =IF('1.2 Scenario Analysis'!$H$13="Non-Carbonated",'4.6 Nitrogenation (2)'!F33,0) -> 0.25390625 | E107: =IF('1.2 Scenario Analysis'!$H$13="Non-Carbonated",'4.6 Nitrogenation (2)'!G33,0) -> 0.0095937402 | F107: =D107/$D$235 -> 0.0010551533 | H107: =IF('1.2 Scenario Analysis'!$H$13="Non-Carbonated",'4.6 Nitrogenation (2)'!F37,0) -> 0.28320312 | I107: =IF('1.2 Scenario Analysis'!$H$13="Non-Carbonated",'4.6 Nitrogenation (2)'!G37,0) -> 0.0095313675 | J107: =H107/H$235 -> 0.0011328574
C108: Total Machinery Cost | D108: =SUM(D107:D107) -> 0.25390625 | E108: =SUM(E107:E107) -> 0.0095937402 | F108: =SUM(F107:F107) -> 0.0010551533 | H108: =SUM(H107:H107) -> 0.28320312 | I108: =SUM(I107:I107) -> 0.0095313675 | J108: =SUM(J107:J107) -> 0.0011328574
C110: Utility | D110: Total Hourly Cost (€) | E110: Total Cost per MT (€/MT) | F110: Percentage of the Total Cost (%) | H110: Total Hourly Cost (€) | I110: Total Cost per MT (€/MT) | J110: Percentage of the Total Cost (%)
C111: Electricity and Natural Gas Cost | D111: =IF('1.2 Scenario Analysis'!$H$13="Non-Carbonated",'4.6 Nitrogenation (2)'!F43,0) -> 3.1954548 | E111: =IF('1.2 Scenario Analysis'!$H$13="Non-Carbonated",'4.6 Nitrogenation (2)'!G43,0) -> 0.12073891 | F111: =D111/$D$235 -> 0.01327929 | H111: =IF('1.2 Scenario Analysis'!$H$13="Non-Carbonated",'4.6 Nitrogenation (2)'!F47,0) -> 3.7068185 | I111: =IF('1.2 Scenario Analysis'!$H$13="Non-Carbonated",'4.6 Nitrogenation (2)'!G47,0) -> 0.12475515 | J111: =H111/$H$235 -> 0.014827862
C112: Other Utility Cost | D112: =15%*D111 -> 0.47931822 | E112: =15%*E111 -> 0.018110836 | F112: =D112/$D$235 -> 0.0019918935 | H112: =15%*H111 -> 0.55602278 | I112: =15%*I111 -> 0.018713273 | J112: =H112/$H$235 -> 0.0022241793
C113: Total Utility Cost | D113: =SUM(D111:D112) -> 3.674773 | E113: =SUM(E111:E112) -> 0.13884974 | F113: =SUM(F111:F112) -> 0.015271184 | H113: =SUM(H111:H112) -> 4.2628413 | I113: =SUM(I111:I112) -> 0.14346843 | J113: =SUM(J111:J112) -> 0.017052041
C116: Labour Cost | D116: Total Hourly Cost (€) | E116: Total Cost per MT (€/MT) | F116: Percentage of the Total Cost (%) | H116: Total Hourly Cost (€) | I116: Total Cost per MT (€/MT) | J116: Percentage of the Total Cost (%)
C117: Production Manager | D117: =IF('1.2 Scenario Analysis'!$H$13="Non-Carbonated",'4.6 Nitrogenation (2)'!F53,0) -> 2.2505195 | E117: =IF('1.2 Scenario Analysis'!$H$13="Non-Carbonated",'4.6 Nitrogenation (2)'!G53,0) -> 0.085034926 | F117: =D117/$D$235 -> 0.0093524404 | H117: =IF('1.2 Scenario Analysis'!$H$13="Non-Carbonated",'4.6 Nitrogenation (2)'!F60,0) -> 2.2505195 | I117: =IF('1.2 Scenario Analysis'!$H$13="Non-Carbonated",'4.6 Nitrogenation (2)'!G60,0) -> 0.075742554 | J117: =H117/$H$235 -> 0.0090024348
C118: Shift Supervisor | D118: =IF('1.2 Scenario Analysis'!$H$13="Non-Carbonated",'4.6 Nitrogenation (2)'!F54,0) -> 1.8653017 | E118: =IF('1.2 Scenario Analysis'!$H$13="Non-Carbonated",'4.6 Nitrogenation (2)'!G54,0) -> 0.070479636 | F118: =D118/$D$235 -> 0.0077515984 | H118: =IF('1.2 Scenario Analysis'!$H$13="Non-Carbonated",'4.6 Nitrogenation (2)'!F61,0) -> 1.8653017 | I118: =IF('1.2 Scenario Analysis'!$H$13="Non-Carbonated",'4.6 Nitrogenation (2)'!G61,0) -> 0.062777824 | J118: =H118/$H$235 -> 0.0074615027
C119: Machine Operator | D119: =IF('1.2 Scenario Analysis'!$H$13="Non-Carbonated",'4.6 Nitrogenation (2)'!F55,0) -> 1.1616204 | E119: =IF('1.2 Scenario Analysis'!$H$13="Non-Carbonated",'4.6 Nitrogenation (2)'!G55,0) -> 0.043891337 | F119: =D119/$D$235 -> 0.0048273237 | H119: =IF('1.2 Scenario Analysis'!$H$13="Non-Carbonated",'4.6 Nitrogenation (2)'!F62,0) -> 1.1616204 | I119: =IF('1.2 Scenario Analysis'!$H$13="Non-Carbonated",'4.6 Nitrogenation (2)'!G62,0) -> 0.039095018 | J119: =H119/$H$235 -> 0.004646666
C120: Production Worker | D120: =IF('1.2 Scenario Analysis'!$H$13="Non-Carbonated",'4.6 Nitrogenation (2)'!F56,0) -> 2.214619 | E120: =IF('1.2 Scenario Analysis'!$H$13="Non-Carbonated",'4.6 Nitrogenation (2)'!G56,0) -> 0.083678442 | F120: =D120/$D$235 -> 0.0092032496 | H120: =IF('1.2 Scenario Analysis'!$H$13="Non-Carbonated",'4.6 Nitrogenation (2)'!F63,0) -> 2.214619 | I120: =IF('1.2 Scenario Analysis'!$H$13="Non-Carbonated",'4.6 Nitrogenation (2)'!G63,0) -> 0.074534303 | J120: =H120/$H$235 -> 0.0088588273
C121: Total labor Cost | D121: =SUM(D117:D120) -> 7.4920606 | E121: =SUM(E117:E120) -> 0.28308434 | F121: =SUM(F117:F120) -> 0.031134612 | H121: =SUM(H117:H120) -> 7.4920606 | I121: =SUM(I117:I120) -> 0.2521497 | J121: =SUM(J117:J120) -> 0.029969431
C122: Total Nitrogenation Cost | D122: =D121+D113+D108 -> 11.42074 | E122: =E121+E113+E108 -> 0.43152783 | F122: =SUM(F121,F113,F108) -> 0.047460949 | H122: =H121+H113+H108 -> 12.038105 | I122: =I121+I113+I108 -> 0.40514949 | J122: =SUM(J121,J113,J108) -> 0.04815433
C124: Can Pasteurisation Process
B125: Can Pasteurisation Process | C125: Machinery | D125: Total Hourly Cost (€) | E125: Total Depreciation per MT (€/MT) | F125: Percentage of the Total Cost (%) | H125: Total Hourly Cost (€) | I125: Total Depreciation per MT (€/MT) | J125: Percentage of the Total Cost (%)
C126: Steam Heating Tunnel Pasteuriser | D126: =IF('1.2 Scenario Analysis'!$H$14="Can",'4.7 Can Pasteurisation (2)'!F33,0) -> 0 | E126: =IF('1.2 Scenario Analysis'!I14="Can",'4.7 Can Pasteurisation (2)'!G33,0) -> 0 | F126: =D126/$D$235 -> 0 | H126: =IF('1.2 Scenario Analysis'!$H$14="Can",'4.7 Can Pasteurisation (2)'!F37,0) -> 0 | I126: =IF('1.2 Scenario Analysis'!$H$14="Can",'4.7 Can Pasteurisation (2)'!G37,0) -> 0 | J126: =H126/H$235 -> 0
C127: Total Machinery Cost | D127: =SUM(D126:D126) -> 0 | E127: =SUM(E126:E126) -> 0 | F127: =SUM(F126:F126) -> 0 | H127: =SUM(H126:H126) -> 0 | I127: =SUM(I126:I126) -> 0 | J127: =SUM(J126:J126) -> 0
C129: Utility | D129: Total Hourly Cost (€) | E129: Total Cost per MT (€/MT) | F129: Percentage of the Total Cost (%) | H129: Total Hourly Cost (€) | I129: Total Cost per MT (€/MT) | J129: Percentage of the Total Cost (%)
C130: Electricity and Natural Gas Cost | D130: =IF('1.2 Scenario Analysis'!$H$14="Can",'4.7 Can Pasteurisation (2)'!F43,0) -> 0 | E130: =IF('1.2 Scenario Analysis'!$H$14="Can",'4.7 Can Pasteurisation (2)'!G43,0) -> 0 | F130: =D130/$D$235 -> 0 | H130: =IF('1.2 Scenario Analysis'!$H$14="Can",'4.7 Can Pasteurisation (2)'!F47,0) -> 0 | I130: =IF('1.2 Scenario Analysis'!$H$14="Can",'4.7 Can Pasteurisation (2)'!G47,0) -> 0 | J130: =H130/$H$235 -> 0
...

Sheet 2.2 Cost Model Packing (3)
C5: Summary – Packing Cost
D7: Semi-Automatic | H7: Automatic
C8: Dry Aseptic Cleaning Process
B9: Dry Aseptic Cleaning Process | C9: Machinery | D9: Total Hourly Cost (€) | E9: Total Depreciation per MT (€/MT) | F9: Percentage of the Total Cost (%) | H9: Total Hourly Cost (€) | I9: Total Depreciation per MT (€/MT) | J9: Percentage of the Total Cost (%)
C10: Preform Steriliser | D10: ='4.1 Dry Aseptic Cleaning (3)'!F34 -> 0.28320312 | E10: ='4.1 Dry Aseptic Cleaning (3)'!G34 -> 0.015052887 | F10: =D10/$D$235 -> 0.0011773081 | H10: ='4.1 Dry Aseptic Cleaning (3)'!F39 -> 0.34179688 | I10: ='4.1 Dry Aseptic Cleaning (3)'!G39 -> 0.014968499 | J10: =H10/H$235 -> 0.0013676961
C11: Air Jet and Vacuum Cleaning Machines | D11: ='4.1 Dry Aseptic Cleaning (3)'!F35 -> 0.19042969 | E11: ='4.1 Dry Aseptic Cleaning (3)'!G35 -> 0.010121769 | F11: =D11/$D$235 -> 0.00079163821 | H11: ='4.1 Dry Aseptic Cleaning (3)'!F40 -> 0.234375 | I11: ='4.1 Dry Aseptic Cleaning (3)'!G40 -> 0.010264114 | J11: =H11/H$235 -> 0.00093784874
C12: Total Machinery Cost | D12: =SUM(D10:D11) -> 0.47363281 | E12: =SUM(E10:E11) -> 0.025174656 | F12: =SUM(F10:F11) -> 0.0019689463 | H12: =SUM(H10:H11) -> 0.57617188 | I12: =SUM(I10:I11) -> 0.025232613 | J12: =SUM(J10:J11) -> 0.0023055448
C14: Utility | D14: Total Hourly Cost (€) | E14: Total Cost per MT (€/MT) | F14: Percentage of the Total Cost (%) | H14: Total Hourly Cost (€) | I14: Total Cost per MT (€/MT) | J14: Total Cost per MT (€/MT)
C15: Electricity and Natural Gas Cost | D15: ='4.1 Dry Aseptic Cleaning (3)'!F47 -> 4.5590914 | E15: ='4.1 Dry Aseptic Cleaning (3)'!G47 -> 0.24232603 | F15: =D15/$D$235 -> 0.018952669 | H15: ='4.1 Dry Aseptic Cleaning (3)'!F52 -> 5.2409096 | I15: ='4.1 Dry Aseptic Cleaning (3)'!G52 -> 0.22951805 | J15: =H15/$H$235 -> 0.020971437
C16: Other Utility Cost | D16: =15%*D15 -> 0.68386371 | E16: =15%*E15 -> 0.036348904 | F16: =D16/$D$235 -> 0.0028429004 | H16: =15%*H15 -> 0.78613645 | I16: =15%*I15 -> 0.034427708 | J16: =H16/$H$235 -> 0.0031457155
C17: Total Utility Cost | D17: =SUM(D15:D16) -> 5.2429551 | E17: =SUM(E15:E16) -> 0.27867493 | F17: =SUM(F15:F16) -> 0.02179557 | H17: =SUM(H15:H16) -> 6.0270461 | I17: =SUM(I15:I16) -> 0.26394576 | J17: =SUM(J15:J16) -> 0.024117152
C20: Labour Cost | D20: Total Hourly Cost (€) | E20: Total Cost per MT (€/MT) | F20: Percentage of the Total Cost (%) | H20: Total Hourly Cost (€) | I20: Total Cost per MT (€/MT) | J20: Percentage of the Total Cost (%)
C21: Production Manager | D21: ='4.1 Dry Aseptic Cleaning (3)'!F58 -> 2.2505195 | E21: ='4.1 Dry Aseptic Cleaning (3)'!G58 -> 0.1196202 | F21: =D21/$D$235 -> 0.0093556694 | H21: ='4.1 Dry Aseptic Cleaning (3)'!F65 -> 2.2505195 | I21: ='4.1 Dry Aseptic Cleaning (3)'!G65 -> 0.098558243 | J21: =H21/$H$235 -> 0.0090054266
C22: Shift Supervisor | D22: ='4.1 Dry Aseptic Cleaning (3)'!F59 -> 1.8653017 | E22: ='4.1 Dry Aseptic Cleaning (3)'!G59 -> 0.099145007 | F22: =D22/$D$235 -> 0.0077542746 | H22: ='4.1 Dry Aseptic Cleaning (3)'!F66 -> 1.8653017 | I22: ='4.1 Dry Aseptic Cleaning (3)'!G66 -> 0.081688189 | J22: =H22/$H$235 -> 0.0074639823
C23: Machine Operator | D23: ='4.1 Dry Aseptic Cleaning (3)'!F60 -> 1.1616204 | E23: ='4.1 Dry Aseptic Cleaning (3)'!G60 -> 0.061742756 | F23: =D23/$D$235 -> 0.0048289904 | H23: ='4.1 Dry Aseptic Cleaning (3)'!F67 -> 1.1616204 | I23: ='4.1 Dry Aseptic Cleaning (3)'!G67 -> 0.050871486 | J23: =H23/$H$235 -> 0.0046482102
C24: Production Worker | D24: ='4.1 Dry Aseptic Cleaning (3)'!F61 -> 2.214619 | E24: ='4.1 Dry Aseptic Cleaning (3)'!G61 -> 0.11771201 | F24: =D24/$D$235 -> 0.0092064271 | H24: ='4.1 Dry Aseptic Cleaning (3)'!F68 -> 2.214619 | I24: ='4.1 Dry Aseptic Cleaning (3)'!G68 -> 0.096986035 | J24: =H24/$H$235 -> 0.0088617713
C25: Total labor Cost | D25: =SUM(D21:D24) -> 7.4920606 | E25: =SUM(E21:E24) -> 0.39821998 | F25: =SUM(F21:F24) -> 0.031145361 | H25: =SUM(H21:H24) -> 7.4920606 | I25: =SUM(I21:I24) -> 0.32810395 | J25: =SUM(J21:J24) -> 0.02997939
C26: Total Dry Aseptic Cleaning Cost | D26: =D25+D17+D12 -> 13.208649 | E26: =E25+E17+E12 -> 0.70206956 | F26: =SUM(F25,F17,F12) -> 0.054909878 | H26: =H25+H17+H12 -> 14.095279 | I26: =I25+I17+I12 -> 0.61728233 | J26: =SUM(J25,J17,J12) -> 0.056402088
D28: Semi-Automatic | H28: Automatic
C29: PET Bottle Blowing Process
B30: PET Bottle Blowing Process | C30: Machinery | D30: Total Hourly Cost (€) | E30: Total Depreciation per MT (€/MT) | F30: Percentage of the Total Cost (%) | H30: Total Hourly Cost (€) | I30: Total Depreciation per MT (€/MT) | J30: Percentage of the Total Cost (%)
C31: PET Bottle Blowing Machine | D31: =IF('1.2 Scenario Analysis'!$M$14="Can",0,'4.2 PET Bottle Blowing (3)'!F35) -> 0.5078125 | E31: =IF('1.2 Scenario Analysis'!$M$14="Can",0,'4.2 PET Bottle Blowing (3)'!G35) -> 0.037503019 | F31: =D31/$D$235 -> 0.0021110352 | H31: =IF('1.2 Scenario Analysis'!$M$14="Can",0,'4.2 PET Bottle Blowing (3)'!F38) -> 0.53710938 | I31: =IF('1.2 Scenario Analysis'!$M$14="Can",0,'4.2 PET Bottle Blowing (3)'!G38) -> 0.031666304 | J31: =H31/H$235 -> 0.0021492367
C32: Total Machinery Cost | D32: =SUM(D31:D31) -> 0.5078125 | E32: =SUM(E31:E31) -> 0.037503019 | F32: =SUM(F31:F31) -> 0.0021110352 | H32: =SUM(H31:H31) -> 0.53710938 | I32: =SUM(I31:I31) -> 0.031666304 | J32: =SUM(J31:J31) -> 0.0021492367
C34: Utility | D34: Total Hourly Cost (€) | E34: Total Cost per MT (€/MT) | F34: Percentage of the Total Cost (%) | H34: Total Hourly Cost (€) | I34: Total Cost per MT (€/MT) | J34: Total Cost per MT (€/MT)
C35: Electricity and Natural Gas Cost | D35: =IF('1.2 Scenario Analysis'!$M$14="Can",0,'4.2 PET Bottle Blowing (3)'!F45) -> 13.08182 | E35: =IF('1.2 Scenario Analysis'!$M$14="Can",0,'4.2 PET Bottle Blowing (3)'!G45) -> 0.96611986 | F35: =D35/$D$235 -> 0.054382636 | H35: =IF('1.2 Scenario Analysis'!$M$14="Can",0,'4.2 PET Bottle Blowing (3)'!F49) -> 13.593184 | I35: =IF('1.2 Scenario Analysis'!$M$14="Can",0,'4.2 PET Bottle Blowing (3)'!G49) -> 0.80141198 | J35: =H35/$H$235 -> 0.05439296
C36: Other Utility Cost | D36: =15%*D35 -> 1.962273 | E36: =15%*E35 -> 0.14491798 | F36: =D36/$D$235 -> 0.0081573954 | H36: =15%*H35 -> 2.0389775 | I36: =15%*I35 -> 0.1202118 | J36: =H36/$H$235 -> 0.008158944
C37: Total Utility Cost | D37: =SUM(D35:D36) -> 15.044093 | E37: =SUM(E35:E36) -> 1.1110378 | F37: =SUM(F35:F36) -> 0.062540032 | H37: =SUM(H35:H36) -> 15.632161 | I37: =SUM(I35:I36) -> 0.92162378 | J37: =SUM(J35:J36) -> 0.062551904
C40: Labour Cost | D40: Total Hourly Cost (€) | E40: Total Cost per MT (€/MT) | F40: Percentage of the Total Cost (%) | H40: Total Hourly Cost (€) | I40: Total Cost per MT (€/MT) | J40: Percentage of the Total Cost (%)
C41: Production Manager | D41: =IF('1.2 Scenario Analysis'!$M$14="Can",0,'4.2 PET Bottle Blowing (3)'!F54) -> 2.2505195 | E41: =IF('1.2 Scenario Analysis'!$M$14="Can",0,'4.2 PET Bottle Blowing (3)'!G54) -> 0.16620559 | F41: =D41/$D$235 -> 0.0093556694 | H41: =IF('1.2 Scenario Analysis'!$M$14="Can",0,'4.2 PET Bottle Blowing (3)'!F61) -> 2.2505195 | I41: =IF('1.2 Scenario Analysis'!$M$14="Can",0,'4.2 PET Bottle Blowing (3)'!G61) -> 0.13268365 | J41: =H41/$H$235 -> 0.0090054266
C42: Shift Supervisor | D42: =IF('1.2 Scenario Analysis'!$M$14="Can",0,'4.2 PET Bottle Blowing (3)'!F55) -> 1.8653017 | E42: =IF('1.2 Scenario Analysis'!$M$14="Can",0,'4.2 PET Bottle Blowing (3)'!G55) -> 0.13775645 | F42: =D42/$D$235 -> 0.0077542746 | H42: =IF('1.2 Scenario Analysis'!$M$14="Can",0,'4.2 PET Bottle Blowing (3)'!F62) -> 1.8653017 | I42: =IF('1.2 Scenario Analysis'!$M$14="Can",0,'4.2 PET Bottle Blowing (3)'!G62) -> 0.10997241 | J42: =H42/$H$235 -> 0.0074639823
C43: Machine Operator | D43: =IF('1.2 Scenario Analysis'!$M$14="Can",0,'4.2 PET Bottle Blowing (3)'!F56) -> 1.1616204 | E43: =IF('1.2 Scenario Analysis'!$M$14="Can",0,'4.2 PET Bottle Blowing (3)'!G56) -> 0.085788108 | F43: =D43/$D$235 -> 0.0048289904 | H43: =IF('1.2 Scenario Analysis'!$M$14="Can",0,'4.2 PET Bottle Blowing (3)'!F63) -> 1.1616204 | I43: =IF('1.2 Scenario Analysis'!$M$14="Can",0,'4.2 PET Bottle Blowing (3)'!G63) -> 0.068485542 | J43: =H43/$H$235 -> 0.0046482102
C44: Production Worker | D44: =IF('1.2 Scenario Analysis'!$M$14="Can",0,'4.2 PET Bottle Blowing (3)'!F57) -> 2.214619 | E44: =IF('1.2 Scenario Analysis'!$M$14="Can",0,'4.2 PET Bottle Blowing (3)'!G57) -> 0.16355426 | F44: =D44/$D$235 -> 0.0092064271 | H44: =IF('1.2 Scenario Analysis'!$M$14="Can",0,'4.2 PET Bottle Blowing (3)'!F64) -> 2.214619 | I44: =IF('1.2 Scenario Analysis'!$M$14="Can",0,'4.2 PET Bottle Blowing (3)'!G64) -> 0.13056707 | J44: =H44/$H$235 -> 0.0088617713
C45: Total labor Cost | D45: =SUM(D41:D44) -> 7.4920606 | E45: =SUM(E41:E44) -> 0.5533044 | F45: =SUM(F41:F44) -> 0.031145361 | H45: =SUM(H41:H44) -> 7.4920606 | I45: =SUM(I41:I44) -> 0.44170868 | J45: =SUM(J41:J44) -> 0.02997939
C46: Total PET Bottle Blowing Cost | D46: =D45+D37+D32 -> 23.043966 | E46: =E45+E37+E32 -> 1.7018453 | F46: =SUM(F45,F37,F32) -> 0.095796428 | H46: =H45+H37+H32 -> 23.661331 | I46: =I45+I37+I32 -> 1.3949988 | J46: =SUM(J45,J37,J32) -> 0.094680532
C48: Wet Aseptic Cleaning Process
B49: Wet Aseptic Cleaning Process | C49: Machinery | D49: Total Hourly Cost (€) | E49: Total Depreciation per MT (€/MT) | F49: Percentage of the Total Cost (%) | H49: Total Hourly Cost (€) | I49: Total Depreciation per MT (€/MT) | J49: Percentage of the Total Cost (%)
C50: PET Bottle Washing and Rinsing Machine | D50: =IF('1.2 Scenario Analysis'!$M$18="Wet Aseptic",'4.3 Wet Aseptic Cleaning (3)'!F34,0) -> 0 | E50: =IF('1.2 Scenario Analysis'!$M$18="Wet Aseptic",'4.3 Wet Aseptic Cleaning (3)'!G34,0) -> 0 | F50: =D50/$D$235 -> 0 | H50: =IF('1.2 Scenario Analysis'!$M$18="Wet Aseptic",'4.3 Wet Aseptic Cleaning (3)'!F37,0) -> 0 | I50: =IF('1.2 Scenario Analysis'!$M$18="Wet Aseptic",'4.3 Wet Aseptic Cleaning (3)'!G37,0) -> 0 | J50: =H50/H$235 -> 0
C51: Total Machinery Cost | D51: =SUM(D50:D50) -> 0 | E51: =SUM(E50:E50) -> 0 | F51: =SUM(F50:F50) -> 0 | H51: =SUM(H50:H50) -> 0 | I51: =SUM(I50:I50) -> 0 | J51: =SUM(J50:J50) -> 0
C53: Utility | D53: Total Hourly Cost (€) | E53: Total Cost per MT (€/MT) | F53: Percentage of the Total Cost (%) | H53: Total Hourly Cost (€) | I53: Total Cost per MT (€/MT) | J53: Percentage of the Total Cost (%)
C54: Electricity and Natural Gas Cost | D54: =IF('1.2 Scenario Analysis'!$M$18="Wet Aseptic",'4.3 Wet Aseptic Cleaning (3)'!F43,0) -> 0 | E54: =IF('1.2 Scenario Analysis'!$M$18="Wet Aseptic",'4.3 Wet Aseptic Cleaning (3)'!G43,0) -> 0 | F54: =D54/$D$235 -> 0 | H54: =IF('1.2 Scenario Analysis'!$M$18="Wet Aseptic",'4.3 Wet Aseptic Cleaning (3)'!F47,0) -> 0 | I54: =IF('1.2 Scenario Analysis'!$M$18="Wet Aseptic",'4.3 Wet Aseptic Cleaning (3)'!G47,0) -> 0 | J54: =H54/$H$235 -> 0
C55: Other Utility Cost | D55: =15%*D54 -> 0 | E55: =15%*E54 -> 0 | F55: =D55/$D$235 -> 0 | H55: =15%*H54 -> 0 | I55: =15%*I54 -> 0 | J55: =H55/$H$235 -> 0
C56: Total Utility Cost | D56: =SUM(D54:D55) -> 0 | E56: =SUM(E54:E55) -> 0 | F56: =SUM(F54:F55) -> 0 | H56: =SUM(H54:H55) -> 0 | I56: =SUM(I54:I55) -> 0 | J56: =SUM(J54:J55) -> 0
C59: Labour Cost | D59: Total Hourly Cost (€) | E59: Total Cost per MT (€/MT) | F59: Percentage of the Total Cost (%) | H59: Total Hourly Cost (€) | I59: Total Cost per MT (€/MT) | J59: Percentage of the Total Cost (%)
C60: Production Manager | D60: =IF('1.2 Scenario Analysis'!$M$18="Wet Aseptic",'4.3 Wet Aseptic Cleaning (3)'!F53,0) -> 0 | E60: =IF('1.2 Scenario Analysis'!$M$18="Wet Aseptic",'4.3 Wet Aseptic Cleaning (3)'!G53,0) -> 0 | F60: =D60/$D$235 -> 0 | H60: =IF('1.2 Scenario Analysis'!$M$18="Wet Aseptic",'4.3 Wet Aseptic Cleaning (3)'!F60,0) -> 0 | I60: =IF('1.2 Scenario Analysis'!$M$18="Wet Aseptic",'4.3 Wet Aseptic Cleaning (3)'!G60,0) -> 0 | J60: =H60/$H$235 -> 0
C61: Shift Supervisor | D61: =IF('1.2 Scenario Analysis'!$M$18="Wet Aseptic",'4.3 Wet Aseptic Cleaning (3)'!F54,0) -> 0 | E61: =IF('1.2 Scenario Analysis'!$M$18="Wet Aseptic",'4.3 Wet Aseptic Cleaning (3)'!G54,0) -> 0 | F61: =D61/$D$235 -> 0 | H61: =IF('1.2 Scenario Analysis'!$M$18="Wet Aseptic",'4.3 Wet Aseptic Cleaning (3)'!F61,0) -> 0 | I61: =IF('1.2 Scenario Analysis'!$M$18="Wet Aseptic",'4.3 Wet Aseptic Cleaning (3)'!G61,0) -> 0 | J61: =H61/$H$235 -> 0
C62: Machine Operator | D62: =IF('1.2 Scenario Analysis'!$M$18="Wet Aseptic",'4.3 Wet Aseptic Cleaning (3)'!F55,0) -> 0 | E62: =IF('1.2 Scenario Analysis'!$M$18="Wet Aseptic",'4.3 Wet Aseptic Cleaning (3)'!G55,0) -> 0 | F62: =D62/$D$235 -> 0 | H62: =IF('1.2 Scenario Analysis'!$M$18="Wet Aseptic",'4.3 Wet Aseptic Cleaning (3)'!F62,0) -> 0 | I62: =IF('1.2 Scenario Analysis'!$M$18="Wet Aseptic",'4.3 Wet Aseptic Cleaning (3)'!G62,0) -> 0 | J62: =H62/$H$235 -> 0
C63: Production Worker | D63: =IF('1.2 Scenario Analysis'!$M$18="Wet Aseptic",'4.3 Wet Aseptic Cleaning (3)'!F56,0) -> 0 | E63: =IF('1.2 Scenario Analysis'!$M$18="Wet Aseptic",'4.3 Wet Aseptic Cleaning (3)'!G56,0) -> 0 | F63: =D63/$D$235 -> 0 | H63: =IF('1.2 Scenario Analysis'!$M$18="Wet Aseptic",'4.3 Wet Aseptic Cleaning (3)'!F63,0) -> 0 | I63: =IF('1.2 Scenario Analysis'!$M$18="Wet Aseptic",'4.3 Wet Aseptic Cleaning (3)'!G63,0) -> 0 | J63: =H63/$H$235 -> 0
C64: Total labor Cost | D64: =SUM(D60:D63) -> 0 | E64: =SUM(E60:E63) -> 0 | F64: =SUM(F60:F63) -> 0 | H64: =SUM(H60:H63) -> 0 | I64: =SUM(I60:I63) -> 0 | J64: =SUM(J60:J63) -> 0
C65: Total Wet Aseptic Cleaning Cost | D65: =D64+D56+D51 -> 0 | E65: =E64+E56+E51 -> 0 | F65: =SUM(F64,F56,F51) -> 0 | H65: =H64+H56+H51 -> 0 | I65: =I64+I56+I51 -> 0 | J65: =SUM(J64,J56,J51) -> 0
C67: Can Filling & Closing Process
B68: Can Filling & Closing Process | C68: Machinery | D68: Total Hourly Cost (€) | E68: Total Depreciation per MT (€/MT) | F68: Percentage of the Total Cost (%) | H68: Total Hourly Cost (€) | I68: Total Depreciation per MT (€/MT) | J68: Percentage of the Total Cost (%)
C69: Can Filling and Sealing Machine | D69: =IF('1.2 Scenario Analysis'!$M$14="Can",'4.4 Can Filling & Closing (3)'!F34,0) -> 0 | E69: =IF('1.2 Scenario Analysis'!$M$14="Can",'4.4 Can Filling & Closing (3)'!G34,0) -> 0 | F69: =D69/$D$235 -> 0 | H69: =IF('1.2 Scenario Analysis'!$M$14="Can",'4.4 Can Filling & Closing (3)'!F38,0) -> 0 | I69: =IF('1.2 Scenario Analysis'!$M$14="Can",'4.4 Can Filling & Closing (3)'!G38,0) -> 0 | J69: =H69/H$235 -> 0
C70: Total Machinery Cost | D70: =SUM(D69:D69) -> 0 | E70: =SUM(E69:E69) -> 0 | F70: =SUM(F69:F69) -> 0 | H70: =SUM(H69:H69) -> 0 | I70: =SUM(I69:I69) -> 0 | J70: =SUM(J69:J69) -> 0
C72: Utility | D72: Total Hourly Cost (€) | E72: Total Cost per MT (€/MT) | F72: Percentage of the Total Cost (%) | H72: Total Hourly Cost (€) | I72: Total Cost per MT (€/MT) | J72: Percentage of the Total Cost (%)
C73: Electricity and Natural Gas Cost | D73: =IF('1.2 Scenario Analysis'!$M$14="Can",'4.4 Can Filling & Closing (3)'!F44,0) -> 0 | E73: =IF('1.2 Scenario Analysis'!$M$14="Can",'4.4 Can Filling & Closing (3)'!G44,0) -> 0 | F73: =D73/$D$235 -> 0 | H73: =IF('1.2 Scenario Analysis'!$M$14="Can",'4.4 Can Filling & Closing (3)'!F48,0) -> 0 | I73: =IF('1.2 Scenario Analysis'!$M$14="Can",'4.4 Can Filling & Closing (3)'!G48,0) -> 0 | J73: =H73/$H$235 -> 0
C74: Other Utility Cost | D74: =15%*D73 -> 0 | E74: =15%*E73 -> 0 | F74: =D74/$D$235 -> 0 | H74: =15%*H73 -> 0 | I74: =15%*I73 -> 0 | J74: =H74/$H$235 -> 0
C75: Total Utility Cost | D75: =SUM(D73:D74) -> 0 | E75: =SUM(E73:E74) -> 0 | F75: =SUM(F73:F74) -> 0 | H75: =SUM(H73:H74) -> 0 | I75: =SUM(I73:I74) -> 0 | J75: =SUM(J73:J74) -> 0
C78: Labour Cost | D78: Total Hourly Cost (€) | E78: Total Cost per MT (€/MT) | F78: Percentage of the Total Cost (%) | H78: Total Hourly Cost (€) | I78: Total Cost per MT (€/MT) | J78: Percentage of the Total Cost (%)
C79: Production Manager | D79: =IF('1.2 Scenario Analysis'!$M$14="Can",'4.4 Can Filling & Closing (3)'!F54,0) -> 0 | E79: =IF('1.2 Scenario Analysis'!$M$14="Can",'4.4 Can Filling & Closing (3)'!G54,0) -> 0 | F79: =D79/$D$235 -> 0 | H79: =IF('1.2 Scenario Analysis'!$M$14="Can",'4.4 Can Filling & Closing (3)'!F61,0) -> 0 | I79: =IF('1.2 Scenario Analysis'!$M$14="Can",'4.4 Can Filling & Closing (3)'!G61,0) -> 0 | J79: =H79/$H$235 -> 0
C80: Shift Supervisor | D80: =IF('1.2 Scenario Analysis'!$M$14="Can",'4.4 Can Filling & Closing (3)'!F55,0) -> 0 | E80: =IF('1.2 Scenario Analysis'!$M$14="Can",'4.4 Can Filling & Closing (3)'!G55,0) -> 0 | F80: =D80/$D$235 -> 0 | H80: =IF('1.2 Scenario Analysis'!$M$14="Can",'4.4 Can Filling & Closing (3)'!F62,0) -> 0 | I80: =IF('1.2 Scenario Analysis'!$M$14="Can",'4.4 Can Filling & Closing (3)'!G62,0) -> 0 | J80: =H80/$H$235 -> 0
C81: Machine Operator | D81: =IF('1.2 Scenario Analysis'!$M$14="Can",'4.4 Can Filling & Closing (3)'!F56,0) -> 0 | E81: =IF('1.2 Scenario Analysis'!$M$14="Can",'4.4 Can Filling & Closing (3)'!G56,0) -> 0 | F81: =D81/$D$235 -> 0 | H81: =IF('1.2 Scenario Analysis'!$M$14="Can",'4.4 Can Filling & Closing (3)'!F63,0) -> 0 | I81: =IF('1.2 Scenario Analysis'!$M$14="Can",'4.4 Can Filling & Closing (3)'!G63,0) -> 0 | J81: =H81/$H$235 -> 0
C82: Production Worker | D82: =IF('1.2 Scenario Analysis'!$M$14="Can",'4.4 Can Filling & Closing (3)'!F57,0) -> 0 | E82: =IF('1.2 Scenario Analysis'!$M$14="Can",'4.4 Can Filling & Closing (3)'!G57,0) -> 0 | F82: =D82/$D$235 -> 0 | H82: =IF('1.2 Scenario Analysis'!$M$14="Can",'4.4 Can Filling & Closing (3)'!F64,0) -> 0 | I82: =IF('1.2 Scenario Analysis'!$M$14="Can",'4.4 Can Filling & Closing (3)'!G64,0) -> 0 | J82: =H82/$H$235 -> 0
C83: Total labor Cost | D83: =SUM(D79:D82) -> 0 | E83: =SUM(E79:E82) -> 0 | F83: =SUM(F79:F82) -> 0 | H83: =SUM(H79:H82) -> 0 | I83: =SUM(I79:I82) -> 0 | J83: =SUM(J79:J82) -> 0
C84: Total Aseptic Filling, Closing Packing Cost | D84: =D83+D75+D70 -> 0 | E84: =E83+E75+E70 -> 0 | F84: =SUM(F83,F75,F70) -> 0 | H84: =H83+H75+H70 -> 0 | I84: =I83+I75+I70 -> 0 | J84: =SUM(J83,J75,J70) -> 0
C86: Aseptic Filling, Closing Process
B87: Aseptic Filling, Closing Process | C87: Machinery | D87: Total Hourly Cost (€) | E87: Total Depreciation per MT (€/MT) | F87: Percentage of the Total Cost (%) | H87: Total Hourly Cost (€) | I87: Total Depreciation per MT (€/MT) | J87: Percentage of the Total Cost (%)
C88: Aseptic Liquid Filling and Capping Machine | D88: =IF('1.2 Scenario Analysis'!$M$14="Can",0,'4.5 Aseptic Filling & Closi (3)'!F33) -> 0.546875 | E88: =IF('1.2 Scenario Analysis'!$M$14="Can",0,'4.5 Aseptic Filling & Closi (3)'!G33) -> 0.021062822 | F88: =D88/$D$235 -> 0.0022734225 | H88: =IF('1.2 Scenario Analysis'!$M$14="Can",0,'4.5 Aseptic Filling & Closi (3)'!F38) -> 0.63476562 | I88: =IF('1.2 Scenario Analysis'!$M$14="Can",0,'4.5 Aseptic Filling & Closi (3)'!G38) -> 0.021773489 | J88: =H88/H$235 -> 0.002540007
C89: Total Machinery Cost | D89: =SUM(D88:D88) -> 0.546875 | E89: =SUM(E88:E88) -> 0.021062822 | F89: =SUM(F88:F88) -> 0.0022734225 | H89: =SUM(H88:H88) -> 0.63476562 | I89: =SUM(I88:I88) -> 0.021773489 | J89: =SUM(J88:J88) -> 0.002540007
C91: Utility | D91: Total Hourly Cost (€) | E91: Total Cost per MT (€/MT) | F91: Percentage of the Total Cost (%) | H91: Total Hourly Cost (€) | I91: Total Cost per MT (€/MT) | J91: Percentage of the Total Cost (%)
C92: Electricity and Natural Gas Cost | D92: =IF('1.2 Scenario Analysis'!$M$14="Can",0,'4.5 Aseptic Filling & Closi (3)'!F44) -> 3.1954548 | E92: =IF('1.2 Scenario Analysis'!$M$14="Can",0,'4.5 Aseptic Filling & Closi (3)'!G44) -> 0.12307254 | F92: =D92/$D$235 -> 0.013283875 | H92: =IF('1.2 Scenario Analysis'!$M$14="Can",0,'4.5 Aseptic Filling & Closi (3)'!F48) -> 3.7068185 | I92: =IF('1.2 Scenario Analysis'!$M$14="Can",0,'4.5 Aseptic Filling & Closi (3)'!G48) -> 0.12714988 | J92: =H92/$H$235 -> 0.01483279
C93: Other Utility Cost | D93: =15%*D92 -> 0.47931822 | E93: =15%*E92 -> 0.018460881 | F93: =D93/$D$235 -> 0.0019925812 | H93: =15%*H92 -> 0.55602278 | I93: =15%*I92 -> 0.019072482 | J93: =H93/$H$235 -> 0.0022249185
C94: Total Utility Cost | D94: =SUM(D92:D93) -> 3.674773 | E94: =SUM(E92:E93) -> 0.14153342 | F94: =SUM(F92:F93) -> 0.015276456 | H94: =SUM(H92:H93) -> 4.2628413 | I94: =SUM(I92:I93) -> 0.14622236 | J94: =SUM(J92:J93) -> 0.017057708
C97: Labour Cost | D97: Total Hourly Cost (€) | E97: Total Cost per MT (€/MT) | F97: Percentage of the Total Cost (%) | H97: Total Hourly Cost (€) | I97: Total Cost per MT (€/MT) | J97: Percentage of the Total Cost (%)
C98: Production Manager | D98: =IF('1.2 Scenario Analysis'!$M$14="Can",0,'4.5 Aseptic Filling & Closi (3)'!F53) -> 2.2505195 | E98: =IF('1.2 Scenario Analysis'!$M$14="Can",0,'4.5 Aseptic Filling & Closi (3)'!G53) -> 0.086678474 | F98: =D98/$D$235 -> 0.0093556694 | H98: =IF('1.2 Scenario Analysis'!$M$14="Can",0,'4.5 Aseptic Filling & Closi (3)'!F60) -> 2.2505195 | I98: =IF('1.2 Scenario Analysis'!$M$14="Can",0,'4.5 Aseptic Filling & Closi (3)'!G60) -> 0.077196462 | J98: =H98/$H$235 -> 0.0090054266
C99: Shift Supervisor | D99: =IF('1.2 Scenario Analysis'!$M$14="Can",0,'4.5 Aseptic Filling & Closi (3)'!F54) -> 1.8653017 | E99: =IF('1.2 Scenario Analysis'!$M$14="Can",0,'4.5 Aseptic Filling & Closi (3)'!G54) -> 0.071841861 | F99: =D99/$D$235 -> 0.0077542746 | H99: =IF('1.2 Scenario Analysis'!$M$14="Can",0,'4.5 Aseptic Filling & Closi (3)'!F61) -> 1.8653017 | I99: =IF('1.2 Scenario Analysis'!$M$14="Can",0,'4.5 Aseptic Filling & Closi (3)'!G61) -> 0.063982869 | J99: =H99/$H$235 -> 0.0074639823
C100: Machine Operator | D100: =IF('1.2 Scenario Analysis'!$M$14="Can",0,'4.5 Aseptic Filling & Closi (3)'!F55) -> 1.1616204 | E100: =IF('1.2 Scenario Analysis'!$M$14="Can",0,'4.5 Aseptic Filling & Closi (3)'!G55) -> 0.044739665 | F100: =D100/$D$235 -> 0.0048289904 | H100: =IF('1.2 Scenario Analysis'!$M$14="Can",0,'4.5 Aseptic Filling & Closi (3)'!F62) -> 1.1616204 | I100: =IF('1.2 Scenario Analysis'!$M$14="Can",0,'4.5 Aseptic Filling & Closi (3)'!G62) -> 0.039845462 | J100: =H100/$H$235 -> 0.0046482102
C101: Production Worker | D101: =IF('1.2 Scenario Analysis'!$M$14="Can",0,'4.5 Aseptic Filling & Closi (3)'!F56) -> 2.214619 | E101: =IF('1.2 Scenario Analysis'!$M$14="Can",0,'4.5 Aseptic Filling & Closi (3)'!G56) -> 0.085295773 | F101: =D101/$D$235 -> 0.0092064271 | H101: =IF('1.2 Scenario Analysis'!$M$14="Can",0,'4.5 Aseptic Filling & Closi (3)'!F63) -> 2.214619 | I101: =IF('1.2 Scenario Analysis'!$M$14="Can",0,'4.5 Aseptic Filling & Closi (3)'!G63) -> 0.075965019 | J101: =H101/$H$235 -> 0.0088617713
C102: Total labor Cost | D102: =SUM(D98:D101) -> 7.4920606 | E102: =SUM(E98:E101) -> 0.28855577 | F102: =SUM(F98:F101) -> 0.031145361 | H102: =SUM(H98:H101) -> 7.4920606 | I102: =SUM(I98:I101) -> 0.25698981 | J102: =SUM(J98:J101) -> 0.02997939
C103: Total Aseptic Filling, Closing Packing Cost | D103: =D102+D94+D89 -> 11.713709 | E103: =E102+E94+E89 -> 0.45115202 | F103: =SUM(F102,F94,F89) -> 0.04869524 | H103: =H102+H94+H89 -> 12.389668 | I103: =I102+I94+I89 -> 0.42498566 | J103: =SUM(J102,J94,J89) -> 0.049577106
C105: Nitrogenation Process
B106: Nitrogenation Process | C106: Machinery | D106: Total Hourly Cost (€) | E106: Total Depreciation per MT (€/MT) | F106: Percentage of the Total Cost (%) | H106: Total Hourly Cost (€) | I106: Total Depreciation per MT (€/MT) | J106: Percentage of the Total Cost (%)
C107: Nitrogen Injection System | D107: =IF('1.2 Scenario Analysis'!$M$13="Non-Carbonated",'4.6 Nitrogenation (3)'!F33,0) -> 0.25390625 | E107: =IF('1.2 Scenario Analysis'!$M$13="Non-Carbonated",'4.6 Nitrogenation (3)'!G33,0) -> 0.0095937402 | F107: =D107/$D$235 -> 0.0010555176 | H107: =IF('1.2 Scenario Analysis'!$M$13="Non-Carbonated",'4.6 Nitrogenation (3)'!F37,0) -> 0.28320312 | I107: =IF('1.2 Scenario Analysis'!$M$13="Non-Carbonated",'4.6 Nitrogenation (3)'!G37,0) -> 0.0095313675 | J107: =H107/H$235 -> 0.0011332339
C108: Total Machinery Cost | D108: =SUM(D107:D107) -> 0.25390625 | E108: =SUM(E107:E107) -> 0.0095937402 | F108: =SUM(F107:F107) -> 0.0010555176 | H108: =SUM(H107:H107) -> 0.28320312 | I108: =SUM(I107:I107) -> 0.0095313675 | J108: =SUM(J107:J107) -> 0.0011332339
C110: Utility | D110: Total Hourly Cost (€) | E110: Total Cost per MT (€/MT) | F110: Percentage of the Total Cost (%) | H110: Total Hourly Cost (€) | I110: Total Cost per MT (€/MT) | J110: Percentage of the Total Cost (%)
C111: Electricity and Natural Gas Cost | D111: =IF('1.2 Scenario Analysis'!$M$13="Non-Carbonated",'4.6 Nitrogenation (3)'!F43,0) -> 3.1954548 | E111: =IF('1.2 Scenario Analysis'!$M$13="Non-Carbonated",'4.6 Nitrogenation (3)'!G43,0) -> 0.12073891 | F111: =D111/$D$235 -> 0.013283875 | H111: =IF('1.2 Scenario Analysis'!$M$13="Non-Carbonated",'4.6 Nitrogenation (3)'!F47,0) -> 3.7068185 | I111: =IF('1.2 Scenario Analysis'!$M$13="Non-Carbonated",'4.6 Nitrogenation (3)'!G47,0) -> 0.12475515 | J111: =H111/$H$235 -> 0.01483279
C112: Other Utility Cost | D112: =15%*D111 -> 0.47931822 | E112: =15%*E111 -> 0.018110836 | F112: =D112/$D$235 -> 0.0019925812 | H112: =15%*H111 -> 0.55602278 | I112: =15%*I111 -> 0.018713273 | J112: =H112/$H$235 -> 0.0022249185
C113: Total Utility Cost | D113: =SUM(D111:D112) -> 3.674773 | E113: =SUM(E111:E112) -> 0.13884974 | F113: =SUM(F111:F112) -> 0.015276456 | H113: =SUM(H111:H112) -> 4.2628413 | I113: =SUM(I111:I112) -> 0.14346843 | J113: =SUM(J111:J112) -> 0.017057708
C116: Labour Cost | D116: Total Hourly Cost (€) | E116: Total Cost per MT (€/MT) | F116: Percentage of the Total Cost (%) | H116: Total Hourly Cost (€) | I116: Total Cost per MT (€/MT) | J116: Percentage of the Total Cost (%)
C117: Production Manager | D117: =IF('1.2 Scenario Analysis'!$M$13="Non-Carbonated",'4.6 Nitrogenation (3)'!F53,0) -> 2.2505195 | E117: =IF('1.2 Scenario Analysis'!$M$13="Non-Carbonated",'4.6 Nitrogenation (3)'!G53,0) -> 0.085034926 | F117: =D117/$D$235 -> 0.0093556694 | H117: =IF('1.2 Scenario Analysis'!$M$13="Non-Carbonated",'4.6 Nitrogenation (3)'!F60,0) -> 2.2505195 | I117: =IF('1.2 Scenario Analysis'!$M$13="Non-Carbonated",'4.6 Nitrogenation (3)'!G60,0) -> 0.075742554 | J117: =H117/$H$235 -> 0.0090054266
C118: Shift Supervisor | D118: =IF('1.2 Scenario Analysis'!$M$13="Non-Carbonated",'4.6 Nitrogenation (3)'!F54,0) -> 1.8653017 | E118: =IF('1.2 Scenario Analysis'!$M$13="Non-Carbonated",'4.6 Nitrogenation (3)'!G54,0) -> 0.070479636 | F118: =D118/$D$235 -> 0.0077542746 | H118: =IF('1.2 Scenario Analysis'!$M$13="Non-Carbonated",'4.6 Nitrogenation (3)'!F61,0) -> 1.8653017 | I118: =IF('1.2 Scenario Analysis'!$M$13="Non-Carbonated",'4.6 Nitrogenation (3)'!G61,0) -> 0.062777824 | J118: =H118/$H$235 -> 0.0074639823
C119: Machine Operator | D119: =IF('1.2 Scenario Analysis'!$M$13="Non-Carbonated",'4.6 Nitrogenation (3)'!F55,0) -> 1.1616204 | E119: =IF('1.2 Scenario Analysis'!$M$13="Non-Carbonated",'4.6 Nitrogenation (3)'!G55,0) -> 0.043891337 | F119: =D119/$D$235 -> 0.0048289904 | H119: =IF('1.2 Scenario Analysis'!$M$13="Non-Carbonated",'4.6 Nitrogenation (3)'!F62,0) -> 1.1616204 | I119: =IF('1.2 Scenario Analysis'!$M$13="Non-Carbonated",'4.6 Nitrogenation (3)'!G62,0) -> 0.039095018 | J119: =H119/$H$235 -> 0.0046482102
C120: Production Worker | D120: =IF('1.2 Scenario Analysis'!$M$13="Non-Carbonated",'4.6 Nitrogenation (3)'!F56,0) -> 2.214619 | E120: =IF('1.2 Scenario Analysis'!$M$13="Non-Carbonated",'4.6 Nitrogenation (3)'!G56,0) -> 0.083678442 | F120: =D120/$D$235 -> 0.0092064271 | H120: =IF('1.2 Scenario Analysis'!$M$13="Non-Carbonated",'4.6 Nitrogenation (3)'!F63,0) -> 2.214619 | I120: =IF('1.2 Scenario Analysis'!$M$13="Non-Carbonated",'4.6 Nitrogenation (3)'!G63,0) -> 0.074534303 | J120: =H120/$H$235 -> 0.0088617713
C121: Total labor Cost | D121: =SUM(D117:D120) -> 7.4920606 | E121: =SUM(E117:E120) -> 0.28308434 | F121: =SUM(F117:F120) -> 0.031145361 | H121: =SUM(H117:H120) -> 7.4920606 | I121: =SUM(I117:I120) -> 0.2521497 | J121: =SUM(J117:J120) -> 0.02997939
C122: Total Nitrogenation Cost | D122: =D121+D113+D108 -> 11.42074 | E122: =E121+E113+E108 -> 0.43152783 | F122: =SUM(F121,F113,F108) -> 0.047477335 | H122: =H121+H113+H108 -> 12.038105 | I122: =I121+I113+I108 -> 0.40514949 | J122: =SUM(J121,J113,J108) -> 0.048170333
C124: Can Pasteurisation Process
B125: Can Pasteurisation Process | C125: Machinery | D125: Total Hourly Cost (€) | E125: Total Depreciation per MT (€/MT) | F125: Percentage of the Total Cost (%) | H125: Total Hourly Cost (€) | I125: Total Depreciation per MT (€/MT) | J125: Percentage of the Total Cost (%)
C126: Steam Heating Tunnel Pasteuriser | D126: =IF('1.2 Scenario Analysis'!$M$14="Can",'4.7 Can Pasteurisation (3)'!F33,0) -> 0 | E126: =IF('1.2 Scenario Analysis'!$M$14="Can",'4.7 Can Pasteurisation (3)'!G33,0) -> 0 | F126: =D126/$D$235 -> 0 | H126: =IF('1.2 Scenario Analysis'!$M$14="Can",'4.7 Can Pasteurisation (3)'!F37,0) -> 0 | I126: =IF('1.2 Scenario Analysis'!$M$14="Can",'4.7 Can Pasteurisation (3)'!G37,0) -> 0 | J126: =H126/H$235 -> 0
C127: Total Machinery Cost | D127: =SUM(D126:D126) -> 0 | E127: =SUM(E126:E126) -> 0 | F127: =SUM(F126:F126) -> 0 | H127: =SUM(H126:H126) -> 0 | I127: =SUM(I126:I126) -> 0 | J127: =SUM(J126:J126) -> 0
C129: Utility | D129: Total Hourly Cost (€) | E129: Total Cost per MT (€/MT) | F129: Percentage of the Total Cost (%) | H129: Total Hourly Cost (€) | I129: Total Cost per MT (€/MT) | J129: Percentage of the Total Cost (%)
C130: Electricity and Natural Gas Cost | D130: =IF('1.2 Scenario Analysis'!$M$14="Can",'4.7 Can Pasteurisation (3)'!F43,0) -> 0 | E130: =IF('1.2 Scenario Analysis'!$M$14="Can",'4.7 Can Pasteurisation (3)'!G43,0) -> 0 | F130: =D130/$D$235 -> 0 | H130: =IF('1.2 Scenario Analysis'!$M$14="Can",'4.7 Can Pasteurisation (3)'!F47,0) -> 0 | I130: =IF('1.2 Scenario Analysis'!$M$14="Can",'4.7 Can Pasteurisation (3)'!G47,0) -> 0 | J130: =H130/$H$235 -> 0
...

Sheet Assumption & Analysis
E2: Light green coloured cells indicate input variables
B5: Key Details and Sources
B7: 1 | C7: The following companies have been studied to develop the should cost model for RTD Ice Tea: L'Européenne D'Embouteillage SNC (Châteauneuf-de-Gadagne, France), Vrumona (Bunnik, Netherlands), Sumol + Compsal S.A (Pombal, Portugal) RTD Ice Tea Equipment Suppliers – TetraPak, Frau Group, Krones AG, Pentair, GEA Group and Alfa Laval
C8: Product Details
B9: 2 | C9: The should cost model has been developed for RTD Ice Tea in France, Netherlands and Portugal
C10: Plant Details and Capital Investments
